Workbook

Sheet Uso de estimador
A1: Estimador de HC en base a S0
A2: Elaborado por: Javier Soto
A3: Fecha de creación: 20.08.2024
A4: Versión del documento : V01
A5: La estimación está orientada a consultoría funcional. No incluye estimación de asignación de gerente de proyecto, gerente de consultoría, arquitecto, líder ABAP, roles y perfiles. También se basa en que los consultores tienen un nivel de experiencia adecuado( > 8 años aprox.). Asímismo, se debe estimar por separado la fase deploy en base a otras variables propias del cliente. Igualmente con la fase RUN en base al acuerdo comercial de soporte que se requiera.
A6: Tipos de procesos: La estimación se basa en las diferentes actividades que se realizan en las fase del proyecto dependiedo del tipo de proceso. Tenemos definido los tipos de proceso:
A7: Estructura organizativa: Explicación de estructura organizativa. Definición de información necesaria para la EO(Anexo) Desarrollo de BPD. Configuración.
A8: Datos maestros: Explicación del dato maestros. Desarrollo de BPD. Definición de campos a configurar en dato maestros(Anexos) Inventariar estructura de carga masiva Explorar proceso de carga masiva en Migration Cockpits Soporte a los procesos de carga para pruebas. Soporte a los procesos de carga para PRD.
A9: Proceso: Explicación del proceso. Explicación del diagrama de flujo. Preparación de datos para taller de demostración. Taller de demostración en sistema. Desarrollo de BPD. Definiciones de configuraciones en Anexos. Integración con otros frentes. Revisión de Roles Definición de escenarios de negocio para pruebas. Configuración. Pruebas internas de consultoría. Documentación de consultoría. Pruebas unitarias. Pruebas integrales. CutOver para proceso. Soporte de incidencias.
A10: Reportes: Taller de demostración de reportes. Integración con otros frentes. Revisión de Roles. Creación de variantes. Navegación en SAPGUI / Fiori
A11: Grado de adopción:
A12: Asimismo, se debe indicar el grado de adopción de cada proceso para mejorar la estimación en base al QUAD-A
... A22: 04 Muy alta: Existen muchos registros, muchas variantes y está asociado a desarrollo.

Sheet Atributos
A1: SEIDOR SprintZero V1.0 | P1: Tipo | Q1: Descripción | R1: T. Descubrimiento | S1: T. Preparación Inicial | T1: T. Exploración | U1: T. Realización | V1: T. Despliegue | W1: T. Soporte
P2: DM | Q2: Explicación del dato maestros. Desarrollo de BPD. Definición de campos a configurar en dato maestros(Anexos) Inventariar estructura de carga masiva Explorar proceso de carga masiva en Migration Cockpits Soporte a los procesos de carga para pruebas. Soporte a los procesos de carga para PRD. | R2: 1 | S2: 1 | T2: 8 | U2: 8 | V2: 8 | W2: 0
P3: EO | Q3: Explicación de estructura organizativa. Definición de información necesaria para la EO(Anexo) Desarrollo de BPD. Configuración. | R3: 1 | S3: 1 | T3: 4 | U3: 4 | V3: 0 | W3: 0
A4: Revisado por: Javier Soto Castillo | I4: Line of Business | J4: Responsable | L4: Módulos | M4: RICEF | N4: Fase | P4: PR | Q4: Explicación del proceso. Explicación del diagrama de flujo. Preparación de datos para taller de demostración. Taller de demostración en sistema. Desarrollo de BPD. Definiciones de configuraciones en Anexos. Integración con otros frentes. Revisión de Roles Definición de escenarios de negocio para pruebas. Configuración. Pruebas internas de consultoría. Documentación de consultoría. Pruebas unitarias. Pruebas integrales. CutOver para proceso. Soporte de incidencias. | R4: 1 | S4: 2 | T4: =8+8 -> 16 | U4: =16+8+8 -> 32 | V4: 8 | W4: 8
I5: Manufactura | J5: Javier Soto | L5: PP | M5: Report | N5: Proyecto | P5: RE | Q5: Taller de demostración de reportes. Integración con otros frentes. Revisión de Roles. Creación de variantes. Navegación en SAPGUI / Fiori | R5: 1 | S5: 2 | T5: 4 | U5: =8+8 -> 16 | V5: 0 | W5: 8
A6: Listado de procesos: Contiene todos los procesos configurados. | I6: Gestión de activos | J6: Santiago Sánchez | L6: QM | M6: Interface | N6: Soporte
A7: Listado de RICEF: Contiene todos los RICEF creados. | I7: Finanzas | J7: Yvan Montero | L7: PM | M7: Conversion
I8: Ventas | L8: FI | M8: Enhacenment
I9: Abastecimiento y compras | J9: Luis | L9: CO | M9: Forms
I10: Cadena de suministro | L10: MM | M10: WorkFlows
L11: EWM
A12: Estado | L12: WM
A13: 00 Nuevo | L13: RE
A14: 01 Documentado | L14: PS
A15: 02 Configurado | L15: SD
A16: 03 Probado | L16: HCM
A17: 04 Terminado
A18: 99 Obsoleto
A20: MAXIMO | B20: 1.5 | G20: MINIMO
A21: Complejidad | B21: Factor | G21: Complejidad | H21: Factor
A22: 01 Baja | B22: =+H22*$B$20 -> 1.5 | G22: 01 Baja | H22: 1
A23: 02 Media | B23: =+H23*$B$20 -> 2.25 | G23: 02 Media | H23: 1.5
A24: 03 Alta | B24: =+H24*$B$20 -> 3 | G24: 03 Alta | H24: 2
A25: 04 Muy Alta | B25: =+H25*$B$20 -> 4.5 | G25: 04 Muy Alta | H25: 3
A27: QUAD-A
A28: 01 Adoptar | B28: 1 | E28: 1
A29: 02 Ajustar | B29: 1.5 | E29: 1.5 | I29: =1.5*1.5 -> 2.25
A30: 03 Agregar | B30: 2.5 | E30: 2.5 | I30: =3*1.5 -> 4.5
A31: 04 Abstener | B31: 0 | E31: 0
A33: #Registros
A34: 01 < 0 : 100 > | B34: 2
A35: 02 <100 : 1K > | B35: 3
A36: 03 <1K : 10K > | B36: 4
A37: 04 <10K : 100K > | B37: 6
A38: #Usuarios
A39: 01 <1 : 10 > | B39: 2
A40: 02 <10 : 25 > | B40: 3
A41: 03 <25 : 60 > | B41: 4
A42: 04 <60 : 100> | B42: 5
A43: 05 <100 : 200> | B43: 6
A45: RICEFW
A46: 01 Reporte
A47: 02 Interface
A48: 03 Conversión
A49: 04 Mejora
A50: 05 Formulario
A51: 06 Workflow
A52: 07 BTP
A54: Prioridad
A55: 01 Listo para PI
A56: 02 Listo para Go-live
A57: 03 Listo para 1er Cierre M.
... A66: 05 Muy Alta

Sheet S0
A1: Línea de negocio | B1: Área de negocio | C1: Proceso de negocio | D1: SAP S/4HANA BP | E1: Actividades | F1: Descripción | G1: Variantes | H1: Exclusiones | I1: Mód. | J1: BC_SET_S0 | K1: BC_SET_S0 - Prerequisito | L1: Observaciones | M1: Fase | N1: Anexo BPD | O1: Estructuras de carga masiva | P1: Estado | Q1: TA | R1: Complejidad | S1: TP | T1: Discovery | U1: Prepare | V1: Explore | W1: Realize | X1: Deploy | Y1: Run
A2: Finanzas | B2: EO | C2: CO-00_Estructura organizativa(CO_EO1) | E2: Sociedad CO. Sociedad PA. Jerarquía de Centros de Beneficio Jerarquía de Centros de Costos | F2: En la estructura SAP representa la vista jurídica u organizativa de una empresa como los niveles de la organización. La misma que, corresponde a un requisito esencial tanto para los datos maestros; como para definir, los procesos esenciales. A través de los objetos de costo en dicha estructura; posteriormente, se realizaran las contabilizaciones en las cuentas de ingresos y gastos. | H2: * No se puede cambiar la moneda CO ni PA luego de tener movimientos | I2: CO | J2: YS0_S4HANA_EO_001 YS0_S4HANA_EO_C001 | M2: 1 | P2: 04 Terminado | R2: 1 | S2: EO | T2: =+VLOOKUP(S2,Atributos!$P$2:$W$5,3)*R2 -> 1 | U2: =+VLOOKUP(S2,Atributos!$P$2:$W$5,4)*R2 -> 1 | V2: =+VLOOKUP(S2,Atributos!$P$2:$W$5,5)*R2 -> 4 | W2: =+VLOOKUP(S2,Atributos!$P$2:$W$5,6)*R2 -> 4 | X2: =+VLOOKUP(S2,Atributos!$P$2:$W$5,7)*R2 -> 0 | Y2: =+VLOOKUP(S2,Atributos!$P$2:$W$5,8)*R2 -> 0
A3: Finanzas | B3: Gestión de datos maestros | C3: CO-01_Administración de datos maestros de Controlling(CO_M010) | D3: J58-00_J58-02 | E3: Gestión de Centros de Beneficio. Gestión de Centros de Costos. Gestión de clases de costo. Gestión de valores estadísticos. Gestión de órdenes internas. | F3: Corresponden a los datos que contienen información relevante para los procesos de la empresa y se encuentran almacenados de forma centralizada, para evitar redundancias y son empleadas por las diversas aplicaciones. En la contabilidad de costos tenemos: - Centro de beneficio: Es una unidad organizativa de finanzas que refleja una estructura de la empresa orientada hacia la gestión. Se pueden analizar los resultados operativos con la vinculación a las cuentas de resultado. - Centro de Costos: Es una unidad organizativa de controlling que representa una ubicación delimitada donde se generan los costes. - Gestión de clases de costo: Este maestro comprenden a las cuentas de resultado que tienen injerencia en la contabilidad de costos interna y que se requieren, para realizar los procesos en controlling. - Los valores estadísticos representan los drivers o inductores para distribuir los gastos. - Órdenes internas: Son colectores de costos que permiten acumular costos de eventos específicos, campañas, inversiones, etc. | G3: * Crear varios tipos de Ordenes Internas | H3: * La data maestra luego de tener movimiento no puede ser eliminada | I3: CO | J3: YS0_S4HANA_EO_001 YS0_S4HANA_EO_C001 | M3: 1 | N3: ANEXO_CO01 - Área Funcional ANEXO_CO02 - Segmento | P3: 04 Terminado | R3: 1 | S3: DM | T3: =+VLOOKUP(S3,Atributos!$P$2:$W$5,3)*R3 -> 1 | U3: =+VLOOKUP(S3,Atributos!$P$2:$W$5,4)*R3 -> 1 | V3: =+VLOOKUP(S3,Atributos!$P$2:$W$5,5)*R3 -> 8 | W3: =+VLOOKUP(S3,Atributos!$P$2:$W$5,6)*R3 -> 8 | X3: =+VLOOKUP(S3,Atributos!$P$2:$W$5,7)*R3 -> 8 | Y3: =+VLOOKUP(S3,Atributos!$P$2:$W$5,8)*R3 -> 0
A4: Finanzas | B4: Costos | C4: CO-02_Planificación de Ingresos, costos y gastos(CO_P010) | D4: 1HB | E4: Planificación de ingresos, costos y gastos, por centro de beneficio y centro de costos. Planificación de órdenes internas. | F4: Controlling permite planificar la estructura de costos y gastos de las futuras operaciones de la empresa para períodos determinados y efectuar comparaciones Real / Plan para su control. | G4: * Cargar diferentes Versione de planificación * Copiar de Real a Versión Plan * Copiar de Vérsión Plan a Versión Plan | H4: * El cálculo de planificación es por fuera de SAP * La planificación no es restrictiva solo informativa * Se puede planificar a nivel de ceco + clase de coste | I4: CO | J4: YS0_S4HANA_EO_001 YS0_S4HANA_EO_C001 | L4: Faltan roles. | M4: 1 | P4: 04 Terminado | R4: 1 | S4: PR | T4: =+VLOOKUP(S4,Atributos!$P$2:$W$5,3)*R4 -> 1 | U4: =+VLOOKUP(S4,Atributos!$P$2:$W$5,4)*R4 -> 2 | V4: =+VLOOKUP(S4,Atributos!$P$2:$W$5,5)*R4 -> 16 | W4: =+VLOOKUP(S4,Atributos!$P$2:$W$5,6)*R4 -> 32 | X4: =+VLOOKUP(S4,Atributos!$P$2:$W$5,7)*R4 -> 8 | Y4: =+VLOOKUP(S4,Atributos!$P$2:$W$5,8)*R4 -> 8
A5: Finanzas | B5: Costos | C5: CO-03_Control de Ingresos, costos y gastos(CO_P020) | D5: J54 | E5: Imputación real a cuentas de ingresos, costos y gastos. Gestión de órdenes internas de gastos y de inversión. Creación de ciclos de distribución y de subreparto. | F5: Comprende los distintos procesos por los cuales se registran imputaciones reales en las cuentas contables de costos, gastos, ingresos e inversión, ya sea por medio de centros de costos, centros de beneficio u órdenes internas. La ordenes internas son objetos de costos que se usan para identificar operaciones específicas y temporales con el fin de facilitar un análisis. Estas se aplican para controlar proyectos, campañas, obras en curso, etc. Los ciclos de distribución y/o subreparto sirven para distribuir o trasladar los costos de objetos de costos origen a objetos de costos destino. El ciclo de distribución traslada a través de la misma clase de costo, mientras el subreparto requiere de la clase de coste secundaria. | G5: * Imputaciones a cecos * Imputaciones a diferentes clase de Ordenes ( Inversión, reales , estadisticas) * Ciclos de distribución con diferentes metodos ( % , VE, Importe Fijo , etc) * Ciclos de Subreparto diferentes métodos ( % , VE , importe Fijo , Etc) | H5: * Los Drivers de los ciclos de distribución y subreparto no son automaticos ; si se define que el valor es mensual entonces se debe actualizar . * Todo objeto de costo con movimiento no puede ser eliminado. | I5: CO | J5: YS0_S4HANA_EO_001 YS0_S4HANA_EO_C001 | L5: Faltan roles. | M5: 1 | P5: 04 Terminado | R5: 1 | S5: PR | T5: =+VLOOKUP(S5,Atributos!$P$2:$W$5,3)*R5 -> 1 | U5: =+VLOOKUP(S5,Atributos!$P$2:$W$5,4)*R5 -> 2 | V5: =+VLOOKUP(S5,Atributos!$P$2:$W$5,5)*R5 -> 16 | W5: =+VLOOKUP(S5,Atributos!$P$2:$W$5,6)*R5 -> 32 | X5: =+VLOOKUP(S5,Atributos!$P$2:$W$5,7)*R5 -> 8 | Y5: =+VLOOKUP(S5,Atributos!$P$2:$W$5,8)*R5 -> 8
A6: Finanzas | B6: Costos | C6: CO-04_Análisis de Rentabilidad(CO_P040) | D6: J55 | E6: Definición características CO-PA. Subreparto de gastos. | F6: Es una herramienta que brinda SAP, para ayudar a las empresas a evaluar su rentabilidad mediante sus segmentos de mercado a partir de sus ventas, ganancias/pérdidas e información proveniente de otros módulos como finanzas, ventas y logística. Se tienen características como canal de ventas, línea de negocio, oficina de ventas, cliente, material, etc. dicha información puede ser analizada por periodos, ejercicio. | G6: * COPA - Análitico * COPA - Contable * Agregar caracteristicas Z* * Agregar caracteristicas despues de la activación de COPA * Ciclos de Subreparto de PA * Ejecución del TOP- DOW | H6: * COPA - Análitico ; existe la posibilidad que no cuadre exacto con la contabilidad ya que se usa para gestión * Los drivers del ciclo de subreparto no son automaticos . | I6: CO | J6: YS0_S4HANA_EO_001 YS0_S4HANA_EO_C001 | L6: Faltan roles. No hay flujo | M6: 1 | P6: 04 Terminado | R6: 1 | S6: PR | T6: =+VLOOKUP(S6,Atributos!$P$2:$W$5,3)*R6 -> 1 | U6: =+VLOOKUP(S6,Atributos!$P$2:$W$5,4)*R6 -> 2 | V6: =+VLOOKUP(S6,Atributos!$P$2:$W$5,5)*R6 -> 16 | W6: =+VLOOKUP(S6,Atributos!$P$2:$W$5,6)*R6 -> 32 | X6: =+VLOOKUP(S6,Atributos!$P$2:$W$5,7)*R6 -> 8 | Y6: =+VLOOKUP(S6,Atributos!$P$2:$W$5,8)*R6 -> 8
A7: Finanzas | B7: Costos | C7: CO-05_Reportes de Análisis(CO_P050) | D7: 4RC | E7: Reportes de Rentabilidad. Elaboración de reportes de gestión. Elaboración de estados financieros internos. | F7: Se refiere a los reportes de gastos por centros de costos, reportes de márgenes (por sociedad, unidad de negocio, etc.) y de estados financieros internos, por medio de la herramienta Report Painter. | H7: * Los reportes son Report Writer no se pueden transformar en ALV | I7: CO | J7: YS0_S4HANA_EO_001 YS0_S4HANA_EO_C001 | L7: Faltan roles. No hay flujo | M7: 1 | P7: 04 Terminado | R7: 1 | S7: RE | T7: =+VLOOKUP(S7,Atributos!$P$2:$W$5,3)*R7 -> 1 | U7: =+VLOOKUP(S7,Atributos!$P$2:$W$5,4)*R7 -> 2 | V7: =+VLOOKUP(S7,Atributos!$P$2:$W$5,5)*R7 -> 4 | W7: =+VLOOKUP(S7,Atributos!$P$2:$W$5,6)*R7 -> 16 | X7: =+VLOOKUP(S7,Atributos!$P$2:$W$5,7)*R7 -> 0 | Y7: =+VLOOKUP(S7,Atributos!$P$2:$W$5,8)*R7 -> 8
A8: Finanzas | B8: Cierre contable y financiero | C8: CO-06_Cierre de Controlling(CO_P060) | D8: J54 / BEV | E8: Análisis de ingresos en centros de beneficio. Análisis de costos y gastos en centros de costo y órdenes. Liquidación de ordenes internas. Ejecución de Distribución / Subreparto de gasto. | F8: En el cierre de Controlling, se tienen los siguientes eventos: - Análisis de ingresos en centros de beneficio: El proceso de análisis de los ingresos debe ser periodico durante el mes. - Análisis de costos y gastos en centros de costo y órdenes: El proceso de análisis de los costos y gastos deben ser periodicos durante el mes. - Liquidación de las ordenes internas: Las ordenes son acumuladores de gasto temporales por lo que en el cierre del periodo se debe realizar el proceso de liquidación con el objetivo que queden en cero. - Ejecución de distribución / subreparto de gasto: Este proceso comprende a las distribuciones de gastos operativos entre las unidades de negocio o según el modelo/criterio que determine la empresa. | I8: CO | J8: YS0_S4HANA_EO_001 YS0_S4HANA_EO_C001 | L8: Faltan roles. No hay flujo | M8: 1 | P8: 04 Terminado | R8: 1 | S8: PR | T8: =+VLOOKUP(S8,Atributos!$P$2:$W$5,3)*R8 -> 1 | U8: =+VLOOKUP(S8,Atributos!$P$2:$W$5,4)*R8 -> 2 | V8: =+VLOOKUP(S8,Atributos!$P$2:$W$5,5)*R8 -> 16 | W8: =+VLOOKUP(S8,Atributos!$P$2:$W$5,6)*R8 -> 32 | X8: =+VLOOKUP(S8,Atributos!$P$2:$W$5,7)*R8 -> 8 | Y8: =+VLOOKUP(S8,Atributos!$P$2:$W$5,8)*R8 -> 8
A9: Finanzas | B9: Costos | C9: CO-07_Costos de producción(CO_P030) | I9: CO | J9: YS0_S4HANA_EO_001 YS0_S4HANA_EO_C001 | M9: 2 | P9: 04 Terminado | R9: 1 | S9: PR | T9: =+VLOOKUP(S9,Atributos!$P$2:$W$5,3)*R9 -> 1 | U9: =+VLOOKUP(S9,Atributos!$P$2:$W$5,4)*R9 -> 2 | V9: =+VLOOKUP(S9,Atributos!$P$2:$W$5,5)*R9 -> 16 | W9: =+VLOOKUP(S9,Atributos!$P$2:$W$5,6)*R9 -> 32 | X9: =+VLOOKUP(S9,Atributos!$P$2:$W$5,7)*R9 -> 8 | Y9: =+VLOOKUP(S9,Atributos!$P$2:$W$5,8)*R9 -> 8
A10: Cadena de suministro | B10: EO | C10: EWM-00_Estructura organizativa(EWM_EO1) | E10: Número de almacén Tipos de almacén Áreas de almacenamiento | F10: Se detallan los niveles en los que se subdivide centro de distribución | I10: EWM | M10: 2 | P10: 04 Terminado | R10: 1 | S10: EO | T10: =+VLOOKUP(S10,Atributos!$P$2:$W$5,3)*R10 -> 1 | U10: =+VLOOKUP(S10,Atributos!$P$2:$W$5,4)*R10 -> 1 | V10: =+VLOOKUP(S10,Atributos!$P$2:$W$5,5)*R10 -> 4 | W10: =+VLOOKUP(S10,Atributos!$P$2:$W$5,6)*R10 -> 4 | X10: =+VLOOKUP(S10,Atributos!$P$2:$W$5,7)*R10 -> 0 | Y10: =+VLOOKUP(S10,Atributos!$P$2:$W$5,8)*R10 -> 0
A11: Cadena de suministro | B11: Gestión de datos maestros | C11: EWM-01_Administración de Datos Maestros(EWM_M010) | E11: Ampliación de materiales: Indicadores de tipo de almacén Indicadores de área de almacenamiento | F11: Se actualiza la información del material para colocarle los indicadores correspondientes a ingreso y salida. | I11: EWM | M11: 2 | P11: 04 Terminado | R11: 1 | S11: DM | T11: =+VLOOKUP(S11,Atributos!$P$2:$W$5,3)*R11 -> 1 | U11: =+VLOOKUP(S11,Atributos!$P$2:$W$5,4)*R11 -> 1 | V11: =+VLOOKUP(S11,Atributos!$P$2:$W$5,5)*R11 -> 8 | W11: =+VLOOKUP(S11,Atributos!$P$2:$W$5,6)*R11 -> 8 | X11: =+VLOOKUP(S11,Atributos!$P$2:$W$5,7)*R11 -> 8 | Y11: =+VLOOKUP(S11,Atributos!$P$2:$W$5,8)*R11 -> 0
A12: Cadena de suministro | B12: Almacenamianto | C12: EWM-02_Procesos de entrada (EWM_P010) | D12: 1FS | E12: Orden de compra o ingreso directo: Generación de la entrega entrante Modificación de la entrega/contabilización Creación de la orden de almacén Confirmación de de la orden | F12: El proceso de ingreso permite brindar soporte a las actividades ejecutadas desde la recepción de la mercadería hasta la colocación de los materiales en la ubicación final | G12: - Ingreso por compra - Ingreso directo sin pedido - Ingreso por traslado | I12: EWM | M12: 2 | P12: 04 Terminado | R12: 1 | S12: PR | T12: =+VLOOKUP(S12,Atributos!$P$2:$W$5,3)*R12 -> 1 | U12: =+VLOOKUP(S12,Atributos!$P$2:$W$5,4)*R12 -> 2 | V12: =+VLOOKUP(S12,Atributos!$P$2:$W$5,5)*R12 -> 16 | W12: =+VLOOKUP(S12,Atributos!$P$2:$W$5,6)*R12 -> 32 | X12: =+VLOOKUP(S12,Atributos!$P$2:$W$5,7)*R12 -> 8 | Y12: =+VLOOKUP(S12,Atributos!$P$2:$W$5,8)*R12 -> 8
A13: Cadena de suministro | B13: Almacenamianto | C13: EWM-03_Procesos de salida (EWM_P020) | D13: 1G2 | E13: Pedido de venta o salida directa: Generación de la entrega de salida Creación de la orden de almacén Confirmación de de la orden Contabilización de la entrega de salida | F13: El proceso de salida permite brindar soporte a las actividades ejecutadas desde la extracción de la recepción de la mercadería hasta la colocación de los materiales en la ubicación final | G13: -Salida por venta -Salida por consumo directo -Salida por traslado | I13: EWM | M13: 2 | P13: 04 Terminado | R13: 1 | S13: PR | T13: =+VLOOKUP(S13,Atributos!$P$2:$W$5,3)*R13 -> 1 | U13: =+VLOOKUP(S13,Atributos!$P$2:$W$5,4)*R13 -> 2 | V13: =+VLOOKUP(S13,Atributos!$P$2:$W$5,5)*R13 -> 16 | W13: =+VLOOKUP(S13,Atributos!$P$2:$W$5,6)*R13 -> 32 | X13: =+VLOOKUP(S13,Atributos!$P$2:$W$5,7)*R13 -> 8 | Y13: =+VLOOKUP(S13,Atributos!$P$2:$W$5,8)*R13 -> 8
A14: Cadena de suministro | B14: Almacenamianto | C14: EWM-04_Procesos internos (EWM_P030) | D14: 1V5 | E14: Cambio de ubicación individual Cambio de ubicaión masivo Cambio de tipo de stock | F14: Los procesos dentro del almacén pueden ser mapeados a detalle en el sistema para reflejar los cambios de ubicación y/o tipos de stock | G14: -Cambio de ubicación individual -Cambio de ubicación masivo -Cambio de tipo de stock | I14: EWM | M14: 2 | P14: 04 Terminado | R14: 1 | S14: PR | T14: =+VLOOKUP(S14,Atributos!$P$2:$W$5,3)*R14 -> 1 | U14: =+VLOOKUP(S14,Atributos!$P$2:$W$5,4)*R14 -> 2 | V14: =+VLOOKUP(S14,Atributos!$P$2:$W$5,5)*R14 -> 16 | W14: =+VLOOKUP(S14,Atributos!$P$2:$W$5,6)*R14 -> 32 | X14: =+VLOOKUP(S14,Atributos!$P$2:$W$5,7)*R14 -> 8 | Y14: =+VLOOKUP(S14,Atributos!$P$2:$W$5,8)*R14 -> 8
A15: Cadena de suministro | B15: Almacenamianto | C15: EWM-05_Inventario (EWM_P040) | D15: 1V7 | E15: Toma de inventario por material Toma de inventario por ubicación | F15: Proceso de conteo de materiales y/o ubicaciones con mayor precisión | G15: -Toma de inventario por material sin diferencia -Tomoa de inventario por ubicación con diferencia | I15: EWM | M15: 2 | P15: 04 Terminado | R15: 1 | S15: PR | T15: =+VLOOKUP(S15,Atributos!$P$2:$W$5,3)*R15 -> 1 | U15: =+VLOOKUP(S15,Atributos!$P$2:$W$5,4)*R15 -> 2 | V15: =+VLOOKUP(S15,Atributos!$P$2:$W$5,5)*R15 -> 16 | W15: =+VLOOKUP(S15,Atributos!$P$2:$W$5,6)*R15 -> 32 | X15: =+VLOOKUP(S15,Atributos!$P$2:$W$5,7)*R15 -> 8 | Y15: =+VLOOKUP(S15,Atributos!$P$2:$W$5,8)*R15 -> 8
A16: Finanzas | B16: EO | C16: FI-00_Estructura Organizativa(FI_EO1) | E16: Sociedad FI Variante de ejercicio Variante de periodos Plan de cuentas Clase de cuentas Definición de monedas Clases de documentos Claves de contabilización Documento financiero Tipo de cambio Ledgers paralelos Sociedad GL | F16: La estructura organizativa representa la vista jurídica u organizativa de la empresa y corresponde a un requisito esencial tanto para la determinación de los datos maestros, como para los procesos a definir en la empresa. Asi mismo, abarca la definción de conceptos escenciales para dar soporte a los procesos contables. Por ejemplo, conceptos como: las Clases de documento, variante de ejercicio, variante de periodos, Claves de contabiización y otros. | G16: - Las Sociedades FI pueden estar sujetas a alguna caracteristicas desde su creación por ejemplo: a) Plan de Cuentas Operativo y Plan de Cuentas País ( Se define en Base a la Sociedad Matriz o Grupo ) | H16: "Revalorización en modena extranjera" Caso que se generea ingreso o gasto que de manera automática se imputa a un cebe o ceco. | I16: FI | J16: YS0_S4HANA_EO_001 YS0_S4HANA_EO_C001 | M16: 1 | N16: ANEXO_FI01 - Clases de documentos | P16: 04 Terminado | R16: 1 | S16: EO | T16: =+VLOOKUP(S16,Atributos!$P$2:$W$5,3)*R16 -> 1 | U16: =+VLOOKUP(S16,Atributos!$P$2:$W$5,4)*R16 -> 1 | V16: =+VLOOKUP(S16,Atributos!$P$2:$W$5,5)*R16 -> 4 | W16: =+VLOOKUP(S16,Atributos!$P$2:$W$5,6)*R16 -> 4 | X16: =+VLOOKUP(S16,Atributos!$P$2:$W$5,7)*R16 -> 0 | Y16: =+VLOOKUP(S16,Atributos!$P$2:$W$5,8)*R16 -> 0
A17: Finanzas | B17: Gestión de datos maestros | C17: FI-01_Maestro de Contabilidad General(FI_M010) | D17: J58-01 | E17: Plan de cuentas Operativo -Segmento de Plan de Cuentas -Segmento de Sociedad Reportes | F17: El maestro del Plan de Cuentas, agrupa la totalidad de las cuentas de mayor de la organización. En SAP, una sociedad puede gestionar tres planes de cuentas: - Plan de cuentas operativo (es indispensable). - Plan de cuentas de grupo. - Plan de cuentas del país | G17: 1) Manejar en la Sociedad solo con el Plan Contable Operativo ( ejemplo :PCGE ) 2) Manejar en la Sociedad Plan Contable Operativo y Alternativo ( ejemplo : CAPE (Opeativo ) y Alternativo PCGE ( Local ) 3) Opcional manejar Plan de Cuenta Grupo | I17: FI | J17: YS0_S4HANA_EO_001 YS0_S4HANA_EO_C001 | L17: Faltan app y roles | M17: 1 | O17: MC_FI_M010 - Plan de cuentas | P17: 04 Terminado | R17: 1 | S17: DM | T17: =+VLOOKUP(S17,Atributos!$P$2:$W$5,3)*R17 -> 1 | U17: =+VLOOKUP(S17,Atributos!$P$2:$W$5,4)*R17 -> 1 | V17: =+VLOOKUP(S17,Atributos!$P$2:$W$5,5)*R17 -> 8 | W17: =+VLOOKUP(S17,Atributos!$P$2:$W$5,6)*R17 -> 8 | X17: =+VLOOKUP(S17,Atributos!$P$2:$W$5,7)*R17 -> 8 | Y17: =+VLOOKUP(S17,Atributos!$P$2:$W$5,8)*R17 -> 0
A18: Finanzas | B18: Gestión de datos maestros | C18: FI-02_Maestro de Activos Fijos(FI_M020) | D18: J62-01 | E18: Maestro de Activos Fijos | F18: El maestro de activos fijos centraliza la administración de los activos fijos mediante la creación y mantenimiento de códigos únicos de AF. Bajos los cuales se contabilizan las altas, bajas, traslados, depreciación u otras operaciones. Los códigos de activos fijos dan soporte a los procesos de activos fijos y permite un análisis contable por código de activo. | G18: 1) Manejar diferentes Areas de Valoración para su tratamiento Contable,Tributario o de Revaluaciones 2) Manejar diferentes tipos de Clave de Amortización : Ejemplo Lineal o por Unidades Producidas. 3) Llevar el control de las Altas, Bajas y traspasos de las diferentes clases de activos dependiendo de sus Vida Utiles | I18: FI | J18: YS0_S4HANA_FIAA_001 | K18: YS0_S4HANA_EO_001 YS0_S4HANA_EO_C001 | L18: Faltan app y roles | M18: 1 | N18: ANEXO_FI06 - Clases de Activos Fijos | O18: MC_FI_M020 - Maestro de Activos Fijos | P18: 04 Terminado | R18: 1 | S18: DM | T18: =+VLOOKUP(S18,Atributos!$P$2:$W$5,3)*R18 -> 1 | U18: =+VLOOKUP(S18,Atributos!$P$2:$W$5,4)*R18 -> 1 | V18: =+VLOOKUP(S18,Atributos!$P$2:$W$5,5)*R18 -> 8 | W18: =+VLOOKUP(S18,Atributos!$P$2:$W$5,6)*R18 -> 8 | X18: =+VLOOKUP(S18,Atributos!$P$2:$W$5,7)*R18 -> 8 | Y18: =+VLOOKUP(S18,Atributos!$P$2:$W$5,8)*R18 -> 0
A19: Finanzas | B19: Gestión de tesorería | C19: FI-03_Maestro de bancos(FI_M030) | D19: BFA | E19: Maestro de Bancos Bancos propios Cuentas bancarias | F19: Con la gestión de cuentas bancarias el área de tesorería puede centralizar la gestión de cuentas bancarias utilizando los datos maestros de cuentas bancarias. | G19: 1) Crear Bancos País 2) Crear Bancos Propios 3) Crear Cuentas Bancarias de Bancos Propios. | I19: FI | J19: YS0_S4HANA_EO_001 YS0_S4HANA_EO_C001 | L19: Faltan app y roles | M19: 1 | N19: ANEXO_FI07 - Bancos propios y cuentas bancarias ANEXO_FI09 - Claves de bancos | O19: MC_FI_M030 - Maestro de bancos | P19: 04 Terminado | R19: 1 | S19: DM | T19: =+VLOOKUP(S19,Atributos!$P$2:$W$5,3)*R19 -> 1 | U19: =+VLOOKUP(S19,Atributos!$P$2:$W$5,4)*R19 -> 1 | V19: =+VLOOKUP(S19,Atributos!$P$2:$W$5,5)*R19 -> 8 | W19: =+VLOOKUP(S19,Atributos!$P$2:$W$5,6)*R19 -> 8 | X19: =+VLOOKUP(S19,Atributos!$P$2:$W$5,7)*R19 -> 8 | Y19: =+VLOOKUP(S19,Atributos!$P$2:$W$5,8)*R19 -> 0
A20: Finanzas | B20: Contabilidad | C20: FI-04_Contabilidad General(FI_P010) | D20: J58-03 J58-04 | E20: Registro de Asientos de Diario Registro de Asientos de provisiones Asientos periódicos Anulación de registros Desglose de documentos Reportes | F20: En SAP S/4HANA este proceso proporciona soporte a la gestión de la información financiera referida a la evaluación y generación de los reportes de resultados y de cuentas de balance. Por lo que, permite la emisión de documentos de contabilidad general, como asientos diarios o asientos periódicos. | G20: 1) Provisiones y Extornos ( Afectos o Inafectos ) 2) Reclasificaciones 2) Asientos Periodicos por concepto de Alquileres 3) Anulaciones de documentos. | I20: FI | J20: YS0_S4HANA_EO_001 YS0_S4HANA_EO_C001 | M20: 1 | P20: 04 Terminado | R20: 1 | S20: PR | T20: =+VLOOKUP(S20,Atributos!$P$2:$W$5,3)*R20 -> 1 | U20: =+VLOOKUP(S20,Atributos!$P$2:$W$5,4)*R20 -> 2 | V20: =+VLOOKUP(S20,Atributos!$P$2:$W$5,5)*R20 -> 16 | W20: =+VLOOKUP(S20,Atributos!$P$2:$W$5,6)*R20 -> 32 | X20: =+VLOOKUP(S20,Atributos!$P$2:$W$5,7)*R20 -> 8 | Y20: =+VLOOKUP(S20,Atributos!$P$2:$W$5,8)*R20 -> 8
A21: Finanzas | B21: Operaciones financieras | C21: FI-05_Cuentas por Pagar(FI_P020) | D21: J60 | E21: Maestro de Interlocutor Comercial (Acreedores o Proveedores) Registro de Facturas y otros Comprobantes de Proveedor - Registro de Comprobantes por Finanzas (FI) - Registro de Comprobantes Con Orden de Compra (MM) Indicadores de impuestos Compras Percepciones por compra Registro de Comprobantes de Importación de bienes Registro de IGV no domiciliado Solicitudes de Anticipo Acreedor Retenciones en la factura - Detracciones de IGV - Retenciones no Domiciliados - Retenciones dietas Retenciones en el pago - Retenciones de IGV - Retenciones de 4ta categoría Anulación de Registro Registros preliminares Cuenta de mayor especial (CME) Compensaciones - Con anticipos - Con N/D y N/C - Canje de letras - Factura Negociable o Factoring o Compensación Deudor/Acreedor o Anulación de compensación Reportes | F21: El proceso de cuentas por pagar comprende básicamente la contabilidad en acreedores producto de las operaciones de adquisición de bienes o servicios que generen una obligación de pago. Los acreedores cuentan con un código único en el maestro de Business Partner bajo el cual se registran sus operaciones y permiten el análisis auxiliar por cuenta acreedora. Así mismo se contabilizan facturas y abonos, se registran pagos y anticipos, se gestionan los valores entregados como medios de pago y al contabilizar datos en acreedores, el sistema crea un documento contable y transfiere los datos introducidos al libro mayor y según corresponda al Libro de Compras. | G21: 1) Registro de Comprobantes por Finanzas ( Todos los documentos SUNAT ) 2) Registro de Comprobantes usando los diferentes tipos de Indicadores de Impuestos. 3) Registro de FActura de No Domiciliado , Provisión IGV No Domiciliado y Extorno provisión IGV 4) Registro de Formulario de Declaración - pago o Boleta de pago de tributos Internos 5) Generar Solicitudes de Anticipo y su respectiva Contabilización. 6) Anulaciones de Registros o Comprobantes 7) Creación de documentos preliminares antes de su contabilización 8) Redireccionamiento de Cuentas a través del uso del CME 9) Compensaciones Parciales o Totales de la cuentas por pagar. Letras, Factura Negociable y Facttoring 10) Compensaciones entre Deudores(CXC) y Acreedores ( CXP) 11) Descompesación de documentos de pago | H21: Los indicadores de impuestos están asociado al IGV. No está considerado otro tipo de impuesto como ISC, impuestos especiales de sectores industriales, FISE, Rodamiento, impuestos a los plásticos, etc | I21: FI | J21: YS0_S4HANA_EO_001 YS0_S4HANA_EO_C001 | M21: 1 | N21: ANEXO_FI05 - CME ANEXO_FI10 - Retenciones | P21: 04 Terminado | R21: 1 | S21: PR | T21: =+VLOOKUP(S21,Atributos!$P$2:$W$5,3)*R21 -> 1 | U21: =+VLOOKUP(S21,Atributos!$P$2:$W$5,4)*R21 -> 2 | V21: =+VLOOKUP(S21,Atributos!$P$2:$W$5,5)*R21 -> 16 | W21: =+VLOOKUP(S21,Atributos!$P$2:$W$5,6)*R21 -> 32 | X21: =+VLOOKUP(S21,Atributos!$P$2:$W$5,7)*R21 -> 8 | Y21: =+VLOOKUP(S21,Atributos!$P$2:$W$5,8)*R21 -> 8
A22: Finanzas | B22: Operaciones financieras | C22: FI-06_Otras Cuentas por Pagar(FI_P021) | D22: J60 | E22: Registro de otras Cuentas por Pagar (Prestamos con terceros o vinculadas, Pagares, Financiamientos, Cuotas de Leasing) Impuestos Caja Chica - Constitución de Caja Chica por medio de anticipo. - Registro de Facturas y otros Comprobantes de Proveedor - Liquidación de documentos - Reposición de Caja Chica Entregas a Rendir - Solicitud (anticipo) - Registro de Salidas a Rendir (Pago a colaborador) - Registro de facturas - Liquidación de Gastos Desembolsos - Registro de facturas por pagar - Compensación de facturas por pagar contra cuenta por pagar al trabajador - Reposición al trabajador Tarjetas de crédito empresariales - Registro de facturas por pagar - Compensación de comprobantes de pago contra cuenta de tarjetas de crédito - Registro de cuenta tarjetas de crédito contra cuenta bancos Reportes | F22: El proceso de Otras cuentas por pagar abarca el registro en acreedores de operaciones no core de negocio. Tales como financiamientos, impuestos, entredas a rendir, caja chica. | G22: 1) Generar documentos por Préstamos a Terceros o Vinculadas 2) Generar documentos por Obligaciones Bancarias ( Pagarés ); incluyendo sus amortizaciones y cancelaciones 3) Generar documentos por Financiamientos con Bancos; incluyendo sus amortizaciones y cancelaciones. 4) Registros de Cuotas de Leasing ( Devengamiento incluyendo Intereses ). 5) Registar los impuestos por Pagar ( IGV) contra la SUNAT. 6) Registro, liquidación y reposición Caja Chica 7) Permite registrar Solicitud de Entregas a Rendir, registros de comprobantes y liquidación. 8) Registrar Desembolsos a Empleados por gestionar compras menores a nombre de la Empresa. Registrar comprobante y reposición del dinero al Empleado. 9) Permitir liquidaciones de tarjetas de crédito empresarial contra los comprobantes incurridos. | H22: Los indicadores de impuestos están asociado al IGV. No está considerado otro tipo de impuesto como ISC, impuestos especiales de sectores industriales, FISE, Rodamiento, impuestos a los plásticos, etc | I22: FI | J22: YS0_S4HANA_EO_001 YS0_S4HANA_EO_C001 | M22: 1 | N22: ANEXO_FI05 - CME | P22: 04 Terminado | R22: 1 | S22: PR | T22: =+VLOOKUP(S22,Atributos!$P$2:$W$5,3)*R22 -> 1 | U22: =+VLOOKUP(S22,Atributos!$P$2:$W$5,4)*R22 -> 2 | V22: =+VLOOKUP(S22,Atributos!$P$2:$W$5,5)*R22 -> 16 | W22: =+VLOOKUP(S22,Atributos!$P$2:$W$5,6)*R22 -> 32 | X22: =+VLOOKUP(S22,Atributos!$P$2:$W$5,7)*R22 -> 8 | Y22: =+VLOOKUP(S22,Atributos!$P$2:$W$5,8)*R22 -> 8
A23: Finanzas | B23: Contabilidad | C23: FI-07_Pago a Proveedores(FI_P022) | D23: J60-05 J60-06 | E23: Anticipo a Proveedores Pago Individuales y Masivos - Con nota de crédito (aplicación) - Con Cheque - Con Transferencia Electrónica - Pagos Interbancarios Pago de Planillas de RRHH Pagos Parciales Retenciones en el pago Anulación de pagos Vías de pago Bloqueos de pago Condición de pago Reportes | F23: El proceso de pago a proveedores abarca los diferentes mecanismos y condiciones que el modulo FI ofrece para contabilzar los pagos sobre los registros previamente generados en el proceso de cuentas por pagar. | G23: 1) Generar Solicitudes de Anticipos para la Caja Chica, Entregas a Rendir y Anticipos a Terceros 2) Pagos Individuales o Masivos a Proveedores. Aplicando pagos parciales o totales. 3) Registrar documentos que estan sujetos a Retenciones sea en el documento o en el Pago ( Localización ) 4) Registrar las anulaciones de las compensaciones por los documentos de pago. | I23: FI | J23: YS0_S4HANA_EO_001 YS0_S4HANA_EO_C001 | M23: 1 | N23: ANEXO_FI08 - Condiciones de pago | P23: 04 Terminado | R23: 1 | S23: PR | T23: =+VLOOKUP(S23,Atributos!$P$2:$W$5,3)*R23 -> 1 | U23: =+VLOOKUP(S23,Atributos!$P$2:$W$5,4)*R23 -> 2 | V23: =+VLOOKUP(S23,Atributos!$P$2:$W$5,5)*R23 -> 16 | W23: =+VLOOKUP(S23,Atributos!$P$2:$W$5,6)*R23 -> 32 | X23: =+VLOOKUP(S23,Atributos!$P$2:$W$5,7)*R23 -> 8 | Y23: =+VLOOKUP(S23,Atributos!$P$2:$W$5,8)*R23 -> 8
A24: Finanzas | B24: Operaciones financieras | C24: FI-08_Cuentas Por Cobrar(FI_P030) | D24: J59 | E24: Maestro de Interlocutor Comercial (Deudores o Clientes) Registro de Facturas y otros Comprobantes de Clientes - Registro de Comprobantes por Finanzas (FI) - Registro de Comprobantes Con Pedido Venta(SD) Indicadores de impuestos Ventas Percepciones Venta Registro de Comprobantes de Importación de bienes Registro de IGV no domiciliado Solicitudes de Anticipo Acreedor Retenciones en la factura - Detracciones de IGV - Retenciones no Domiciliados - Retenciones dietas Retenciones en el pago - Retenciones de IGV - Retenciones de 4ta categoría Anulación de Registro Registros preliminares Cuenta de mayor especial (CME) Compensaciones - Con anticipos - Con N/D y N/C - Canje de letras - Factura Negociable o Factoring o Compensación Deudor/Acreedor o Anulación de compensación Reportes | F24: El proceso de cuentas por cobrar comprende básicamente la contabilidad en deudores producto de las operaciones de venta de bienes o servicios que generen una obligación de cobro. Los clientes cuentan con un código único en el maestro de Business Partner bajo el cual se registran sus operaciones y permiten el análisis auxiliar por cuenta deudora. | G24: 1) Registrar Comprobantes de Ventas por FI ( Facturas , Notas de Crédito y Débito ) con sus indicadores de IVA 2) Registrar Provisiones de Ingresos por FI 3) Registrar documentos por Provisión de Cobranza Dudosa 4) Registrar préstamos entre Empresas Vinculadas o Terceros 5) Registro de Otras de Cuentas por Cobrar Diversas 6) Registrar Retenciones en la cuentas por Cobrar en el momento de la contabilización de la factura ( Localización ). Manejando Percepción de Venta y Detracción de Venta. 7) Anulación del documento de venta generado 9) Compensación de Partidas Deudoras, Anticipos, Notas de Crédito y Débito. 10) Compensación de Deudores con Acreedores 11) Anulación o descompnesación de documentos de cobro. | H24: Los indicadores de impuestos están asociado al IGV. No está considerado otro tipo de impuesto como ISC, impuestos especiales de sectores industriales, FISE, Rodamiento, impuestos a los plásticos, etc | I24: FI | J24: YS0_S4HANA_EO_001 YS0_S4HANA_EO_C001 | M24: 1 | N24: ANEXO_FI05 - CME | P24: 04 Terminado | R24: 1 | S24: PR | T24: =+VLOOKUP(S24,Atributos!$P$2:$W$5,3)*R24 -> 1 | U24: =+VLOOKUP(S24,Atributos!$P$2:$W$5,4)*R24 -> 2 | V24: =+VLOOKUP(S24,Atributos!$P$2:$W$5,5)*R24 -> 16 | W24: =+VLOOKUP(S24,Atributos!$P$2:$W$5,6)*R24 -> 32 | X24: =+VLOOKUP(S24,Atributos!$P$2:$W$5,7)*R24 -> 8 | Y24: =+VLOOKUP(S24,Atributos!$P$2:$W$5,8)*R24 -> 8
A25: Finanzas | B25: Tesoreria | C25: FI-09_Gestión de Tesorería(FI_P040) | D25: 4X8 | E25: Operaciones de Tesorería - Transferencia entre Cuentas - Compra/Venta de Divisas Reportes | F25: La Gestión de Tesorería, abarca el registro de las operaciones propias a la administración de los fondos de la empresa. | G25: 1) Gestionar Transferencia Bancarias 2) Registrar Compra / Venta de Divisas 3) Cobranzas | I25: FI | J25: YS0_S4HANA_EO_001 YS0_S4HANA_EO_C001 | M25: 1 | P25: 04 Terminado | R25: 1 | S25: PR | T25: =+VLOOKUP(S25,Atributos!$P$2:$W$5,3)*R25 -> 1 | U25: =+VLOOKUP(S25,Atributos!$P$2:$W$5,4)*R25 -> 2 | V25: =+VLOOKUP(S25,Atributos!$P$2:$W$5,5)*R25 -> 16 | W25: =+VLOOKUP(S25,Atributos!$P$2:$W$5,6)*R25 -> 32 | X25: =+VLOOKUP(S25,Atributos!$P$2:$W$5,7)*R25 -> 8 | Y25: =+VLOOKUP(S25,Atributos!$P$2:$W$5,8)*R25 -> 8
A26: Finanzas | B26: Cierre contable y financiero | C26: FI-10_Gestión de Activos Fijos(FI_P050) | D26: J62 | E26: Alta de Activos Fijos - Por Compra directa - Por Adquisición bajo arrendamiento financiero. - Por liquidación de obra en curso Traslados Baja de Activos Fijos - Por venta - Por desguace Activos mantenidos para la venta Revaluación y Desvalorización Depreciación Operaciones de Cierre Anual Reportes | F26: Este proceso comprende las diferentes operaciones contables que se registran sobre los activos fijos. Así mismo, abarca la reportería para el análisis contable de los activos fijos. | G26: 1) Alta de Activos por Compras o Liquidaciones de Activos en Curso. 2) Alta de Activos por Arrendamiento Financiero desde FI. 3) Traspasos de Activos 4) Bajas de Activos: Baja por Desguace / Baja por Venta 5) Revaluaciones de Activos Fijos 6) Ejecución de las Depreciaciones 7) Cambio de Ejercicio y Cierre de Ejercicio de Activos Fijos | I26: FI | J26: YS0_S4HANA_FIAA_001 | K26: YS0_S4HANA_EO_001 YS0_S4HANA_EO_C001 | L26: Faltan app y roles | M26: 1 | P26: 04 Terminado | R26: 1 | S26: PR | T26: =+VLOOKUP(S26,Atributos!$P$2:$W$5,3)*R26 -> 1 | U26: =+VLOOKUP(S26,Atributos!$P$2:$W$5,4)*R26 -> 2 | V26: =+VLOOKUP(S26,Atributos!$P$2:$W$5,5)*R26 -> 16 | W26: =+VLOOKUP(S26,Atributos!$P$2:$W$5,6)*R26 -> 32 | X26: =+VLOOKUP(S26,Atributos!$P$2:$W$5,7)*R26 -> 8 | Y26: =+VLOOKUP(S26,Atributos!$P$2:$W$5,8)*R26 -> 8
A27: Finanzas | B27: Cierre contable y financiero | C27: FI-11_Cierre Contable(FI_P100) | D27: J58-01 | E27: Proceso de Cierre de Mes - Registro de documentos - Apertura y Cierre de Períodos contables - Desplazamiento de periodo logístico - Anulación de documentos FI - Análisis y Compensación de cuentas - Conciliación bancaria - Valoración de Moneda Extranjera - Traslación - Liquidación de AFeC - Depreciación/Amortización de activos fijos o intangibles Proceso de Cierre de Año - Arrastre de Saldos Anual - Cierre de ejercicio de Activos Fijos Estados Financieros y libros oficiales Reportes | F27: Este proceso se encuentra constituido por las actividades que permiten cerrar las operaciones necesarias del día, mes y del ejercicio. Para ello, el sistema ofrece un conjunto de programas que permiten ejecutar los procesos de cierre y hacer análisis a través reportes de resultados y de cuentas balance. | G27: 1) Apertura y Cierre periodos contables( Variante de Ejercicio FI) 2) Desplazamiento de Periodo Logistico. 3) Compensaciones Manuales o Automaticas de Cuentas de Mayor 4) Conciliación Banacaria ( Localización ) 5) Valoración de Moneda Extranjera ( Ejemplo: USD a PEN ) 6) Traslasión Moneda Local ( Ejemplo PEN a USD ) 7) Liquidación de Activos FIjo en Curso 8) Ejecución de la Depreciaión del mes correspondiente. 9) Arrastre de Saldos que incluye la apertura del nuevo ejercicio para Activos Fijos. 10) Cierre de Ejercicio de Activos Fijos 11) Reporteria Balance General o Report Painters 12) Libros Electrónicos SUNAT ( Localización Z) | I27: FI | J27: YS0_S4HANA_EO_001 YS0_S4HANA_EO_C001 | M27: 1 | P27: 04 Terminado | R27: 1 | S27: PR | T27: =+VLOOKUP(S27,Atributos!$P$2:$W$5,3)*R27 -> 1 | U27: =+VLOOKUP(S27,Atributos!$P$2:$W$5,4)*R27 -> 2 | V27: =+VLOOKUP(S27,Atributos!$P$2:$W$5,5)*R27 -> 16 | W27: =+VLOOKUP(S27,Atributos!$P$2:$W$5,6)*R27 -> 32 | X27: =+VLOOKUP(S27,Atributos!$P$2:$W$5,7)*R27 -> 8 | Y27: =+VLOOKUP(S27,Atributos!$P$2:$W$5,8)*R27 -> 8
A28: Finanzas | B28: Operaciones financieras avanzadas | C28: FI-12_Gestión de Créditos(SD_P070) | D28: BD6 | E28: Área de control de crédito Segmento de crédito Asignación de la línea de crédito Consumo de la línea de crédito Reportes | F28: Corresponden a los datos que contienen información relevante para la gestión de créditos, funcionalidades para su seguimiento y control. Si la empresa trabaja con líneas de crédito para los clientes, se determina en que procesos de venta aplica este proceso. Al realizar el pedido de venta se verifica si hay deuda vencida y si el pedido sobrepasa la línea de crédito asignada. | G28: Venta Nacional con límite de crédito excedido. Venta Exportación con partidas abiertas vencidas. Venta Servicios con suficiente línea de crédito. | I28: SD | J28: YS0_S4HANA_SD_001 YS0_S4HANA_SD_C001 | K28: YS0_S4HANA_EO_001 YS0_S4HANA_EO_C001 | L28: Falta establecer el flujo adecuado para el proceso, transacciones en el paso a paso del BPD | M28: 1 | P28: 04 Terminado | R28: 1 | S28: PR | T28: =+VLOOKUP(S28,Atributos!$P$2:$W$5,3)*R28 -> 1 | U28: =+VLOOKUP(S28,Atributos!$P$2:$W$5,4)*R28 -> 2 | V28: =+VLOOKUP(S28,Atributos!$P$2:$W$5,5)*R28 -> 16 | W28: =+VLOOKUP(S28,Atributos!$P$2:$W$5,6)*R28 -> 32 | X28: =+VLOOKUP(S28,Atributos!$P$2:$W$5,7)*R28 -> 8 | Y28: =+VLOOKUP(S28,Atributos!$P$2:$W$5,8)*R28 -> 8
A29: Abastecimiento y compras | B29: EO | C29: MM-00_Estructura organizativa(MM_EO1) | E29: Sociedad Organización de Compra Grupo de Compra Centros Almacén | F29: En la estructura SAP S/4HANA se representa la vista jurídica u organizativa de una empresa como los niveles de la organización. La determinación de dichos niveles constituye la Estructura Organizativa y corresponde, a un requisito escencial tanto para la determinación de los datos maestros como para los procesos a definir en la empresa. | I29: MM | J29: YS0_S4HANA_EO_001 YS0_S4HANA_EO_C001 | M29: 1 | P29: 04 Terminado | R29: 1 | S29: EO | T29: =+VLOOKUP(S29,Atributos!$P$2:$W$5,3)*R29 -> 1 | U29: =+VLOOKUP(S29,Atributos!$P$2:$W$5,4)*R29 -> 1 | V29: =+VLOOKUP(S29,Atributos!$P$2:$W$5,5)*R29 -> 4 | W29: =+VLOOKUP(S29,Atributos!$P$2:$W$5,6)*R29 -> 4 | X29: =+VLOOKUP(S29,Atributos!$P$2:$W$5,7)*R29 -> 0 | Y29: =+VLOOKUP(S29,Atributos!$P$2:$W$5,8)*R29 -> 0
A30: Abastecimiento y compras | B30: Gestión de datos maestros | C30: MM-01_Maestro de materiales(MM_M010) | E30: Niveles de organización Agrupación de Materiales Gestión de Valoración Vistas de Información - Datos básicos - Datos de compras - Datos de ventas - Datos de planificación - Datos de centro/almacén - Datos contables Reportes | F30: En SAP S/4HANA el maestro de materiales es el más importante repositorio de información base para todos los procesos logísticos y de gestión de stocks. Aquí se administran todos los datos de los materiales gestionados por la organización. El maestro de materiales está estructurado en “vistas” o pestañas de datos. Cada vista contiene campos específicos relacionados a un área funcional o proceso de negocio. Si a un material no se le ha completado correctamente las vistas vinculadas a un proceso, este material no podrá ser utilizado en dichos procesos. | G30: Tipo de Material: -Mercadería -Materia Prima -Material no valorado -Suministros -Embalajes -Producto semielaborado -Producto Terminado -Material Servicios | H30: Se excluye campos no mencionados en el BPD. | I30: MM | K30: YS0_S4HANA_EO_001 YS0_S4HANA_EO_C001 | L30: Deacuerdo a las best practice de SAP, el maestro de servicios (Tx. AC01/AC02/AC03) se reemplazará por la utilización del tipo de material ‘SERV‘ para los servicios que se compran y venden. | M30: 1 | N30: ANEXO_MM01 - Grupo de artículos ANEXO_MM02 - Categoría de valoración ANEXO_MM03 - Planificadores de necesidad ANEXO_MM05 - Jerarquía de productos ANEXO_MM08 - OBYC | O30: MC_MM_M010 - Maestro de materiales | P30: 04 Terminado | R30: 1 | S30: DM | T30: =+VLOOKUP(S30,Atributos!$P$2:$W$5,3)*R30 -> 1 | U30: =+VLOOKUP(S30,Atributos!$P$2:$W$5,4)*R30 -> 1 | V30: =+VLOOKUP(S30,Atributos!$P$2:$W$5,5)*R30 -> 8 | W30: =+VLOOKUP(S30,Atributos!$P$2:$W$5,6)*R30 -> 8 | X30: =+VLOOKUP(S30,Atributos!$P$2:$W$5,7)*R30 -> 8 | Y30: =+VLOOKUP(S30,Atributos!$P$2:$W$5,8)*R30 -> 0
A31: Abastecimiento y compras | B31: Gestión de datos maestros | C31: MM-03_Datos maestros de compras(MM_M020) | E31: Creación de condiciones. Creación de registros info | F31: Las condiciones son los acuerdos que se tienen con los proveedores sobre precios, recargos, descuentos, etc. Las cuales pueden ser empleados por los documentos logísticos. Los registros info relacionan la información de los materiales con los proveedores como acuerdos comerciales. | G31: Precios: manual o de registro info Descuentos: fijos y porcentual Recargos: fijo y porcentual. Impuestos : IGV Costos Indirectos : Transporte e instalación. Importaciones: comisiones agente de aduana fijo y %, flete, seguro,%advalorem,almacenaje, transporte, estiba, cuadrilla, gasto portuario, vistos buenos, servicios logísticos, gastos administrativos, Instalación. Se utiliza para compras nacionales e importadas. | H31: Se excluye variaciones o lógicas especiales para los esquemas de cálculos o condiciones definidos en el BPD. | I31: MM | J31: YS0_S4HANA_BP_001 YS0_S4HANA_MM_001 | K31: YS0_S4HANA_EO_001 YS0_S4HANA_EO_C001 | M31: 1 | O31: MC_MM_M030_Registro de condiciones MC_MM_M040_Registros info | P31: 04 Terminado | R31: 1 | S31: DM | T31: =+VLOOKUP(S31,Atributos!$P$2:$W$5,3)*R31 -> 1 | U31: =+VLOOKUP(S31,Atributos!$P$2:$W$5,4)*R31 -> 1 | V31: =+VLOOKUP(S31,Atributos!$P$2:$W$5,5)*R31 -> 8 | W31: =+VLOOKUP(S31,Atributos!$P$2:$W$5,6)*R31 -> 8 | X31: =+VLOOKUP(S31,Atributos!$P$2:$W$5,7)*R31 -> 8 | Y31: =+VLOOKUP(S31,Atributos!$P$2:$W$5,8)*R31 -> 0
A32: Abastecimiento y compras | B32: Operaciones de compras | C32: MM-10_Compras de stock(MM_P050) | D32: J45 | E32: Generación de Solicitud de Pedido Liberación de Solicitud de Pedido Generación de Pedido de Compra Liberación de Pedido de Compra Envío de formato de pedido de compra al proveedor. Entrada de Mercadería Registro de Facturas Reportes | F32: Este proceso en SAP permite brindar soporte al Proceso de Abastecimiento de Proveedores Locales o extranjeros para la adquisición de existencias de una empresa. Cabe mencionar que, para los procesos definidos en SAP, las existencias son aquellas que: - Emplean un código de material, que contará con gestión de cantidad y valor. - El ingreso de dicho material es contabilizado en ctas. de existencias. | G32: -Compras asociadas a contratos por valor afectos a IGV -Compras asociadas a contratos por importe inafectos a IGV. -Compras sin estrategias de liberación con retenciones. -Compras con estrategia de liberación con detracciones. -Compras con descuentos, recargos, costos indirectos,afectos y no afectos al IGV. -Compras con posiciones gratuitas -Entregas parciales. -Facturación parcial. -Anulación de entrega. -Anulación de factura. -Compras locales e importaciones. | H32: No se usa planes de entrega. No se utiliza entregas entrantes ni confirmaciones de OC. | I32: MM | J32: YS0_S4HANA_MM_001 | K32: YS0_S4HANA_EO_001 YS0_S4HANA_EO_C001 | L32: Las transacciones de petición de ofertas y ofertas están obsoletas. Hay que volver a configurar el proceso basado en las nuevas prácticas de SAP a través de apps creadas para este fin. | M32: 1 | O32: MC_MM_P051_Pedidos | P32: 04 Terminado | Q32: S0_B001_00_010 | R32: 1 | S32: PR | T32: =+VLOOKUP(S32,Atributos!$P$2:$W$5,3)*R32 -> 1 | U32: =+VLOOKUP(S32,Atributos!$P$2:$W$5,4)*R32 -> 2 | V32: =+VLOOKUP(S32,Atributos!$P$2:$W$5,5)*R32 -> 16 | W32: =+VLOOKUP(S32,Atributos!$P$2:$W$5,6)*R32 -> 32 | X32: =+VLOOKUP(S32,Atributos!$P$2:$W$5,7)*R32 -> 8 | Y32: =+VLOOKUP(S32,Atributos!$P$2:$W$5,8)*R32 -> 8
A33: Abastecimiento y compras | B33: Operaciones de compras | C33: MM-11_Compra de servicios(MM_P051) | D33: 22Z | E33: Generación de Solicitud de Pedido Liberación de Solicitud de Pedido Generación de Pedido de Abierto Liberación de Pedido Abierto Generación de Pedido de Compra Liberación de Pedido de Compra Envío de formato de pedido de compra al proveedor. Entrada de Mercadería Registro de Facturas Reportes | F33: Este proceso de compras utiliza solicitudes de pedido o directamente órdenes de compra. Se realiza el flujo de compras con aprobaciones de órdenes de compra, hoja de entrada de servicio y registro de la factura. A diferencia de las compras de stock, este proceso requiere de una imputación en las solicitudes de pedidos u órdenes de compra ya que los importes son registrados directamente en el gasto ya que no se requiere tenerlos en cuentas de inventario. | G33: -Compras asociadas a contratos por valor afectos a IGV -Compras asociadas a contratos por importe inafectos a IGV. -Compras sin estrategias de liberación con retenciones. -Compras con estrategia de liberación con detracciones. -Compras con descuentos, recargos, costos indirectos,afectos y no afectos al IGV. -Compras con posiciones gratuitas -Entregas parciales. -Facturación parcial. -Anulación de entrega. -Anulación de factura. -Compras locales e importaciones. | H33: No se usa planes de entrega. No se utiliza entregas entrantes ni confirmaciones de OC. | I33: MM | J33: YS0_S4HANA_MM_001 | K33: YS0_S4HANA_EO_001 YS0_S4HANA_EO_C001 | L33: Las transacciones de petición de ofertas y ofertas están obsoletas. Hay que volver a configurar el proceso basado en las nuevas prácticas de SAP a través de apps creadas para este fin. | M33: 1 | O33: MC_MM_P051_Pedidos | P33: 04 Terminado | Q33: S0_B001_00_010 | R33: 1 | S33: PR | T33: =+VLOOKUP(S33,Atributos!$P$2:$W$5,3)*R33 -> 1 | U33: =+VLOOKUP(S33,Atributos!$P$2:$W$5,4)*R33 -> 2 | V33: =+VLOOKUP(S33,Atributos!$P$2:$W$5,5)*R33 -> 16 | W33: =+VLOOKUP(S33,Atributos!$P$2:$W$5,6)*R33 -> 32 | X33: =+VLOOKUP(S33,Atributos!$P$2:$W$5,7)*R33 -> 8 | Y33: =+VLOOKUP(S33,Atributos!$P$2:$W$5,8)*R33 -> 8
A34: Abastecimiento y compras | B34: Operaciones de compras | C34: MM-12_Compras de consumibles(MM_P051) | D34: BNX 18J | E34: Tipos de Imputación - Centro de Costo - Orden CO Compra de Bienes - Generación de Solicitud de Pedido - Liberación de Solicitud de Pedido - Generación de Pedido de Compra - Liberación de Pedido de Compra - Envío de formato de pedido de compra al proveedor. - Entrada de Mercadería - Registro de Facturas Reportes | F34: Este proceso de compras utiliza solicitudes de pedido o directamente órdenes de compra. Se realiza el flujo de compras con aprobaciones de órdenes de compra, ingresos de mercadería al almacén y registro de la factura. A diferencia de las compras de stock, este proceso requiere de una imputación en las solicitudes de pedidos u órdenes de compra ya que los importes son registrados directamente en el gasto ya que no se requiere tenerlos en cuentas de inventario. Este proceso está orientado a compra de materiales que no forman parte del core del negocio pero que son requeridos para la gestión y están dentro del presupuesto anual de la compañía como por ejemplo la compra de útiles de economato, activos fijos, etc. | G34: -Compras de material no valorado imputados a varios centro de costos. -Compras de suministro imputadas a una orden CO. -Compras imputadas a un activo fijo. -Compras de servicios imputada a un centro de costos. -Imputación U.(Desconocida). | I34: MM | J34: YS0_S4HANA_MM_001 | K34: YS0_S4HANA_EO_001 YS0_S4HANA_EO_C001 | L34: Las transacciones de petición de ofertas y ofertas están obsoletas. Hay que volver a configurar el proceso basado en las nuevas prácticas de SAP a través de apps creadas para este fin. SAP indica que debemos usar materiales SERV para servicios, eso implica que va a ser obsoleto el uso de las HES? | M34: 1 | P34: 04 Terminado | R34: 1 | S34: PR | T34: =+VLOOKUP(S34,Atributos!$P$2:$W$5,3)*R34 -> 1 | U34: =+VLOOKUP(S34,Atributos!$P$2:$W$5,4)*R34 -> 2 | V34: =+VLOOKUP(S34,Atributos!$P$2:$W$5,5)*R34 -> 16 | W34: =+VLOOKUP(S34,Atributos!$P$2:$W$5,6)*R34 -> 32 | X34: =+VLOOKUP(S34,Atributos!$P$2:$W$5,7)*R34 -> 8 | Y34: =+VLOOKUP(S34,Atributos!$P$2:$W$5,8)*R34 -> 8
A35: Abastecimiento y compras | B35: Abastecimiento y gestión de contratos | C35: MM-13_Compras con contratos(MM_P052) | D35: BMD | E35: Generación de Solicitud de Pedido Generación de Pedido de Abierto Liberación de Pedido Abierto Generación de Pedido de Compra Entrada de mercancía Registro de Factura del Proveedor Extranjero de la Orden de Compra Registro de Facturas de Costos Indirectos Reportes | F35: Este proceso de compras se utiliza para tener mayor predictibilidad en el abastecimiento ya que previamente se puede negociar con los proveedores volúmenes importantes de compras a lo largo de un periodo determinado logrando mejores condiciones de cumplimiento por parte del proveedor. El proceso inicia con una solicitud de pedido que contienen el volumen total del requerimiento, en base a este volumen se negocia un contrato con el proveedor. El gerente de compra aprueba la formulación del contrato. Luego todas las solicitudes de compra pueden usar las condiciones comerciales negociadas en los contratos generados hasta agotar el volumen negociado con el proveedor. Los contratos también se pueden usar para procesos de abastecimiento que involucran importación. | G35: Compra con pedido abierto asociado a solped con condiciones de importación: - Comisiones agente de aduana fijo y %. - Flete. - Seguro. - %advalorem. - Almacenaje, transporte, estiba, cuadrilla, gasto portuario, vistos buenos, servicios logísticos, gastos administrativos, Instalación. | H35: Sin gestión de stock en operadores logísticos | I35: MM | J35: YS0_S4HANA_MM_001 | K35: YS0_S4HANA_EO_001 YS0_S4HANA_EO_C001 | L35: Las transacciones de petición de ofertas y ofertas están obsoletas. Hay que volver a configurar el proceso basado en las nuevas prácticas de SAP a través de apps creadas para este fin. | M35: 1 | P35: 04 Terminado | R35: 1 | S35: PR | T35: =+VLOOKUP(S35,Atributos!$P$2:$W$5,3)*R35 -> 1 | U35: =+VLOOKUP(S35,Atributos!$P$2:$W$5,4)*R35 -> 2 | V35: =+VLOOKUP(S35,Atributos!$P$2:$W$5,5)*R35 -> 16 | W35: =+VLOOKUP(S35,Atributos!$P$2:$W$5,6)*R35 -> 32 | X35: =+VLOOKUP(S35,Atributos!$P$2:$W$5,7)*R35 -> 8 | Y35: =+VLOOKUP(S35,Atributos!$P$2:$W$5,8)*R35 -> 8
A36: Abastecimiento y compras | B36: Operaciones de compras | C36: MM-14_Consignaciones(MM_P053) | D36: 2LG | E36: Generación de Solicitud de Pedido de Consignación Generación o actualización de registro Info por consignación Generación de Pedido de Compra por consignación Liberación de Pedido de compra de consignación Generación de Formulario de Orden de Compra al proveedor Entrada de Mercadería a consignación Traspaso de Consignación a libre utilización (stock propio) Toma de Materiales en Consignación Liquidación de materiales en consignación tomados Reportes | F36: Este proceso conserva las consideraciones del Proceso de Compra Nacional mencionada anteriormente y se le suman las siguientes particularidades: 1. El proveedor suministra los materiales (artículos en consignación) y la empresa que realiza la adquisición, los guarda en sus almacenes o bodegas. Sin embargo, el proveedor queda como el propietario legal del material hasta que sean tomado. 2. Para el pago de la factura, se realizan cortes periódicos coordinados entre el proveedor y la empresa que realiza la adquisición o compra, para identificar cual ha sido el consumo a la fecha y realizar el pago, en función de un precio, previamente acordado antes de realizar el consumo. 3. SAP permite a través de sus reportes, identificar el material que se encuentra en estado consignado y controlar, una vez pase al stock propio. Obs. Este modelo, legalmente conlleva a presentar al estado un libro de consignación. Generalmente utilizado en empresas que consumen combustibles a gran escala. | G36: - Proceso de consignación de proveedor simple: Generación de solicitud de compra, generación de pedido de compra, entrada de mercadería a consignación, toma de materiales y liquidación. | I36: MM | J36: YS0_S4HANA_MM_001 | K36: YS0_S4HANA_EO_001 YS0_S4HANA_EO_C001 | M36: 1 | P36: 04 Terminado | R36: 1 | S36: PR | T36: =+VLOOKUP(S36,Atributos!$P$2:$W$5,3)*R36 -> 1 | U36: =+VLOOKUP(S36,Atributos!$P$2:$W$5,4)*R36 -> 2 | V36: =+VLOOKUP(S36,Atributos!$P$2:$W$5,5)*R36 -> 16 | W36: =+VLOOKUP(S36,Atributos!$P$2:$W$5,6)*R36 -> 32 | X36: =+VLOOKUP(S36,Atributos!$P$2:$W$5,7)*R36 -> 8 | Y36: =+VLOOKUP(S36,Atributos!$P$2:$W$5,8)*R36 -> 8
A37: Abastecimiento y compras | B37: Operaciones de compras | C37: MM-15_Subcontratación(MM_P054) | D37: BMY | E37: Generación de la Solicitud de Pedido Liberación de la Solicitud de Pedido Generación o actualización de registro Info por subcontratación Generación de Pedido de Subcontratación Liberación del Pedido de subcontratación Generación de Formulario de Compra al proveedor Entrega de componentes a Proveedor por Subcontratación (Emisión de guía de remisión) Entrada de Mercadería del producto final Registro de Factura Reportes | F37: Este proceso conserva las consideraciones del Proceso de Compra Nacional mencionada anteriormente y se le suman las siguientes particularidades: 1. Durante el proceso de compra, el proveedor puede recibir todos o una parte de los componentes, con los que fabricará o ensamblará para poder abastecer con un producto final. 2. SAP permite optimizar el proceso, armando listas de materiales para que se dé una propuesta automática a los materiales que debemos entregar al proveedor. Si bien el proceso soporta el uso de lista de materiales, debe considerarse el esfuerzo necesario por parte del negocio de crear este dato maestros y darle el mantenimiento adecuado. 3. SAP cuenta con reportes que permitirán monitorear el material que está siendo entregado al proveedor; así como, controlar el stock del nuevo material una vez se dé el ingreso. | G37: - Proceso de subcontratación simple: Los materiales entregados al proveedor salen del mismo centro donde el proveedor entrega el producto procesado. | H37: Se excluye | I37: MM | J37: YS0_S4HANA_MM_001 | K37: YS0_S4HANA_EO_001 YS0_S4HANA_EO_C001 | M37: 1 | P37: 04 Terminado | R37: 1 | S37: PR | T37: =+VLOOKUP(S37,Atributos!$P$2:$W$5,3)*R37 -> 1 | U37: =+VLOOKUP(S37,Atributos!$P$2:$W$5,4)*R37 -> 2 | V37: =+VLOOKUP(S37,Atributos!$P$2:$W$5,5)*R37 -> 16 | W37: =+VLOOKUP(S37,Atributos!$P$2:$W$5,6)*R37 -> 32 | X37: =+VLOOKUP(S37,Atributos!$P$2:$W$5,7)*R37 -> 8 | Y37: =+VLOOKUP(S37,Atributos!$P$2:$W$5,8)*R37 -> 8
A38: Abastecimiento y compras | B38: Operaciones de compras | C38: MM-20_Estrategias de liberación(MM_P030) | E38: Estrategias para Solicitud de Pedido Estrategias para Orden de Compra Estrategias para Pedido Abierto Estrategia para Hoja de Entrada de Servicio | F38: Esta funcionalidad de SAP S/4HANA permite establecer criterios de aprobación definidos para los documentos de compras y ejecutar las liberaciones desde My Inbox que se puede desplegar en celulares. | G38: - Liberación de solicitudes - Liberación orden de compra - Liberación pedido abierto - Liberación de hojas de entrada de servicio. | H38: 1. Se excluye las notificaciones para liberar los documentos. Esto será en la siguiente versión 2. Se excluye cualquier cambio de lógica adicional al funcionamiento estándar de las estrategias. | I38: MM | J38: YS0_S4HANA_MM_001 | K38: YS0_S4HANA_EO_001 YS0_S4HANA_EO_C001 | L38: Debería haber un anexo para la definción de las estrategias | M38: 1 | N38: ANEXO_MM04 - Solicitante ANEXO_MM07 - Estrategias de liberación | P38: 04 Terminado | R38: 1 | S38: PR | T38: =+VLOOKUP(S38,Atributos!$P$2:$W$5,3)*R38 -> 1 | U38: =+VLOOKUP(S38,Atributos!$P$2:$W$5,4)*R38 -> 2 | V38: =+VLOOKUP(S38,Atributos!$P$2:$W$5,5)*R38 -> 16 | W38: =+VLOOKUP(S38,Atributos!$P$2:$W$5,6)*R38 -> 32 | X38: =+VLOOKUP(S38,Atributos!$P$2:$W$5,7)*R38 -> 8 | Y38: =+VLOOKUP(S38,Atributos!$P$2:$W$5,8)*R38 -> 8
A39: Cadena de suministro | B39: Inventario | C39: MM-40_Gestión de Stocks(MM_P060) | D39: BMC | E39: Entrada de Mercadería - Por Pedido de Compra - Por Pedido de Traslado - Sin Pedido de compra ° Por Carga Inicial ° Entrada sin referencia Traspasos - Entre almacenes en un paso - Entre almacenes en dos pasos. - Cambio tipo de stock - Cambio de código de material Traslado con pedido de traslado (entre centros) - Creación de Pedido de Traslado - Generación Entrega de Salida - Generación de la salida de materiales. - Registro de Entrada de Mercadería a centro destino Salidas No Comerciales de Materiales/Mercancías - Generación de reservas para atención de almacén. - Salida por consumo Devolución a proveedor - Con pedido de devolución Desguace (Deterioro, caducidad, obsolescencia, y/o merma Salida por ventas Reportes | F39: Este proceso contempla todos los movimientos que se puedan realizar con las existencias o material que solo cuenten con gestión de cantidad y se encuentren dentro de los almacenes o bodegas de la empresa y que sean registrado dentro de SAP. Movimientos como: - Entradas de material. - Salidas de material no comerciales. - Traslados planificados o no planificados. - Traspaso entre materiales. Entre otros movimientos. | G39: - Movientos traspaso entre almacenes de 1 y 2 pasos. - Cambio de tipo de stock. - Cambio Código de material - Traslado entre centros con pedido de traslado - Anulación de documento de material. - Devolución a proveedor con pedido de devolución. - Salida por deterioro. - Salidas por reserva a centro de costo. - Traspaso de lotes. | H39: - Determinación de lotes - Variación del costo del material por traslado de productos. | I39: MM | J39: YS0_S4HANA_MM_001 | K39: YS0_S4HANA_EO_001 YS0_S4HANA_EO_C001 | M39: 1 | O39: MC_MM_P060 - Gestión de stock - carga inicial | P39: 04 Terminado | R39: 1 | S39: PR | T39: =+VLOOKUP(S39,Atributos!$P$2:$W$5,3)*R39 -> 1 | U39: =+VLOOKUP(S39,Atributos!$P$2:$W$5,4)*R39 -> 2 | V39: =+VLOOKUP(S39,Atributos!$P$2:$W$5,5)*R39 -> 16 | W39: =+VLOOKUP(S39,Atributos!$P$2:$W$5,6)*R39 -> 32 | X39: =+VLOOKUP(S39,Atributos!$P$2:$W$5,7)*R39 -> 8 | Y39: =+VLOOKUP(S39,Atributos!$P$2:$W$5,8)*R39 -> 8
A40: Cadena de suministro | B40: Inventario | C40: MM-50_Gestión de Inventarios(MM_P070) | D40: 4LU BML | E40: Generación de Documento de inventario Generación del Formulario de Inventario (Estándar) Registro del conteo (recuento) de inventario Generación de listado de diferencias Contabilización de diferencias Reportes | F40: Este proceso en SAP S/4HANA, permite la toma del inventario de los almacenes de su empresa para el balance. Dicho inventario, puede realizarse tanto para el stock propio como para el stock especial como por ej. el stock en consignación en el cliente, stock externo de artículos en consignación del proveedor o embalaje en préstamo. Teniendo como premisa que el inventario de cada uno de ellos; es decir, del stock propio y del especial, deben realizarse por separado. Por lo tanto, se deberán crear diferentes documentos de inventarios para la toma de dichos inventarios. | G40: Contabilización del conteo (material sujeto a lote). Contabilización en base a reconteo (material no sujeto a lote). | H40: Se excluye pruebas de toma de inventario para otro tipo de stock especial. Solo stock propio. | I40: MM | J40: YS0_S4HANA_MM_001 | K40: YS0_S4HANA_EO_001 YS0_S4HANA_EO_C001 | M40: 1 | P40: 04 Terminado | R40: 1 | S40: PR | T40: =+VLOOKUP(S40,Atributos!$P$2:$W$5,3)*R40 -> 1 | U40: =+VLOOKUP(S40,Atributos!$P$2:$W$5,4)*R40 -> 2 | V40: =+VLOOKUP(S40,Atributos!$P$2:$W$5,5)*R40 -> 16 | W40: =+VLOOKUP(S40,Atributos!$P$2:$W$5,6)*R40 -> 32 | X40: =+VLOOKUP(S40,Atributos!$P$2:$W$5,7)*R40 -> 8 | Y40: =+VLOOKUP(S40,Atributos!$P$2:$W$5,8)*R40 -> 8
A41: Gestión de activos | B41: EO | C41: PM-00_Estructura organizativa(PM_EO) | E41: Definición de estructura PM | F41: Define el uso del modelo centralizado o descentralizado. | G41: Define el uso del modelo centralizado o descentralizado. | I41: PM | K41: YS0_S4HANA_EO_001 YS0_S4HANA_EO_C001 | M41: 2 | P41: 04 Terminado | R41: 1 | S41: EO | T41: =+VLOOKUP(S41,Atributos!$P$2:$W$5,3)*R41 -> 1 | U41: =+VLOOKUP(S41,Atributos!$P$2:$W$5,4)*R41 -> 1 | V41: =+VLOOKUP(S41,Atributos!$P$2:$W$5,5)*R41 -> 4 | W41: =+VLOOKUP(S41,Atributos!$P$2:$W$5,6)*R41 -> 4 | X41: =+VLOOKUP(S41,Atributos!$P$2:$W$5,7)*R41 -> 0 | Y41: =+VLOOKUP(S41,Atributos!$P$2:$W$5,8)*R41 -> 0
A42: Gestión de activos | B42: Datos maestros de mantenimiento | C42: PM-01_Datos maestros de mantenimiento | E42: - Catálogos - Clases y características - Ubicaciones técnicas - Equipos - Puestos de trabajo - Listas de materiales | F42: Describe los datos maestros necesarios para representar las instalaciones industriales dentro del sistema y poder llevar de manera adecuada el seguimiento de las actividades de mantenimiento a nivel de cada activo. | I42: PM | M42: 2 | P42: 04 Terminado | R42: 1 | S42: DM | T42: =+VLOOKUP(S42,Atributos!$P$2:$W$5,3)*R42 -> 1 | U42: =+VLOOKUP(S42,Atributos!$P$2:$W$5,4)*R42 -> 1 | V42: =+VLOOKUP(S42,Atributos!$P$2:$W$5,5)*R42 -> 8 | W42: =+VLOOKUP(S42,Atributos!$P$2:$W$5,6)*R42 -> 8 | X42: =+VLOOKUP(S42,Atributos!$P$2:$W$5,7)*R42 -> 8 | Y42: =+VLOOKUP(S42,Atributos!$P$2:$W$5,8)*R42 -> 0
A43: Gestión de activos | B43: Gestión de mantenimiento | C43: PM-10_Mantenimiento correctivo(PM_P010) | D43: BH1 | E43: Creación de aviso. Creación de OM. Liberación de OM. Integración con compras. Notificación. Consumo de reservas. Cierre técnico. Cierre comercial | F43: Describe el flujo de proceso desde que se reporta un incidente hasta la solución del mismo. Está basado en el aviso de mantenimiento que sirve para documentar el incidente de mantenimiento y la OM que sirve para controlar las operaciones desde el punto de vista de la logística, compras y costos. | I43: PM | J43: BH1 / BH2 | K43: YS0_S4HANA_EO_001 YS0_S4HANA_EO_C001 | M43: 2 | P43: 04 Terminado | R43: 1 | S43: PR | T43: =+VLOOKUP(S43,Atributos!$P$2:$W$5,3)*R43 -> 1 | U43: =+VLOOKUP(S43,Atributos!$P$2:$W$5,4)*R43 -> 2 | V43: =+VLOOKUP(S43,Atributos!$P$2:$W$5,5)*R43 -> 16 | W43: =+VLOOKUP(S43,Atributos!$P$2:$W$5,6)*R43 -> 32 | X43: =+VLOOKUP(S43,Atributos!$P$2:$W$5,7)*R43 -> 8 | Y43: =+VLOOKUP(S43,Atributos!$P$2:$W$5,8)*R43 -> 8
A44: Gestión de activos | B44: Gestión de mantenimiento | C44: PM-20_Mantenimiento preventivo (PM_P020) | D44: BJ2 | E44: Creación de estrategias. Creación de hojas de ruta. Creación de planes de mantenimiento. Registro de documentos de medición Programación de plan. Creación de OM. Liberación de OM. Integración con compras. Notificación. Consumo de reservas. Cierre técnico. Cierre comercial | F44: Se define las frecuencias necesarias para establecer los mantenimientos preventivos, puede realizarse a través de variables temporales o en base a los contadores de los puntos de medición. Se define el uso de las hojas de ruta. Estas describen las operaciones de mantenimiento que se deben realizar de acuerdo a las definiciones de negocio o especificaciones de fabricante. Generalmente se usan en conjunto con los planes de mantenimiento preventivo. Se puede asociar de manera diferenciada hojas de ruta para cada equipo o ubicación técnica; sin embargo también es posible asignar una hoja de ruta genérica va varios equipos y ubicaciones técnicas. Se describe la estrategia y frecuencia sobre la cual se crearán las peticiones de mantenimiento. Se indican diferentes horizontes que permiten anticipar la creación de las OM. Asímismo se tiene una visión de corto y mediano plazo donde se puede evidenciar en adelanto o atraso de mantenimientos en base a la situación actual de las OM y documentos de medición. Se describe el flujo de proceso desde que se genera una OM preventiva hasta la culminación de todas sus actividades. Está basado en la OM que sirve para controlar las operaciones desde el punto de vista de la logística, compras y costos. | G44: Planes de mantenimiento basados en tiempo. Planes de mantenimiento basados en actividad. | I44: PM | J44: BJ2 | K44: YS0_S4HANA_EO_001 YS0_S4HANA_EO_C001 | M44: 2 | P44: 04 Terminado | R44: 1 | S44: PR | T44: =+VLOOKUP(S44,Atributos!$P$2:$W$5,3)*R44 -> 1 | U44: =+VLOOKUP(S44,Atributos!$P$2:$W$5,4)*R44 -> 2 | V44: =+VLOOKUP(S44,Atributos!$P$2:$W$5,5)*R44 -> 16 | W44: =+VLOOKUP(S44,Atributos!$P$2:$W$5,6)*R44 -> 32 | X44: =+VLOOKUP(S44,Atributos!$P$2:$W$5,7)*R44 -> 8 | Y44: =+VLOOKUP(S44,Atributos!$P$2:$W$5,8)*R44 -> 8
A45: Manufactura | B45: EO | C45: PP-00_Estructura organizativa(PP_EO) | E45: NA | F45: Define las áreas de planificación en caso se plantee la planificación separada de almacenes | I45: PP | M45: 3 | P45: 00 Nuevo | R45: 1 | S45: EO | T45: =+VLOOKUP(S45,Atributos!$P$2:$W$5,3)*R45 -> 1 | U45: =+VLOOKUP(S45,Atributos!$P$2:$W$5,4)*R45 -> 1 | V45: =+VLOOKUP(S45,Atributos!$P$2:$W$5,5)*R45 -> 4 | W45: =+VLOOKUP(S45,Atributos!$P$2:$W$5,6)*R45 -> 4 | X45: =+VLOOKUP(S45,Atributos!$P$2:$W$5,7)*R45 -> 0 | Y45: =+VLOOKUP(S45,Atributos!$P$2:$W$5,8)*R45 -> 0
A46: Manufactura | B46: Gestión de datos maestros | C46: PP-01_Datos maestros de producción(PP_M010) | E46: Creación, modificación y visualización de puestos de trabajo | F46: Definición del uso de los puestos de trabajo en entorno de fabricación discreta o repetitiva. Descripción de las principales vistas para la planificación y programación de capacidades, y definición de los inductores de costos de producción | H46: Se excluye la planificación detallada PPDS. Se excluye la integración de HR. | I46: PP | J46: YS0_S4HANA_PP_001 | K46: YS0_S4HANA_EO_001 YS0_S4HANA_EO_C001 | M46: 2 | N46: ANEXO_P2M00 - Resp.Pto.Trabajo | O46: MC_PP_M010 - Puestos de trabajo | P46: 04 Terminado | R46: 1 | S46: DM | T46: =+VLOOKUP(S46,Atributos!$P$2:$W$5,3)*R46 -> 1 | U46: =+VLOOKUP(S46,Atributos!$P$2:$W$5,4)*R46 -> 1 | V46: =+VLOOKUP(S46,Atributos!$P$2:$W$5,5)*R46 -> 8 | W46: =+VLOOKUP(S46,Atributos!$P$2:$W$5,6)*R46 -> 8 | X46: =+VLOOKUP(S46,Atributos!$P$2:$W$5,7)*R46 -> 8 | Y46: =+VLOOKUP(S46,Atributos!$P$2:$W$5,8)*R46 -> 0
A47: Manufactura | B47: Planificación de producción | C47: PP-10_Planificación de producción - MPS | D47: BJ5 | E47: Creación de demanda. Creación de órdenes previsionales. Fijación de órdenes previsionales. Conversión de órdenes previsionales. | F47: Definición del proceso de planificación basado en MRP Live. Parte de la creación de las estimaciones o necesidades primaria planificadas a nivel de centro y SKU entendida como demanda restringida. Ejecución de MRP Live para que se propongan las órdenes previsionales y se carguen los puestos de trabajo o recursos con necesidades de capacidad. Se analizan los recursos críticos para priorizar las órdenes a realizarse. Se fijan las órdenes previsionales para evitar que se modificquen con un nuevo proceso MRP Live. Finalmente se convierten en órdenes de faricación o proceso que se entregan a planta para su ejecución. | G47: Stock de seguridad estático y dinámico. Procesos masivos e individuales. Tamaños de lote exactos y fijos con redondeos. Cálculo de rechazo de conjunto y componente. | H47: No incluye estrategias MTO. No incluye optimización de la planificación. No incluye secuenciación PP/DS No incluye DD-MRP No incluye MRP predictivo | I47: PP | J47: YS0_S4HANA_PP_001 | K47: YS0_S4HANA_EO_001 YS0_S4HANA_EO_C001 | M47: 2 | P47: 04 Terminado | R47: 1 | S47: PR | T47: =+VLOOKUP(S47,Atributos!$P$2:$W$5,3)*R47 -> 1 | U47: =+VLOOKUP(S47,Atributos!$P$2:$W$5,4)*R47 -> 2 | V47: =+VLOOKUP(S47,Atributos!$P$2:$W$5,5)*R47 -> 16 | W47: =+VLOOKUP(S47,Atributos!$P$2:$W$5,6)*R47 -> 32 | X47: =+VLOOKUP(S47,Atributos!$P$2:$W$5,7)*R47 -> 8 | Y47: =+VLOOKUP(S47,Atributos!$P$2:$W$5,8)*R47 -> 8
A48: Manufactura | B48: Planificación de producción | C48: PP-11_Evaluación de capacidades - CRP | D48: 31L/3LQ | E48: Revisiónde cuellos de botella. Análisis de utilización de los recursos: Sobre cargas y subutilización. | F48: Luego del proceso MRP Live, se evaluan los recursos o puestos de trabajo críticos. Se priorizan las órdenes que deben atenderse. Se busca tener una utilización adecuada, el planificador de capacidad debe asignar adecuadamente las órdenes coordinando continuamente con planificación, planta y mantenimiento la disponibilidad de los recursos. | I48: PP | J48: YS0_S4HANA_PP_001 | K48: YS0_S4HANA_EO_001 YS0_S4HANA_EO_C001 | M48: 3 | P48: 04 Terminado | R48: 1 | S48: PR | T48: =+VLOOKUP(S48,Atributos!$P$2:$W$5,3)*R48 -> 1 | U48: =+VLOOKUP(S48,Atributos!$P$2:$W$5,4)*R48 -> 2 | V48: =+VLOOKUP(S48,Atributos!$P$2:$W$5,5)*R48 -> 16 | W48: =+VLOOKUP(S48,Atributos!$P$2:$W$5,6)*R48 -> 32 | X48: =+VLOOKUP(S48,Atributos!$P$2:$W$5,7)*R48 -> 8 | Y48: =+VLOOKUP(S48,Atributos!$P$2:$W$5,8)*R48 -> 8
A49: Manufactura | B49: Planificación de producción | C49: PP-12_Planificación de necesidades(MM_P010) | D49: J44 | E49: Definición del método planificación de necesidades Verificación / Actualización de datos maestros de planificación Ejecución de planificación Verificación de propuesta de abastecimiento Asignación de fuente de aprovisionamiento Creación de pedido de compra Reportes | F49: La Planif. De Necesidades corresponde a la funcionalidad que brinda SAP para garantizar la disponibilidad del material; es decir que, se emplea para el aprovisionamiento o la fabricación de las cantidades en el momento oportuno, tanto para necesidades internas como para los requerimientos del área Comercial. Este proceso implica el mantenimiento de datos maestros consistentes, la supervisión de stocks y la propuesta automática del aprovisionamiento para compras y/o producción bajo el análisis del planner de la empresa. | G49: Planificación por punto de pedido(VB): - Con stock de seguridad estático. - Tamaño de lote hasta stock máximo. Planificación determinista para compras(PD,P1,PE,P3,P4): - Con lotes exactos con redondeo y SS estático. Planificación determinista para traslados(PD,P1,P2,P3,P4): - Con lotes fijos sin stock de seguridad. | H49: Se excluye otro tipo de: Planificación, stock de seguridad, y tamaño de lote. | I49: PP | J49: YS0_S4HANA_MM_001 | K49: YS0_S4HANA_EO_001 YS0_S4HANA_EO_C001 | M49: 1 | P49: 04 Terminado | R49: 1 | S49: PR | T49: =+VLOOKUP(S49,Atributos!$P$2:$W$5,3)*R49 -> 1 | U49: =+VLOOKUP(S49,Atributos!$P$2:$W$5,4)*R49 -> 2 | V49: =+VLOOKUP(S49,Atributos!$P$2:$W$5,5)*R49 -> 16 | W49: =+VLOOKUP(S49,Atributos!$P$2:$W$5,6)*R49 -> 32 | X49: =+VLOOKUP(S49,Atributos!$P$2:$W$5,7)*R49 -> 8 | Y49: =+VLOOKUP(S49,Atributos!$P$2:$W$5,8)*R49 -> 8
A50: Manufactura | B50: Planificación de producción | C50: PP-13_Planificación predictiva MRP | D50: 4B5 | E50: Creación de proyecciones de escenarios hipotéticos. Ejecución de pMRP. Análisis de capacidades y cobertura. | F50: pMRP permite hacer una ejecución del proceso de planificación e2e de manera simulada para analizar escenarios hipotéticos y poder contar con planes de accion de manera anticipada. Dentro del proceso de S&OP sirve para restringir la demanda consensuada. | I50: PP | K50: YS0_S4HANA_EO_001 YS0_S4HANA_EO_C001 | P50: 00 Nuevo | R50: 1 | S50: PR | T50: =+VLOOKUP(S50,Atributos!$P$2:$W$5,3)*R50 -> 1 | U50: =+VLOOKUP(S50,Atributos!$P$2:$W$5,4)*R50 -> 2 | V50: =+VLOOKUP(S50,Atributos!$P$2:$W$5,5)*R50 -> 16 | W50: =+VLOOKUP(S50,Atributos!$P$2:$W$5,6)*R50 -> 32 | X50: =+VLOOKUP(S50,Atributos!$P$2:$W$5,7)*R50 -> 8 | Y50: =+VLOOKUP(S50,Atributos!$P$2:$W$5,8)*R50 -> 8
A51: Manufactura | B51: Planificación de producción | C51: PP-14_Planificación basada en demanda - DDMRP | D51: 2QI/1Y2 | E51: Clasificación de materiales. Posicionamiento de stock. Propuesta de aprovisionamiento. | F51: Proceso de planificación orientado a la demanda. Parte de la clasificación de los productos en base a su costo relativo (ABC), variación de consumo (XYZ), leadtime (EFG) uso en lista de materiales (PQR). Posiciona el stock de acuerdo a zonas: Roja(Stock de seguridad), ambar (Punto de pedido) y verde (Stock máximo). Propone la reposición de stock de tal manera que se procura un stock en la zona ambar/verde. Como el comportamiento de un producto varia a lo largo del tiempo, este proceso puede reclasificar fácilmente los productos de manera periódica asegurando siempre un adecuado suministro sin exceso ni ruptura de stock. | I51: PP | K51: YS0_S4HANA_EO_001 YS0_S4HANA_EO_C001 | P51: 00 Nuevo | R51: 1 | S51: PR | T51: =+VLOOKUP(S51,Atributos!$P$2:$W$5,3)*R51 -> 1 | U51: =+VLOOKUP(S51,Atributos!$P$2:$W$5,4)*R51 -> 2 | V51: =+VLOOKUP(S51,Atributos!$P$2:$W$5,5)*R51 -> 16 | W51: =+VLOOKUP(S51,Atributos!$P$2:$W$5,6)*R51 -> 32 | X51: =+VLOOKUP(S51,Atributos!$P$2:$W$5,7)*R51 -> 8 | Y51: =+VLOOKUP(S51,Atributos!$P$2:$W$5,8)*R51 -> 8
A52: Manufactura | B52: Planificación de producción | C52: PP-15_Programación detallada de producción PPDS | E52: Ejecución de heurístico. Fijación de órdenes previsionales. | F52: Proceso avanzado que permite hacer una nivelaciones de las capacidades de producción en base a métods heurísticos y optimizados. Parte del análisis de las órdenes previsionales creadas por el MRP Live y termina entregando un programa de producción para el corto plazo balanceado y programado a detalle. | I52: PP | K52: YS0_S4HANA_EO_001 YS0_S4HANA_EO_C001 | P52: 00 Nuevo | R52: 1 | S52: PR | T52: =+VLOOKUP(S52,Atributos!$P$2:$W$5,3)*R52 -> 1 | U52: =+VLOOKUP(S52,Atributos!$P$2:$W$5,4)*R52 -> 2 | V52: =+VLOOKUP(S52,Atributos!$P$2:$W$5,5)*R52 -> 16 | W52: =+VLOOKUP(S52,Atributos!$P$2:$W$5,6)*R52 -> 32 | X52: =+VLOOKUP(S52,Atributos!$P$2:$W$5,7)*R52 -> 8 | Y52: =+VLOOKUP(S52,Atributos!$P$2:$W$5,8)*R52 -> 8
A53: Manufactura | B53: Operaciones de manufactura | C53: PP-20_Fabricación contra stock - Discreta (PP_P020) | D53: BJ5 | E53: Gestión de órdenes de fabricación que se dervian de un plan de producción.Notificación de actividades, consumo de componentes y entrada de mercancía. | F53: Definición del flujo de fabricación en entorno de fabricación discreta. Parte desde la creación de la orden de fabricación hasta su cierre técnico. Incluye acividades de liberación, notificación, abastecimiento de almacenes de piso, ingreso de producto. Este proceso puede ser complementado con la planificación de producción. dentro de sus variantes incluye la entrega de subproductos y coproductos secundarios. | G53: Fabricación de un producto. Fabricación de coproductos. Fabricación de subproductos. Fabricación de PT y SE Reprocesos. | H53: No incluye embalaje con HU. No se hace cálculo de componente activo. No se incluye subcontratación. | I53: PP | J53: YS0_S4HANA_PP_001 | K53: YS0_S4HANA_EO_001 YS0_S4HANA_EO_C001 | M53: 2 | N53: ANEXO_PP01 - Causas de desviación ANEXO_PP02 - Responsable de control de producción | P53: 04 Terminado | R53: 1 | S53: PR | T53: =+VLOOKUP(S53,Atributos!$P$2:$W$5,3)*R53 -> 1 | U53: =+VLOOKUP(S53,Atributos!$P$2:$W$5,4)*R53 -> 2 | V53: =+VLOOKUP(S53,Atributos!$P$2:$W$5,5)*R53 -> 16 | W53: =+VLOOKUP(S53,Atributos!$P$2:$W$5,6)*R53 -> 32 | X53: =+VLOOKUP(S53,Atributos!$P$2:$W$5,7)*R53 -> 8 | Y53: =+VLOOKUP(S53,Atributos!$P$2:$W$5,8)*R53 -> 8
A54: Manufactura | B54: Operaciones de manufactura | C54: PP-21_Reprocesos - Discreta (PP_P021) | D54: BJN | E54: Gestión de órdenes de fabricación. Notificación de actividades, consumo de componentes y entrada de mercancía. | F54: Utilización de órdenes diferenciadas para la gestión de reprocesos. Sigue la misma lógica que el procesos de fabricación contra stock. La presima principal es que un producto entra nuevamente a la línea de producción para ser ajustado a los valores de su especificación cuando se ha advertido defectos en el proceso de fabricación. Esto deriva en un sobrecosto. | I54: PP | K54: YS0_S4HANA_EO_001 YS0_S4HANA_EO_C001 | P54: 04 Terminado | R54: 1 | S54: PR | T54: =+VLOOKUP(S54,Atributos!$P$2:$W$5,3)*R54 -> 1 | U54: =+VLOOKUP(S54,Atributos!$P$2:$W$5,4)*R54 -> 2 | V54: =+VLOOKUP(S54,Atributos!$P$2:$W$5,5)*R54 -> 16 | W54: =+VLOOKUP(S54,Atributos!$P$2:$W$5,6)*R54 -> 32 | X54: =+VLOOKUP(S54,Atributos!$P$2:$W$5,7)*R54 -> 8 | Y54: =+VLOOKUP(S54,Atributos!$P$2:$W$5,8)*R54 -> 8
A55: Manufactura | B55: Operaciones de manufactura | C55: PP-22_Fabricación contra pedido - Discreta (PP_P022) | D55: BJE | E55: Gestión de órdenes de fabricación que se dervian de un pedido de venta.Notificación de actividades, consumo de componentes y entrada de mercancía. | F55: Definición del flujo de fabricación en entorno de fabricación discreta. Parte desde la creación de la orden de fabricación como parte de la integración con el área comercial en la creación del pedido de venta hasta su cierre técnico. Incluye acividades de liberación, notificación, abastecimiento de almacenes de piso, ingreso de producto. Este proceso puede ser complementado con la planificación de producción. dentro de sus variantes incluye la entrega de subproductos y coproductos secundarios. | I55: PP | K55: YS0_S4HANA_EO_001 YS0_S4HANA_EO_C001 | P55: 00 Nuevo | R55: 1 | S55: PR | T55: =+VLOOKUP(S55,Atributos!$P$2:$W$5,3)*R55 -> 1 | U55: =+VLOOKUP(S55,Atributos!$P$2:$W$5,4)*R55 -> 2 | V55: =+VLOOKUP(S55,Atributos!$P$2:$W$5,5)*R55 -> 16 | W55: =+VLOOKUP(S55,Atributos!$P$2:$W$5,6)*R55 -> 32 | X55: =+VLOOKUP(S55,Atributos!$P$2:$W$5,7)*R55 -> 8 | Y55: =+VLOOKUP(S55,Atributos!$P$2:$W$5,8)*R55 -> 8
A56: Manufactura | B56: Operaciones de manufactura | C56: PP-23_Fabricación con co-productos - Discreta (PP_P023) | D56: 3L7 | E56: Gestión de órdenes de fabricación que se dervian de un plan de producción de coproductos. Creación de órdenes de los coproductos. Creación de orden combinada.Notificación de actividades, consumo de componentes y entrada de mercancía. | F56: Definición del flujo de fabricación en entorno de fabricación discreta. Parte desde la creación de la orden de fabricación de manera individual de cada coproducto como parte de la planificación de producción, luego la creación de la orden combinada para la realización de la operación simultánea de los coproductos. Incluye acividades de liberación, notificación, abastecimiento de almacenes de piso, ingreso de producto. Este proceso puede ser complementado con la planificación de producción. dentro de sus variantes incluye la entrega de subproductos y coproductos secundarios. | I56: PP | K56: YS0_S4HANA_EO_001 YS0_S4HANA_EO_C001 | P56: 00 Nuevo | R56: 1 | S56: PR | T56: =+VLOOKUP(S56,Atributos!$P$2:$W$5,3)*R56 -> 1 | U56: =+VLOOKUP(S56,Atributos!$P$2:$W$5,4)*R56 -> 2 | V56: =+VLOOKUP(S56,Atributos!$P$2:$W$5,5)*R56 -> 16 | W56: =+VLOOKUP(S56,Atributos!$P$2:$W$5,6)*R56 -> 32 | X56: =+VLOOKUP(S56,Atributos!$P$2:$W$5,7)*R56 -> 8 | Y56: =+VLOOKUP(S56,Atributos!$P$2:$W$5,8)*R56 -> 8
A57: Manufactura | B57: Operaciones de manufactura | C57: PP-24_Fabricación con subcontratación (PP_P024) | D57: BJK | E57: Gestión de órdenes de fabricación. Notificación de actividades, consumo de componentes y entrada de mercancía. | F57: Variante del proceso de fabricación discreta en la que todo o parte de la fabricación se lleva a cabo con un proveedor. Se integra con la logística. A nivel de costo de producción se agrega el servicio de la subcontratación como parte del esquema de costos. | I57: PP | K57: YS0_S4HANA_EO_001 YS0_S4HANA_EO_C001 | P57: 04 Terminado | R57: 1 | S57: PR | T57: =+VLOOKUP(S57,Atributos!$P$2:$W$5,3)*R57 -> 1 | U57: =+VLOOKUP(S57,Atributos!$P$2:$W$5,4)*R57 -> 2 | V57: =+VLOOKUP(S57,Atributos!$P$2:$W$5,5)*R57 -> 16 | W57: =+VLOOKUP(S57,Atributos!$P$2:$W$5,6)*R57 -> 32 | X57: =+VLOOKUP(S57,Atributos!$P$2:$W$5,7)*R57 -> 8 | Y57: =+VLOOKUP(S57,Atributos!$P$2:$W$5,8)*R57 -> 8
A58: Manufactura | B58: Operaciones de manufactura | C58: PP-30_Fabricación contra stock - Procesos (PP_P030) | D58: BJ8 | E58: Gestión de órdenes de proceso que se derivan de un plan de producción.Notificación de actividades, consumo de componentes y entrada de mercancía. | F58: Definición del flujo de fabricación en entorno de fabricación por procesos. Parte desde la creación de la orden de proceso hasta su cierre técnico. Incluye cálculo de componente activo, actividades de liberación, notificación, abastecimiento de almacenes de piso, ingreso de producto. Este proceso puede ser complementado con la planificación de producción. dentro de sus variantes incluye la entrega de subproductos y coproductos secundarios. | G58: Fabricación de un producto. Fabricación de coproductos. Fabricación de subproductos. Reprocesos. Fabricación de PT y SE | H58: No incluye embalaje con HU. No se hace cálculo de componente activo. No se incluye subcontratación. | I58: PP | J58: YS0_S4HANA_PP_001 | K58: YS0_S4HANA_EO_001 YS0_S4HANA_EO_C001 | M58: 2 | N58: ANEXO_PP01 - Causas de desviación | P58: 04 Terminado | R58: 1 | S58: PR | T58: =+VLOOKUP(S58,Atributos!$P$2:$W$5,3)*R58 -> 1 | U58: =+VLOOKUP(S58,Atributos!$P$2:$W$5,4)*R58 -> 2 | V58: =+VLOOKUP(S58,Atributos!$P$2:$W$5,5)*R58 -> 16 | W58: =+VLOOKUP(S58,Atributos!$P$2:$W$5,6)*R58 -> 32 | X58: =+VLOOKUP(S58,Atributos!$P$2:$W$5,7)*R58 -> 8 | Y58: =+VLOOKUP(S58,Atributos!$P$2:$W$5,8)*R58 -> 8
A59: Manufactura | B59: Operaciones de manufactura | C59: PP-31_Reprocesos - Procesos (PP_P031) | E59: Gestión de órdenes de proceso. Notificación de actividades, consumo de componentes y entrada de mercancía. | F59: Utilización de órdenes diferenciadas para la gestión de reprocesos. Sigue la misma lógica que el procesos de fabricación contra stock. La presima principal es que un producto entra nuevamente a la línea de producción para ser ajustado a los valores de su especificación cuando se ha advertido defectos en el proceso de fabricación. Esto deriva en un sobrecosto. | I59: PP | K59: YS0_S4HANA_EO_001 YS0_S4HANA_EO_C001 | P59: 04 Terminado | R59: 1 | S59: PR | T59: =+VLOOKUP(S59,Atributos!$P$2:$W$5,3)*R59 -> 1 | U59: =+VLOOKUP(S59,Atributos!$P$2:$W$5,4)*R59 -> 2 | V59: =+VLOOKUP(S59,Atributos!$P$2:$W$5,5)*R59 -> 16 | W59: =+VLOOKUP(S59,Atributos!$P$2:$W$5,6)*R59 -> 32 | X59: =+VLOOKUP(S59,Atributos!$P$2:$W$5,7)*R59 -> 8 | Y59: =+VLOOKUP(S59,Atributos!$P$2:$W$5,8)*R59 -> 8
A60: Manufactura | B60: Operaciones de manufactura | C60: PP-32_Fabricación contra pedido - Procesos (PP_P032) | D60: 3OK | E60: Gestión de órdenes de proceso que se dervian de un pedido de venta.Notificación de actividades, consumo de componentes y entrada de mercancía. | F60: Definición del flujo de fabricación en entorno de fabricación por procesos. Parte desde la creación de la orden de proceso como parte de la integración con el área comercial en la creación del pedido de venta hasta su cierre técnico. Incluye acividades de liberación, notificación, abastecimiento de almacenes de piso, ingreso de producto. Este proceso puede ser complementado con la planificación de producción. dentro de sus variantes incluye la entrega de subproductos y coproductos secundarios. | I60: PP | K60: YS0_S4HANA_EO_001 YS0_S4HANA_EO_C001 | P60: 00 Nuevo | R60: 1 | S60: PR | T60: =+VLOOKUP(S60,Atributos!$P$2:$W$5,3)*R60 -> 1 | U60: =+VLOOKUP(S60,Atributos!$P$2:$W$5,4)*R60 -> 2 | V60: =+VLOOKUP(S60,Atributos!$P$2:$W$5,5)*R60 -> 16 | W60: =+VLOOKUP(S60,Atributos!$P$2:$W$5,6)*R60 -> 32 | X60: =+VLOOKUP(S60,Atributos!$P$2:$W$5,7)*R60 -> 8 | Y60: =+VLOOKUP(S60,Atributos!$P$2:$W$5,8)*R60 -> 8
A61: Manufactura | B61: Operaciones de manufactura | C61: PP-40_Fabricación contra Stock - Repetitiva (PP_P040) | D61: BJH | E61: Gestión de colector de costos. Notificación de actividades, consumo de componentes y entrada de mercancía. | F61: Definición del flujo de fabricación en entorno de fabricación repetitiva. Parte desde la creación del colector de costos hasta la notificación de la producción. Incluye notificación, abastecimiento de almacenes de piso, ingreso de producto. Este proceso puede ser complementado con la planificación de producción. dentro de sus variantes incluye la entrega de subproductos. Recomendado para procesos de fabricación de pocos productos y sencillo esquema de planta. | G61: Fabricación de un producto. | H61: No incluye embalaje con HU. No se hace cálculo de componente activo. No se incluye subcontratación. | I61: PP | J61: YS0_S4HANA_PP_001 | K61: YS0_S4HANA_EO_001 YS0_S4HANA_EO_C001 | M61: 2 | N61: ANEXO_PP01 - Causas de desviación | P61: 04 Terminado | R61: 1 | S61: PR | T61: =+VLOOKUP(S61,Atributos!$P$2:$W$5,3)*R61 -> 1 | U61: =+VLOOKUP(S61,Atributos!$P$2:$W$5,4)*R61 -> 2 | V61: =+VLOOKUP(S61,Atributos!$P$2:$W$5,5)*R61 -> 16 | W61: =+VLOOKUP(S61,Atributos!$P$2:$W$5,6)*R61 -> 32 | X61: =+VLOOKUP(S61,Atributos!$P$2:$W$5,7)*R61 -> 8 | Y61: =+VLOOKUP(S61,Atributos!$P$2:$W$5,8)*R61 -> 8
A62: Finanzas | B62: Gestión de datos maestros | C62: PS-01_Datos Maestros de Proyectos(PS_M010) | E62: Creación, modificación y visualización de puestos de trabajo | F62: Definición del uso de los puestos de trabajo en entorno de gestión de proyectos. Descripción de las principales vistas para la planificación y programación de capacidades. | I62: PS | K62: YS0_S4HANA_EO_001 YS0_S4HANA_EO_C001 | M62: 3 | N62: ANEXO_P2M00 - Resp.Pto.Trabajo | P62: 04 Terminado | R62: 1 | S62: DM | T62: =+VLOOKUP(S62,Atributos!$P$2:$W$5,3)*R62 -> 1 | U62: =+VLOOKUP(S62,Atributos!$P$2:$W$5,4)*R62 -> 1 | V62: =+VLOOKUP(S62,Atributos!$P$2:$W$5,5)*R62 -> 8 | W62: =+VLOOKUP(S62,Atributos!$P$2:$W$5,6)*R62 -> 8 | X62: =+VLOOKUP(S62,Atributos!$P$2:$W$5,7)*R62 -> 8 | Y62: =+VLOOKUP(S62,Atributos!$P$2:$W$5,8)*R62 -> 0
A63: Finanzas | B63: Gestión de proyectos | C63: PS-02_Planificación detallada del Proyecto(PS_P010) | E63: Creación de proyecto, creación de elementos PEP en base a la estructura del proyecto. | F63: Definición de la estructura de un proyecto. Asignación de perfiles de proyecto que le permite al sistema usar elementos PEP para el control de gastos así como para la ejecución de proyectos de inversión. Establecimiento de las fecha de inicio y fin de las diferentes etaptas, cálcular el costo planeado en base al detalle de materiales y servicios que se vayan a comprar para el proyecto. | G63: Proyectos solo de elementos PEP. Proyectos que incluyen grafos. | I63: PS | K63: YS0_S4HANA_EO_001 YS0_S4HANA_EO_C001 | M63: 2 | N63: ANEXO_PS01 - Estructura de proyecto | P63: 04 Terminado | R63: 1 | S63: PR | T63: =+VLOOKUP(S63,Atributos!$P$2:$W$5,3)*R63 -> 1 | U63: =+VLOOKUP(S63,Atributos!$P$2:$W$5,4)*R63 -> 2 | V63: =+VLOOKUP(S63,Atributos!$P$2:$W$5,5)*R63 -> 16 | W63: =+VLOOKUP(S63,Atributos!$P$2:$W$5,6)*R63 -> 32 | X63: =+VLOOKUP(S63,Atributos!$P$2:$W$5,7)*R63 -> 8 | Y63: =+VLOOKUP(S63,Atributos!$P$2:$W$5,8)*R63 -> 8
A64: Finanzas | B64: Gestión de proyectos | C64: PS-03_Presupuesto de proyectos(PS_P020) | E64: Asignación, liberación y devolución de presupuesto asignado a los PEP del proyecto. Control de disponibilidad del presupuesto. | F64: Establecer el presupuesto global del proyecto en base a la política de la empresa o en base a los costos planeados del proyecto; permite desagregar el presupuesto a cualquier nivel de la estructura PEP. Permite activar el control de disponibilidad para alertar al planificador cuando el presupuesto esté a un % de su agotamiento y puede impedir que se ejecuten más gastos y comprometidos cuando ya se ha agotado el presupuesto. También permite ampliar el presupuesto con suplementos y hacer traslados de presupuesto entre los diferentes niveles del proyecto. | G64: Proyecto de gastos generales - OPEX. Proyectos de inversión - CAPEX | I64: PS | K64: YS0_S4HANA_EO_001 YS0_S4HANA_EO_C001 | M64: 2 | P64: 04 Terminado | R64: 1 | S64: PR | T64: =+VLOOKUP(S64,Atributos!$P$2:$W$5,3)*R64 -> 1 | U64: =+VLOOKUP(S64,Atributos!$P$2:$W$5,4)*R64 -> 2 | V64: =+VLOOKUP(S64,Atributos!$P$2:$W$5,5)*R64 -> 16 | W64: =+VLOOKUP(S64,Atributos!$P$2:$W$5,6)*R64 -> 32 | X64: =+VLOOKUP(S64,Atributos!$P$2:$W$5,7)*R64 -> 8 | Y64: =+VLOOKUP(S64,Atributos!$P$2:$W$5,8)*R64 -> 8
A65: Finanzas | B65: Gestión de proyectos | C65: PS-04_Ejecución de proyectos(PS_P030) | E65: Imputación de costos a elementos PEP. Notificación de actividades. | F65: La ejecución de los proyectos inicia con la liberación del proyecto. Con esto, las diferentes áreas que participan en el proyecto pueden asignar sus actividades a los elementos PEP que les corresponda. Generalmente está integrado a la logística de compras (Compras imputadas) y a la contabilidad dado que en dichas áreas se permiten imputaciones a elementos PEP. | G65: Proyecto de gastos generales - OPEX. Proyectos de inversión - CAPEX | I65: PS | K65: YS0_S4HANA_EO_001 YS0_S4HANA_EO_C001 | M65: 2 | P65: 04 Terminado | R65: 1 | S65: PR | T65: =+VLOOKUP(S65,Atributos!$P$2:$W$5,3)*R65 -> 1 | U65: =+VLOOKUP(S65,Atributos!$P$2:$W$5,4)*R65 -> 2 | V65: =+VLOOKUP(S65,Atributos!$P$2:$W$5,5)*R65 -> 16 | W65: =+VLOOKUP(S65,Atributos!$P$2:$W$5,6)*R65 -> 32 | X65: =+VLOOKUP(S65,Atributos!$P$2:$W$5,7)*R65 -> 8 | Y65: =+VLOOKUP(S65,Atributos!$P$2:$W$5,8)*R65 -> 8
A66: Finanzas | B66: Gestión de proyectos | C66: PS-05_Cierre tecnico y final(PS_P040) | E66: Cierre técnico, liquidación periódica, liquidación total, cierre total de proyectos. | F66: Cada cierre de mes, a pesar que no se ha concluido un proyecto, se debe realizar la liquidación para que los costos del proyecto se vena reflejados en el gasto a través de centros de costo o en un activo fijo en curso. Si el proyecto ha concluido, el cierre técnico es la señal para que en la liquidación se realice la liquidación total del proyecto; con la liquidación total se puede proceder al cierre total del proyecto. El cierre total impedirá que se signa contabilizando partidas al proyecto. | G66: Liquidaciones contra centros de costo. Liquidación contra Activos Fijos. Liquidación con medidas de inversión. Traslado a AF finales. | I66: PS | K66: YS0_S4HANA_EO_001 YS0_S4HANA_EO_C001 | M66: 2 | P66: 04 Terminado | R66: 1 | S66: PR | T66: =+VLOOKUP(S66,Atributos!$P$2:$W$5,3)*R66 -> 1 | U66: =+VLOOKUP(S66,Atributos!$P$2:$W$5,4)*R66 -> 2 | V66: =+VLOOKUP(S66,Atributos!$P$2:$W$5,5)*R66 -> 16 | W66: =+VLOOKUP(S66,Atributos!$P$2:$W$5,6)*R66 -> 32 | X66: =+VLOOKUP(S66,Atributos!$P$2:$W$5,7)*R66 -> 8 | Y66: =+VLOOKUP(S66,Atributos!$P$2:$W$5,8)*R66 -> 8
A67: Finanzas | B67: Gestión de proyectos | C67: PS-06_Reporte de proyectos(PS_P050) | E67: Seguimiento de proyectos. Estructura de proyecto. Seguimiento de avance, presupuesto asignado, comprometido y disponible. Costo detallado de proyecto. | F67: Periódicamente se revisa la salud del proyecto en base al avance que se reporta de manera integrada con las áreas que intervienen en el proyecto. Todo documento imputado al proyecto compromete presupuesto y rebaja la disponibilidad del mismo, asímismo se tiene una trazabilidad de todas las partidas que se han contabilizado al proyecto. | H67: No contempla % de avance del proyecto. No contempla curva S | I67: PS | M67: 2 | P67: 04 Terminado | R67: 1 | S67: RE | T67: =+VLOOKUP(S67,Atributos!$P$2:$W$5,3)*R67 -> 1 | U67: =+VLOOKUP(S67,Atributos!$P$2:$W$5,4)*R67 -> 2 | V67: =+VLOOKUP(S67,Atributos!$P$2:$W$5,5)*R67 -> 4 | W67: =+VLOOKUP(S67,Atributos!$P$2:$W$5,6)*R67 -> 16 | X67: =+VLOOKUP(S67,Atributos!$P$2:$W$5,7)*R67 -> 0 | Y67: =+VLOOKUP(S67,Atributos!$P$2:$W$5,8)*R67 -> 8
A68: Manufactura | B68: Gestión de datos maestros | C68: QM-01_Datos maestros de calidad(QM_M010) | E68: Catalogos Características de inspección Procedimientos de muestreo Métodos de inspección Puestos de trabajo Planes de inspección | F68: En SAP S/4HANA la gestión de datos maestros permite a la organización contar con información centralizada y homogénea para realizar los diversos procesos integrados de la empresa. Los datos maestros permiten construir las especificaciones de calidad de los procesos y productos; también permiten registrar los acuerdos de calidad de proveedores. Estos datos sirven para planificar el control de calidad ya que en ellos residen los valores de aceptación de los análisis de las muestras. | G68: Catálogo de características. Conjuntos de selección | I68: QM | J68: YS0_S4HANA_QM_001 | M68: 2 | N68: ANEXO_QM01 - Catálogos QM | P68: 04 Terminado | R68: 1 | S68: DM | T68: =+VLOOKUP(S68,Atributos!$P$2:$W$5,3)*R68 -> 1 | U68: =+VLOOKUP(S68,Atributos!$P$2:$W$5,4)*R68 -> 1 | V68: =+VLOOKUP(S68,Atributos!$P$2:$W$5,5)*R68 -> 8 | W68: =+VLOOKUP(S68,Atributos!$P$2:$W$5,6)*R68 -> 8 | X68: =+VLOOKUP(S68,Atributos!$P$2:$W$5,7)*R68 -> 8 | Y68: =+VLOOKUP(S68,Atributos!$P$2:$W$5,8)*R68 -> 0
A69: Manufactura | B69: Control de calidad | C69: QM-02_Inspección de calidad en abastecimiento | D69: 1FM | E69: Creación de lote de inspección. Registro de resultados. Decisión de empleo | F69: Define el tratamiento de las inspecciones en los procesos de compra. Inicia con la creación del lote de inspección de manera automática cuando en el almacén se hace la recepción de la mercadería. El lote entra al estado de control de calidad. En este estado sólo el área de calidad puede darle un tratamiento. Luego se registran los resultados de las muestras de acuerdo al plan de inspección. Finalmente se registra la decisión de empleo en el que se determina si el lote debe ser liberado, bloqueado o devuelto. | G69: Lotes contabilizados en la EM de las órdenes de compra. | H69: Inspección adelantada sin EM. | I69: QM | J69: YS0_S4HANA_QM_001 | K69: YS0_S4HANA_EO_001 YS0_S4HANA_EO_C001 | M69: 2 | P69: 04 Terminado | R69: 1 | S69: PR | T69: =+VLOOKUP(S69,Atributos!$P$2:$W$5,3)*R69 -> 1 | U69: =+VLOOKUP(S69,Atributos!$P$2:$W$5,4)*R69 -> 2 | V69: =+VLOOKUP(S69,Atributos!$P$2:$W$5,5)*R69 -> 16 | W69: =+VLOOKUP(S69,Atributos!$P$2:$W$5,6)*R69 -> 32 | X69: =+VLOOKUP(S69,Atributos!$P$2:$W$5,7)*R69 -> 8 | Y69: =+VLOOKUP(S69,Atributos!$P$2:$W$5,8)*R69 -> 8
A70: Manufactura | B70: Control de calidad | C70: QM-03_Gestión de calidad en producción (QM_P060) | D70: 1E1 | E70: Creación de lote de inspección. Registro de resultados. Decisión de empleo | F70: Define el tratamiento de las inspecciones en producción. Inicia con la creación del lote de inspección de manera automática cuando inicia el proceso productivo. Luego cuando en el almacén se hace la recepción de la mercadería el lote entra al estado de control de calidad, en este estado sólo el área de calidad puede darle un tratamiento. Luego se registran los resultados de las muestras de acuerdo con el plan de inspección. Finalmente se registra la decisión de empleo que determina si el lote debe ser liberado o rechazado. | G70: Lotes en proceso. Lotes terminados. | H70: SPC.Gráficas de calidad. | I70: QM | J70: YS0_S4HANA_QM_001 | K70: YS0_S4HANA_EO_001 YS0_S4HANA_EO_C001 | M70: 2 | P70: 04 Terminado | R70: 1 | S70: PR | T70: =+VLOOKUP(S70,Atributos!$P$2:$W$5,3)*R70 -> 1 | U70: =+VLOOKUP(S70,Atributos!$P$2:$W$5,4)*R70 -> 2 | V70: =+VLOOKUP(S70,Atributos!$P$2:$W$5,5)*R70 -> 16 | W70: =+VLOOKUP(S70,Atributos!$P$2:$W$5,6)*R70 -> 32 | X70: =+VLOOKUP(S70,Atributos!$P$2:$W$5,7)*R70 -> 8 | Y70: =+VLOOKUP(S70,Atributos!$P$2:$W$5,8)*R70 -> 8
A71: Manufactura | B71: Control de calidad | C71: QM-04_Gestión de calidad en almacenes (QM_P070) | D71: 1MR | E71: Creación de lote de inspección. Registro de resultados. Decisión de empleo | F71: Define el tratamiento de las inspecciones en el almacén. Inicia con la creación del lote de inspección de manera automática cuando ocurren traslados. El lote entra al estado de control de calidad. En este estado sólo el área de calidad puede darle un tratamiento. Luego se registran los resultados de las muestras de acuerdo al plan de inspección. Finalmente se registra la decisión de empleo en el que se determina si el lote debe ser liberado, bloqueado o devuelto. | I71: QM | J71: YS0_S4HANA_QM_001 | K71: YS0_S4HANA_EO_001 YS0_S4HANA_EO_C001 | M71: 2 | P71: 00 Nuevo | R71: 1 | S71: PR | T71: =+VLOOKUP(S71,Atributos!$P$2:$W$5,3)*R71 -> 1 | U71: =+VLOOKUP(S71,Atributos!$P$2:$W$5,4)*R71 -> 2 | V71: =+VLOOKUP(S71,Atributos!$P$2:$W$5,5)*R71 -> 16 | W71: =+VLOOKUP(S71,Atributos!$P$2:$W$5,6)*R71 -> 32 | X71: =+VLOOKUP(S71,Atributos!$P$2:$W$5,7)*R71 -> 8 | Y71: =+VLOOKUP(S71,Atributos!$P$2:$W$5,8)*R71 -> 8
A72: Manufactura | B72: Control de calidad | C72: QM-05_Gestión de reclamos a proveedores (QM_P080) | D72: 2F9 | E72: Creación, modificación y visualización de avisos de reclamación | F72: Proceso de investigación de causa raiz cada vez que ocurre una incidencia de calidad que se atribuye al proveedor. Se crea un aviso de reclamo al proveedor donde se especifica el materia, lote, cantidad, etc. Se documentan las diferentes actividades de seguimiento al incidente y finalmente se cierra el aviso con el resultado de la investigación. | I72: QM | K72: YS0_S4HANA_EO_001 YS0_S4HANA_EO_C001 | P72: 00 Nuevo | R72: 1 | S72: PR | T72: =+VLOOKUP(S72,Atributos!$P$2:$W$5,3)*R72 -> 1 | U72: =+VLOOKUP(S72,Atributos!$P$2:$W$5,4)*R72 -> 2 | V72: =+VLOOKUP(S72,Atributos!$P$2:$W$5,5)*R72 -> 16 | W72: =+VLOOKUP(S72,Atributos!$P$2:$W$5,6)*R72 -> 32 | X72: =+VLOOKUP(S72,Atributos!$P$2:$W$5,7)*R72 -> 8 | Y72: =+VLOOKUP(S72,Atributos!$P$2:$W$5,8)*R72 -> 8
A73: Manufactura | B73: Control de calidad | C73: QM-06_Gestión de reclamos de clientes (QM_P081) | D73: 2FA | E73: Creación, modificación y visualización de avisos de reclamación | F73: Proceso de investigación de causa raiz cada vez que ocurre una incidencia de calidad que un cliente le atribuye a la empresa. Se crea un aviso de reclamo del cliente donde se especifica el materia, lote, cantidad, etc. Se documentan las diferentes actividades de seguimiento al incidente y finalmente se cierra el aviso con el resultado de la investigación. | I73: QM | K73: YS0_S4HANA_EO_001 YS0_S4HANA_EO_C001 | P73: 00 Nuevo | R73: 1 | S73: PR | T73: =+VLOOKUP(S73,Atributos!$P$2:$W$5,3)*R73 -> 1 | U73: =+VLOOKUP(S73,Atributos!$P$2:$W$5,4)*R73 -> 2 | V73: =+VLOOKUP(S73,Atributos!$P$2:$W$5,5)*R73 -> 16 | W73: =+VLOOKUP(S73,Atributos!$P$2:$W$5,6)*R73 -> 32 | X73: =+VLOOKUP(S73,Atributos!$P$2:$W$5,7)*R73 -> 8 | Y73: =+VLOOKUP(S73,Atributos!$P$2:$W$5,8)*R73 -> 8
A74: Manufactura | B74: Control de calidad | C74: QM-07_Gestión de reclamos internos (QM_P082) | D74: 2QP | E74: Creación, modificación y visualización de avisos de reclamación | F74: Proceso de investigación de causa raiz cada vez que ocurre una incidencia de calidad que se atribuye a algún proceso interno. Se crea un aviso de reclamo interno donde se especifica el materia, lote, cantidad, etc. Se documentan las diferentes actividades de seguimiento al incidente y finalmente se cierra el aviso con el resultado de la investigación. | I74: QM | K74: YS0_S4HANA_EO_001 YS0_S4HANA_EO_C001 | P74: 00 Nuevo | R74: 1 | S74: PR | T74: =+VLOOKUP(S74,Atributos!$P$2:$W$5,3)*R74 -> 1 | U74: =+VLOOKUP(S74,Atributos!$P$2:$W$5,4)*R74 -> 2 | V74: =+VLOOKUP(S74,Atributos!$P$2:$W$5,5)*R74 -> 16 | W74: =+VLOOKUP(S74,Atributos!$P$2:$W$5,6)*R74 -> 32 | X74: =+VLOOKUP(S74,Atributos!$P$2:$W$5,7)*R74 -> 8 | Y74: =+VLOOKUP(S74,Atributos!$P$2:$W$5,8)*R74 -> 8
A75: Manufactura | B75: Control de calidad | C75: QM-08_Gestión de no-conformes (QM_P090) | D75: 2QN | E75: Creación de defecto. Uso de método 8D de solución de problemas. Crear tareas. | F75: Investigación de defectos con método 8D | I75: QM | K75: YS0_S4HANA_EO_001 YS0_S4HANA_EO_C001 | P75: 00 Nuevo | R75: 1 | S75: PR | T75: =+VLOOKUP(S75,Atributos!$P$2:$W$5,3)*R75 -> 1 | U75: =+VLOOKUP(S75,Atributos!$P$2:$W$5,4)*R75 -> 2 | V75: =+VLOOKUP(S75,Atributos!$P$2:$W$5,5)*R75 -> 16 | W75: =+VLOOKUP(S75,Atributos!$P$2:$W$5,6)*R75 -> 32 | X75: =+VLOOKUP(S75,Atributos!$P$2:$W$5,7)*R75 -> 8 | Y75: =+VLOOKUP(S75,Atributos!$P$2:$W$5,8)*R75 -> 8
A76: Ventas | B76: EO | C76: SD-00_Estructura Organizativa(SD_EO) | E76: Organización de Ventas Canal de Distribución Sector Área de ventas Oficina de Ventas Área de ventas y oficina Grupo de Vendedores Grupo de Vendedores por oficina Vendedores Centro Puesto de Expedición Puesto de Expedición por centro | F76: En la estructura SAP se representa la vista jurídica u organizativa de una empresa como los niveles de la organización. La determinación de dichos niveles constituye la Estructura Organizativa y corresponde, a un requisito escencial tanto para la determinación de los datos maestros como para los procesos a definir en la empresa. | I76: SD | J76: YS0_S4HANA_EO_001 YS0_S4HANA_EO_C001 | M76: 1 | P76: 04 Terminado | R76: 1 | S76: EO | T76: =+VLOOKUP(S76,Atributos!$P$2:$W$5,3)*R76 -> 1 | U76: =+VLOOKUP(S76,Atributos!$P$2:$W$5,4)*R76 -> 1 | V76: =+VLOOKUP(S76,Atributos!$P$2:$W$5,5)*R76 -> 4 | W76: =+VLOOKUP(S76,Atributos!$P$2:$W$5,6)*R76 -> 4 | X76: =+VLOOKUP(S76,Atributos!$P$2:$W$5,7)*R76 -> 0 | Y76: =+VLOOKUP(S76,Atributos!$P$2:$W$5,8)*R76 -> 0
A77: Ventas | B77: Gestión de datos maestros | C77: SD-01_Administración de Datos Maestros de Business Partner(SD_M010) | E77: Definición de agrupación BP Funciones interlocutor del Business Partner Datos interlocutor general Datos de deudor Datos de cliente Datos de proveedor Datos de acreedor Business Partner en Fiori | F77: Corresponden a los datos que contienen información relevante para los procesos de negocio, los mismos que son almacenados centralmente, para ser empleados y procesados a través de las aplicaciones en SAP. Respecto al maestro de Interlocutor comercial o business partner, contiene información referido al cliente de una empresa. | G77: Los BP que se pueden crear son: -BP General -BP Relacionada(Empresa del mismo grupo) -BP Colaborador -BP Centro -BP Destinatario de Mercadería -BP Eventual CPD -BP Contactos | I77: SD | J77: YS0_S4HANA_BP_001 | K77: YS0_S4HANA_EO_001 YS0_S4HANA_EO_C001 | M77: 1 | O77: MC_SD_M010 - BP Comercial | P77: 04 Terminado | R77: 1 | S77: DM | T77: =+VLOOKUP(S77,Atributos!$P$2:$W$5,3)*R77 -> 1 | U77: =+VLOOKUP(S77,Atributos!$P$2:$W$5,4)*R77 -> 1 | V77: =+VLOOKUP(S77,Atributos!$P$2:$W$5,5)*R77 -> 8 | W77: =+VLOOKUP(S77,Atributos!$P$2:$W$5,6)*R77 -> 8 | X77: =+VLOOKUP(S77,Atributos!$P$2:$W$5,7)*R77 -> 8 | Y77: =+VLOOKUP(S77,Atributos!$P$2:$W$5,8)*R77 -> 0
A78: Ventas | B78: Gestión de datos maestros | C78: SD-02_Datos Maestros de Precios y Condiciones(SD_M020) | D78: BKA | E78: Clases de condiciones Secuencia de acceso Esquema de cálculo Reporte | F78: De manera similar a los mencionados anteriormente, almacenan datos de forma centralizada que puede ser empleadas en los procesos comerciales. En este caso, se definen todas las condiciones que representan los acuerdos con los clientes sobre precios, descuentos, entre otras y que pueden ser empleados en los procesos comerciales. Así como, la forma en la que se encontraran estructuradas dichas condiciones en los pedidos de venta. | G78: Un solo esquema de cálculo que incluye: Condiciones: Precios, descuento fijo, descuento porcentual, recargo fijo, recargo porcentual, descuento por anticipo, IGV %, recargo estadístico x detracción, Retención y costo del producto. Precio: - Organización de ventas / Canal de Distribución / Cliente / Material - Organización de ventas / Canal de Distribución / Tipo lista /Moneda/ Material - Organización de ventas / Canal de Distribución / Material Descuentos: Descuento ZD01: Organización de ventas / Cliente / Material Organización de ventas / Grupo de clientes / Material Organización de ventas / Canal de Distribución / Material Bonificación ZNA0: Organización de ventas / Canal de Distribución / Cliente/ Material Organización de ventas / Canal de Distribución / Material Impuestos: ZIGV: País / País Receptor / Clasificación Fiscal Cliente / Clasificación Fiscal Material País / Clasificación Fiscal Cliente / Clasificación Fiscal Material | I78: SD | J78: YS0_S4HANA_SD_001 YS0_S4HANA_SD_C001 | K78: YS0_S4HANA_EO_001 YS0_S4HANA_EO_C001 | M78: 1 | O78: MC_SD_M020 - Registro de condiciones | P78: 04 Terminado | R78: 1 | S78: DM | T78: =+VLOOKUP(S78,Atributos!$P$2:$W$5,3)*R78 -> 1 | U78: =+VLOOKUP(S78,Atributos!$P$2:$W$5,4)*R78 -> 1 | V78: =+VLOOKUP(S78,Atributos!$P$2:$W$5,5)*R78 -> 8 | W78: =+VLOOKUP(S78,Atributos!$P$2:$W$5,6)*R78 -> 8 | X78: =+VLOOKUP(S78,Atributos!$P$2:$W$5,7)*R78 -> 8 | Y78: =+VLOOKUP(S78,Atributos!$P$2:$W$5,8)*R78 -> 0
A79: Ventas | B79: Gestión de pedidos y contratos | C79: SD-10_Venta de stock (SD_P010) | D79: BD9 | E79: Cotización Pedido de Venta Nacional y Exportación - Verificación de stock - Verificación de crédito Proceso de Expedición Facturación Facturación Electrónica Reportes | F79: Este proceso en SAP soporta la comercialización de existencia a clientes nacionales o extranjeros, el mismo que abarca desde la actividad de preventa hasta el cierre de la venta. Para ello, se puede comprometer el stock; con el objetivo, de asegurar la entrega del pedido del cliente. En el caso que el cliente cuente con línea de crédito, se puede validará desde la puesta del documento comercial. Cabe mencionar que, para los procesos definidos en SAP, las existencias son aquellas que: - Emplean un código de material, que contará con gestión de cantidad y valor. - El ingreso de dicho material es contabilizado en ctas. de existencias. | G79: Venta Nacional Afecta al IGV. Venta Nacional Inafecta al IGV. Venta Nacional Afecta al IGV y con Descuento en las líneas de detalle. Venta Nacional Afecta al IGV y con Descuento al total del comprobante. Venta Nacional Afecta al IGV en dólares USD/EUR Autodetracción. Venta Exportación Inafecta al IGV Venta Exportación FOB. Venta Exportación FOB con Descuento en las líneas de detalle. Venta Exportación FOB con Descuento al total del comprobante. | H79: No incluye otros impuestos: ISC, plásticos, etc. | I79: SD | J79: YS0_S4HANA_SD_001 YS0_S4HANA_SD_C001 | K79: YS0_S4HANA_EO_001 YS0_S4HANA_EO_C001 | L79: Soporta venta de activos. Se vende como si fuera material de servicio | M79: 1 | P79: 04 Terminado | Q79: SÍ | R79: 1 | S79: PR | T79: =+VLOOKUP(S79,Atributos!$P$2:$W$5,3)*R79 -> 1 | U79: =+VLOOKUP(S79,Atributos!$P$2:$W$5,4)*R79 -> 2 | V79: =+VLOOKUP(S79,Atributos!$P$2:$W$5,5)*R79 -> 16 | W79: =+VLOOKUP(S79,Atributos!$P$2:$W$5,6)*R79 -> 32 | X79: =+VLOOKUP(S79,Atributos!$P$2:$W$5,7)*R79 -> 8 | Y79: =+VLOOKUP(S79,Atributos!$P$2:$W$5,8)*R79 -> 8
A80: Ventas | B80: Gestión de pedidos y contratos | C80: SD-11_Venta de servicios(SD_P020) | I80: SD | P80: 04 Terminado | R80: 1 | S80: PR | T80: =+VLOOKUP(S80,Atributos!$P$2:$W$5,3)*R80 -> 1 | U80: =+VLOOKUP(S80,Atributos!$P$2:$W$5,4)*R80 -> 2 | V80: =+VLOOKUP(S80,Atributos!$P$2:$W$5,5)*R80 -> 16 | W80: =+VLOOKUP(S80,Atributos!$P$2:$W$5,6)*R80 -> 32 | X80: =+VLOOKUP(S80,Atributos!$P$2:$W$5,7)*R80 -> 8 | Y80: =+VLOOKUP(S80,Atributos!$P$2:$W$5,8)*R80 -> 8
A81: Ventas | B81: Gestión de pedidos y contratos | C81: SD-12_Venta con Anticipos(SD_P012) | D81: BKJ | E81: Pedido de anticipo Facturación Facturación Electrónica Utilización del anticipo en la venta Reportes | F81: Este proceso en SAP soporta el uso de la emisión de factura o boleta por el concepto anticipos; es decir, cuando el cliente realiza un adelanto por la adquisición de productos o servicios, que comprará posteriormente en la misma moneda. Siendo la propuesta de este modelo, aplicar el anticipo como un descuento en el pedido de venta de los productos finales; de modo que, solo se facture el saldo pendiente y emplear la menor cantidad de documentos de facturación. Otra opción es generar un Nota de crédito del anticipo, que luego compensará parcialmente la factura por el importe total de la compra, de modo que el cliente solo paga el saldo de la misma. | G81: Venta Anticipo Afecta al IGV. Nota de Crédito de Anticipo y Venta Nacional se compensa en la cobranza. Venta Nacional con Descuento Manual de Anticipo. | H81: No incluye otros impuestos: ISC, plásticos, etc. | I81: SD | J81: YS0_S4HANA_SD_001 YS0_S4HANA_SD_C001 | K81: YS0_S4HANA_EO_001 YS0_S4HANA_EO_C001 | M81: 1 | P81: 04 Terminado | R81: 1 | S81: PR | T81: =+VLOOKUP(S81,Atributos!$P$2:$W$5,3)*R81 -> 1 | U81: =+VLOOKUP(S81,Atributos!$P$2:$W$5,4)*R81 -> 2 | V81: =+VLOOKUP(S81,Atributos!$P$2:$W$5,5)*R81 -> 16 | W81: =+VLOOKUP(S81,Atributos!$P$2:$W$5,6)*R81 -> 32 | X81: =+VLOOKUP(S81,Atributos!$P$2:$W$5,7)*R81 -> 8 | Y81: =+VLOOKUP(S81,Atributos!$P$2:$W$5,8)*R81 -> 8
A82: Ventas | B82: Gestión de pedidos y contratos | C82: SD-13_Venta Calzada(SD_P013) | D82: BDK BD3 | E82: Pedido de Venta Calzada - Verificación de crédito - Generación de solicitud de pedido Proceso de compra Proceso de Expedición Facturación Facturación Electrónica Reportes | F82: Este proceso se da cuando el producto que requiere el cliente se abastece con un proceso de compra; si no hay stock disponible entonces desde el pedido de venta se genera una solicitud de compra; el stock que ingresa es exclusivo para la venta calzada. | G82: Venta Afecta al IGV. Venta Inafecta al IGV. Venta Afecta al IGV y con Descuento al total del comprobante. Venta Afecta al IGV y con Descuento en las líneas de detalle. Venta Afecta al IGV en dólares USD. | H82: No incluye otros impuestos: ISC, plásticos, etc. | I82: SD | J82: YS0_S4HANA_SD_001 YS0_S4HANA_SD_C001 | K82: YS0_S4HANA_EO_001 YS0_S4HANA_EO_C001 | M82: 1 | P82: 04 Terminado | R82: 1 | S82: PR | T82: =+VLOOKUP(S82,Atributos!$P$2:$W$5,3)*R82 -> 1 | U82: =+VLOOKUP(S82,Atributos!$P$2:$W$5,4)*R82 -> 2 | V82: =+VLOOKUP(S82,Atributos!$P$2:$W$5,5)*R82 -> 16 | W82: =+VLOOKUP(S82,Atributos!$P$2:$W$5,6)*R82 -> 32 | X82: =+VLOOKUP(S82,Atributos!$P$2:$W$5,7)*R82 -> 8 | Y82: =+VLOOKUP(S82,Atributos!$P$2:$W$5,8)*R82 -> 8
A83: Ventas | B83: Gestión de pedidos y contratos | C83: SD-14_Transferencia Gratuita y Donaciones(SD_P014) | D83: BDA | E83: Pedido de Transferencia Gratuita y Donaciones - Verificación de stock Proceso de Expedición Facturación Reportes | F83: Estos procesos son soportados en SAP bajo ciertas particularidades: - El caso de transferencia gratuita se presenta cuando se regala un producto; por lo tanto, la venta estaría valorizado a cero. Para ello, se aplica un descuento del 100% al precio de venta y en el documento de facturación, se debe indicar que es corresponde a una transferencia gratuita. - El caso de donaciones se genera cuando se concede a una entidad y dependencia del Sector Público Nacional mercadería para brindarles apoyo o ayuda. En dicho caso, la factura se emite con el valor de venta regular pero el importe a cobrar es cero. | G83: Venta Transferencia Gratuita afecta a IGV Venta Donaciones Inafecta | I83: SD | J83: YS0_S4HANA_SD_001 YS0_S4HANA_SD_C001 | K83: YS0_S4HANA_EO_001 YS0_S4HANA_EO_C001 | M83: 1 | P83: 04 Terminado | R83: 1 | S83: PR | T83: =+VLOOKUP(S83,Atributos!$P$2:$W$5,3)*R83 -> 1 | U83: =+VLOOKUP(S83,Atributos!$P$2:$W$5,4)*R83 -> 2 | V83: =+VLOOKUP(S83,Atributos!$P$2:$W$5,5)*R83 -> 16 | W83: =+VLOOKUP(S83,Atributos!$P$2:$W$5,6)*R83 -> 32 | X83: =+VLOOKUP(S83,Atributos!$P$2:$W$5,7)*R83 -> 8 | Y83: =+VLOOKUP(S83,Atributos!$P$2:$W$5,8)*R83 -> 8
A84: Ventas | B84: Gestión de pedidos y contratos | C84: SD-15_Venta intercompañía de materiales(SD_P015) | E84: Venta Intercompany (Proceso de compras MM) en la sociedad compradora Proceso de Expedición (en la sociedad vendedora) Facturación (en la sociedad vendedora) Facturación Electrónica Entrada de Mercadería (Proceso MM en la sociedad compradora) Registro de Factura Conciliación manual entre cuenta por cobrar y cuenta por pagar entre sociedades Devolución Intercompany Reportes | F84: Este proceso comercial se desarrolla entre dos empresas (sociedades) que pertenecen a una misma organización o grupo empresarial. La empresa ordenante solicita mercancías de un centro que pertenece a otra sociedad y dado que, cada empresa tiene su propio plan contable, la empresa que entrega la mercadería debe facturar a la sociedad que ingrese el pedido de compra intercompany. El precio de dicha factura tiene un valor que permite a la empresa proveedora cubrir sus costos. | G84: Venta Intercompany Afecta al IGV. Venta Intercompany Inafecta al IGV. | H84: Entre sociedades de Perú | I84: SD | J84: YS0_S4HANA_SD_001 YS0_S4HANA_SD_C001 | K84: YS0_S4HANA_EO_001 YS0_S4HANA_EO_C001 | L84: Falta indicar en FI qué actividad o transacción se ejecuta para compensar las partidas entre compañias. | M84: 1 | P84: 04 Terminado | R84: 1 | S84: PR | T84: =+VLOOKUP(S84,Atributos!$P$2:$W$5,3)*R84 -> 1 | U84: =+VLOOKUP(S84,Atributos!$P$2:$W$5,4)*R84 -> 2 | V84: =+VLOOKUP(S84,Atributos!$P$2:$W$5,5)*R84 -> 16 | W84: =+VLOOKUP(S84,Atributos!$P$2:$W$5,6)*R84 -> 32 | X84: =+VLOOKUP(S84,Atributos!$P$2:$W$5,7)*R84 -> 8 | Y84: =+VLOOKUP(S84,Atributos!$P$2:$W$5,8)*R84 -> 8
A85: Ventas | B85: Gestión de pedidos y contratos | C85: SD-16_Venta Intercompañia avanza(SD_P016) | D85: 5D2 | I85: SD | P85: 00 Nuevo | R85: 1 | S85: PR | T85: =+VLOOKUP(S85,Atributos!$P$2:$W$5,3)*R85 -> 1 | U85: =+VLOOKUP(S85,Atributos!$P$2:$W$5,4)*R85 -> 2 | V85: =+VLOOKUP(S85,Atributos!$P$2:$W$5,5)*R85 -> 16 | W85: =+VLOOKUP(S85,Atributos!$P$2:$W$5,6)*R85 -> 32 | X85: =+VLOOKUP(S85,Atributos!$P$2:$W$5,7)*R85 -> 8 | Y85: =+VLOOKUP(S85,Atributos!$P$2:$W$5,8)*R85 -> 8
A86: Ventas | B86: Gestión de pedidos y contratos | C86: SD-17_Consignaciones(SD_P0140) | D86: 1IU | E86: Reposición de artículos en consignación: - Pedido de Reposición Art. en consignación - Proceso de Expedición Toma de artículos en consignación - Pedido de Toma Art. en consignación - Procedo de Expedición - Facturación - Facturación Electrónica Recojo de artículos en consignación - Pedido de Recojo Art. en consignación - Proceso de Expedición Devolución de artículos en consignación - Pedido de Devolución Art. en consignación - Proceso de Expedición - Facturación - Facturación Electrónica Reportes | F86: Este proceso se da cuando la empresa da en consignación sus productos por ejemplo a distribuidores menores; el stock físicamente va a los distribuidores, pero aún es propiedad de la empresa; hasta que el distribuidor hace la venta al cliente final. Hay 4 escenarios para el tratamiento de este proceso: - La reposición del producto o envió a consignación al distribuidor - La toma cuando el producto consignado se vende al cliente final - El recojo cuando el distribuidor devuelve el producto a la empresa - La devolución cuando el cliente final devuelve el producto al distribuidor | G86: Reposición de artículos en Consignación sin Precio. Toma de artículos en Consignación Afecto al IGV. Devolución de artículos en Consignación Afecto al IGV. Recojo de artículos en Consignación sin Precio. | I86: SD | J86: YS0_S4HANA_SD_001 YS0_S4HANA_SD_C001 | K86: YS0_S4HANA_EO_001 YS0_S4HANA_EO_C001 | L86: Falta indicar trasnacciones por cada actividad. Relacionarlo con BPD o con el diagrama de flujo. Actualizar transporte en el diagrama se muestra pero no se indica en el BPD | M86: 1 | P86: 04 Terminado | R86: 1 | S86: PR | T86: =+VLOOKUP(S86,Atributos!$P$2:$W$5,3)*R86 -> 1 | U86: =+VLOOKUP(S86,Atributos!$P$2:$W$5,4)*R86 -> 2 | V86: =+VLOOKUP(S86,Atributos!$P$2:$W$5,5)*R86 -> 16 | W86: =+VLOOKUP(S86,Atributos!$P$2:$W$5,6)*R86 -> 32 | X86: =+VLOOKUP(S86,Atributos!$P$2:$W$5,7)*R86 -> 8 | Y86: =+VLOOKUP(S86,Atributos!$P$2:$W$5,8)*R86 -> 8
A87: Ventas | B87: Gestión de pedidos y contratos | C87: SD-60_Contrato por Valor(SD_P060) | D87: I9I | E87: Contrato por Valor - Contrato - Pedido mensual - Facturación - Facturación Electrónica Contrato con Plan de Facturación - Contrato - Facturación - Facturación Electrónica Reportes | F87: Esta funcionalidad da soporte para registrar contratos por valor por ejemplo si la empresa tiene contratos de alquiler que facturan mensualmente. | G87: Contrato con Pedido de Venta Afecto al IGV. Contrato con Plan de Facturación Afecto al IGV. | I87: SD | J87: YS0_S4HANA_SD_001 YS0_S4HANA_SD_C001 | K87: YS0_S4HANA_EO_001 YS0_S4HANA_EO_C001 | L87: Falta indicar trasnacciones por cada actividad. Relacionarlo con BPD o con el diagrama de flujo. Actualizar transporte en el diagrama se muestra pero no se indica en el BPD | M87: 1 | P87: 04 Terminado | R87: 1 | S87: PR | T87: =+VLOOKUP(S87,Atributos!$P$2:$W$5,3)*R87 -> 1 | U87: =+VLOOKUP(S87,Atributos!$P$2:$W$5,4)*R87 -> 2 | V87: =+VLOOKUP(S87,Atributos!$P$2:$W$5,5)*R87 -> 16 | W87: =+VLOOKUP(S87,Atributos!$P$2:$W$5,6)*R87 -> 32 | X87: =+VLOOKUP(S87,Atributos!$P$2:$W$5,7)*R87 -> 8 | Y87: =+VLOOKUP(S87,Atributos!$P$2:$W$5,8)*R87 -> 8
A88: Ventas | B88: Gestión de pedidos y contratos | C88: SD-70_Contrato por Cantidad(SD_P060) | D88: I9I | E88: Contrato por Valor - Contrato - Pedido mensual - Facturación - Facturación Electrónica Contrato con Plan de Facturación - Contrato - Facturación - Facturación Electrónica Reportes | F88: Esta funcionalidad da soporte para registrar contratos por valor por ejemplo si la empresa tiene contratos de alquiler que facturan mensualmente. | G88: Contrato con Pedido de Venta Afecto al IGV. Contrato con Plan de Facturación Afecto al IGV. | I88: SD | J88: YS0_S4HANA_SD_001 YS0_S4HANA_SD_C001 | K88: YS0_S4HANA_EO_001 YS0_S4HANA_EO_C001 | L88: Falta indicar trasnacciones por cada actividad. Relacionarlo con BPD o con el diagrama de flujo. Actualizar transporte en el diagrama se muestra pero no se indica en el BPD | M88: 1 | P88: 04 Terminado | R88: 1 | S88: PR | T88: =+VLOOKUP(S88,Atributos!$P$2:$W$5,3)*R88 -> 1 | U88: =+VLOOKUP(S88,Atributos!$P$2:$W$5,4)*R88 -> 2 | V88: =+VLOOKUP(S88,Atributos!$P$2:$W$5,5)*R88 -> 16 | W88: =+VLOOKUP(S88,Atributos!$P$2:$W$5,6)*R88 -> 32 | X88: =+VLOOKUP(S88,Atributos!$P$2:$W$5,7)*R88 -> 8 | Y88: =+VLOOKUP(S88,Atributos!$P$2:$W$5,8)*R88 -> 8
A89: Ventas | B89: Gestión de pedidos y contratos | C89: SD-80_Gestión de reclamos(SD_P080) | D89: 1EZ 1F1 BKL BDQ BKP | E89: Nota de Crédito por Valor - Solicitud de Nota de crédito - Facturación - Facturación Electrónica Nota de Crédito por Devolución - Solicitud de Nota de crédito de devolución - Devolución de mercadería - Facturación - Facturación Electrónica Nota de Débito: - Solicitud de Nota de débito - Facturación - Facturación Electrónica | F89: Este proceso da soporte a los eventos que se pueden presentar post-venta tanto a favor del cliente como a favor del proveedor. Dentro de este proceso se pueden atender casos como los siguientes: - Cuando el cliente hace u n reclamo y este procede, puede devolver la mercadería o dársele crédito a favor. - Cuando se ha incumplido una condición de la venta y/o se presentó a ajuste sobre el precio. | G89: Nota de Crédito Afecta al IGV Nota de Crédito Inafecta Nota de Crédito Afecta al IGV sin referencia Nota de Crédito de Devolución Parcial Afecta al IGV Nota de Crédito de Devolución Total Afecta al IGV Nota de Crédito de Devolución sin referencia Afecta al IGV Nota de debito Afecta al IGV | I89: SD | J89: YS0_S4HANA_SD_001 YS0_S4HANA_SD_C001 | K89: YS0_S4HANA_EO_001 YS0_S4HANA_EO_C001 | L89: Faltan transacciones | M89: 1 | P89: 04 Terminado | R89: 1 | S89: PR | T89: =+VLOOKUP(S89,Atributos!$P$2:$W$5,3)*R89 -> 1 | U89: =+VLOOKUP(S89,Atributos!$P$2:$W$5,4)*R89 -> 2 | V89: =+VLOOKUP(S89,Atributos!$P$2:$W$5,5)*R89 -> 16 | W89: =+VLOOKUP(S89,Atributos!$P$2:$W$5,6)*R89 -> 32 | X89: =+VLOOKUP(S89,Atributos!$P$2:$W$5,7)*R89 -> 8 | Y89: =+VLOOKUP(S89,Atributos!$P$2:$W$5,8)*R89 -> 8

Sheet Evaluar
A2: Grado de adopción | E2: Grado de Complejidad | F2: 01 Adoptar | G2: =COUNTIF(I8:I94, "=01 Adoptar") -> 43 | H2: 01 Baja | I2: =COUNTIFS(J8:J94,"=01 Baja",I8:I94, "<>04 Abstener") -> 35 | K2: =(I2+2*I3+3*I4+I5*4)/SUM(I2:I5) -> 1.36 | L2: =+MAX(L3:L5) -> 4
A3: =(1/(0.618 + (2*G4+1*G3)/(G2+1*G3+2*G4)) - 0.618) -> 0.67255114 | E3: =IF(K2 < 1.1,"Baja",IF(K2 < 2.1,"Media",IF(K2 < 4.1,"Alta","Muy Alta"))) -> Media | F3: 02 Ajustar | G3: =COUNTIF(I8:I94, "=02 Ajustar") -> 6 | H3: 02 Media | I3: =COUNTIFS(J8:J94,"=02 Media",I8:I94, "<>04 Abstener") -> 12 | J3: #Partidas Ab. | K3: 01 < 0 : 100 > | L3: =+VLOOKUP(K3,Atributos!A34:B37,2) -> 2
F4: 03 Agregar | G4: =COUNTIF(I8:I94, "=03 Agregar") -> 1 | H4: 03 Alta | I4: =COUNTIFS(J8:J94,"=03 Alta",I8:I94, "<>04 Abstener") -> 3 | J4: #Datos Maestros | K4: 01 < 0 : 100 > | L4: =+VLOOKUP(K4,Atributos!A34:B37,2) -> 2
F5: 04 Abstener | G5: =COUNTIF(I8:I94, "=04 Abstener") -> 37 | H5: 04 Muy Alta | I5: =COUNTIFS(J8:J94,"=04 Muy Alta",I8:I94, "<>04 Abstener") -> 0 | J5: #Usuarios Finales | K5: 03 <25 : 60 > | L5: =+VLOOKUP(K5,Atributos!A39:B43,2) -> 4 | S5: MINIMO | Y5: PROMEDIO
A7: Proceso de negocio | B7: Modulo | C7: Scope Item | D7: Descripción Scope Item | E7: Actividades | F7: Descripción | G7: Variantes | H7: Exclusiones | I7: QUAD-A | J7: Complejidad | K7: GAP | L7: Discovery | M7: Prepare | N7: Explore | O7: Realize | P7: Deploy | Q7: Run | R7: Semanas Prepare- Deploy | S7: Prepare MIN | T7: Explore MIN | U7: Realize MIN | V7: Deploy MIN | W7: Run MIN | X7: Semanas Prepare- Deploy MIN | Y7: Prepare PROM | Z7: Explore PROM | AA7: Realize PROM | AB7: Deploy PROM | AC7: Run | AD7: Semanas Prepare- Deploy
A8: CO-00_Estructura organizativa(CO_EO1) | B8: =+VLOOKUP(A8,S0!$C$2:$I$89,7) -> CO | C8: N/A EO | D8: No aplica en Estructura Organizativa | E8: =+VLOOKUP(A8,S0!$C$2:$I$89,3) -> Sociedad CO. Sociedad PA. Jerarquía de Centros de Beneficio Jerarquía de Centros de Costos | F8: =+VLOOKUP(A8,S0!$C$2:$I$89,4) -> En la estructura SAP representa la vista jurídica u organizativa de una empresa como los niveles de la organización. La misma que, corresponde a un requisito esencial tanto para los datos maestros; como para definir, los procesos esenciales. A través de los objetos de costo en dicha estructura; posteriormente, se realizaran las contabilizaciones en las cuentas de ingresos y gastos. | G8: 0 | H8: =+VLOOKUP(A8,S0!$C$2:$I$89,6) -> * No se puede cambiar la moneda CO ni PA luego de tener movimientos | I8: 01 Adoptar | J8: 01 Baja | N8: =+VLOOKUP($A8,S0!$C$2:$Y$89,20)/8 * VLOOKUP($I8,Atributos!$A$28:$B$31,2) * VLOOKUP($J8,Atributos!$A$22:$B$25,2)/5 -> 0.15 | O8: =+VLOOKUP($A8,S0!$C$2:$Y$89,21)/8 * VLOOKUP($I8,Atributos!$A$28:$B$31,2) * VLOOKUP($J8,Atributos!$A$22:$B$25,2)/5 -> 0.15 | P8: =+VLOOKUP($A8,S0!$C$2:$Y$89,22)/8 * VLOOKUP($I8,Atributos!$A$28:$B$31,2) * VLOOKUP($J8,Atributos!$A$22:$B$25,2)/5 -> 0 | Q8: =+VLOOKUP($A8,S0!$C$2:$Y$89,23)/8 * VLOOKUP($I8,Atributos!$A$28:$B$31,2) * VLOOKUP($J8,Atributos!$A$22:$B$25,2)/5 -> 0 | R8: =SUM(M8:P8) -> 0.3 | S8: =+(VLOOKUP($A8,S0!$C$2:$Y$89,19)/8 * VLOOKUP($I8,Atributos!$A$28:$B$31,2) * VLOOKUP($J8,Atributos!$G$22:$H$25,2))/5 -> 0.025 | T8: =+VLOOKUP($A8,S0!$C$2:$Y$89,20)/8 * VLOOKUP($I8,Atributos!$A$28:$B$31,2) * VLOOKUP($J8,Atributos!G22:H25,2)/5 -> 0.1 | U8: =+VLOOKUP($A8,S0!$C$2:$Y$89,21)/8 * VLOOKUP($I8,Atributos!$A$28:$B$31,2) * VLOOKUP($J8,Atributos!$G$22:$H$25,2)/5 -> 0.1 | V8: =+VLOOKUP($A8,S0!$C$2:$Y$89,22)/8 * VLOOKUP($I8,Atributos!$A$28:$B$31,2) * VLOOKUP($J8,Atributos!$G$22:$H$25,2)/5 -> 0 | W8: =+VLOOKUP($A8,S0!$C$2:$Y$89,23)/8 * VLOOKUP($I8,Atributos!$A$28:$B$31,2) * VLOOKUP($J8,Atributos!$G$22:$H$25,2)/5 -> 0 | X8: =SUM(S8:V8) -> 0.225 | Y8: =(S8+M8)/2 -> #VALUE! | Z8: =(T8+N8)/2 -> 0.125 | AA8: =(U8+O8)/2 -> 0.125 | AB8: =(V8+P8)/2 -> 0 | AC8: =(W8+Q8)/2 -> 0 | AD8: =SUM(Y8:AB8) -> #VALUE!
A9: CO-01_Administración de datos maestros de Controlling(CO_M010) | B9: =+VLOOKUP(A9,S0!$C$2:$I$89,7) -> CO | C9: J58 | D9: Accounting and Financial Close | E9: =+VLOOKUP(A9,S0!$C$2:$I$89,3) -> Gestión de Centros de Beneficio. Gestión de Centros de Costos. Gestión de clases de costo. Gestión de valores estadísticos. Gestión de órdenes internas. | F9: =+VLOOKUP(A9,S0!$C$2:$I$89,4) -> Corresponden a los datos que contienen información relevante para los procesos de la empresa y se encuentran almacenados de forma centralizada, para evitar redundancias y son empleadas por las diversas aplicaciones. En la contabilidad de costos tenemos: - Centro de beneficio: Es una unidad organizativa de finanzas que refleja una estructura de la empresa orientada hacia la gestión. Se pueden analizar los resultados operativos con la vinculación a las cuentas de resultado. - Centro de Costos: Es una unidad organizativa de controlling que representa una ubicación delimitada donde se generan los costes. - Gestión de clases de costo: Este maestro comprenden a las cuentas de resultado que tienen injerencia en la contabilidad de costos interna y que se requieren, para realizar los procesos en controlling. - Los valores estadísticos representan los drivers o inductores para distribuir los gastos. - Órdenes internas: Son colectores de costos que permiten acumular costos de eventos específicos, campañas, inversiones, etc. | G9: =+VLOOKUP(A9,S0!$C$2:$I$89,5) -> * Crear varios tipos de Ordenes Internas | H9: =+VLOOKUP(A9,S0!$C$2:$I$89,6) -> * La data maestra luego de tener movimiento no puede ser eliminada | I9: 01 Adoptar | J9: 02 Media | K9: Detalle de asignación de los costos para la operación en planta y en campo. | M9: =+(VLOOKUP($A9,S0!$C$2:$Y$89,19)/8 * VLOOKUP($I9,Atributos!$A$28:$B32,2) * VLOOKUP($J9,Atributos!$A$22:$B26,2))/5 -> 0.05625 | N9: =+VLOOKUP($A9,S0!$C$2:$Y$89,20)/8 * VLOOKUP($I9,Atributos!$A$28:$B$31,2) * VLOOKUP($J9,Atributos!$A$22:$B$25,2)/5 -> 0.45 | O9: =+VLOOKUP($A9,S0!$C$2:$Y$89,21)/8 * VLOOKUP($I9,Atributos!$A$28:$B$31,2) * VLOOKUP($J9,Atributos!$A$22:$B$25,2)/5 -> 0.45 | P9: =+VLOOKUP($A9,S0!$C$2:$Y$89,22)/8 * VLOOKUP($I9,Atributos!$A$28:$B$31,2) * VLOOKUP($J9,Atributos!$A$22:$B$25,2)/5 -> 0.45 | Q9: =+VLOOKUP($A9,S0!$C$2:$Y$89,23)/8 * VLOOKUP($I9,Atributos!$A$28:$B$31,2) * VLOOKUP($J9,Atributos!$A$22:$B$25,2)/5 -> 0 | R9: =SUM(M9:P9) -> 1.40625 | S9: =+(VLOOKUP($A9,S0!$C$2:$Y$89,19)/8 * VLOOKUP($I9,Atributos!$A$28:$B$31,2) * VLOOKUP($J9,Atributos!$G$22:$H$25,2))/5 -> 0.0375 | T9: =+VLOOKUP($A9,S0!$C$2:$Y$89,20)/8 * VLOOKUP($I9,Atributos!$A$28:$B$31,2) * VLOOKUP($J9,Atributos!$G$22:$H$25,2)/5 -> 0.3 | U9: =+VLOOKUP($A9,S0!$C$2:$Y$89,21)/8 * VLOOKUP($I9,Atributos!$A$28:$B$31,2) * VLOOKUP($J9,Atributos!$G$22:$H$25,2)/5 -> 0.3 | V9: =+VLOOKUP($A9,S0!$C$2:$Y$89,22)/8 * VLOOKUP($I9,Atributos!$A$28:$B$31,2) * VLOOKUP($J9,Atributos!$G$22:$H$25,2)/5 -> 0.3 | W9: =+VLOOKUP($A9,S0!$C$2:$Y$89,23)/8 * VLOOKUP($I9,Atributos!$A$28:$B$31,2) * VLOOKUP($J9,Atributos!$G$22:$H$25,2)/5 -> 0 | X9: =SUM(S9:V9) -> 0.9375 | Y9: =(S9+M9)/2 -> 0.046875 | Z9: =(T9+N9)/2 -> 0.375 | AA9: =(U9+O9)/2 -> 0.375 | AB9: =(V9+P9)/2 -> 0.375 | AC9: =(W9+Q9)/2 -> 0 | AD9: =SUM(Y9:AB9) -> 1.171875
A10: CO-02_Planificación de Ingresos, costos y gastos(CO_P010) | B10: =+VLOOKUP(A10,S0!$C$2:$I$89,7) -> CO | C10: 1HB | D10: Financial Plan Data Upload from File | E10: =+VLOOKUP(A10,S0!$C$2:$I$89,3) -> Planificación de ingresos, costos y gastos, por centro de beneficio y centro de costos. Planificación de órdenes internas. | F10: =+VLOOKUP(A10,S0!$C$2:$I$89,4) -> Controlling permite planificar la estructura de costos y gastos de las futuras operaciones de la empresa para períodos determinados y efectuar comparaciones Real / Plan para su control. | G10: =+VLOOKUP(A10,S0!$C$2:$I$89,5) -> * Cargar diferentes Versione de planificación * Copiar de Real a Versión Plan * Copiar de Vérsión Plan a Versión Plan | H10: =+VLOOKUP(A10,S0!$C$2:$I$89,6) -> * El cálculo de planificación es por fuera de SAP * La planificación no es restrictiva solo informativa * Se puede planificar a nivel de ceco + clase de coste | I10: 01 Adoptar | J10: 01 Baja | L10: =+(VLOOKUP($A10,S0!$C$2:$Y$89,18)/8 * VLOOKUP($I10,Atributos!$A$28:$B$31,2) * VLOOKUP($J10,Atributos!$A$22:$B$25,2))/5 -> 0.0375 | M10: =+(VLOOKUP($A10,S0!$C$2:$Y$89,19)/8 * VLOOKUP($I10,Atributos!$A$28:$B33,2) * VLOOKUP($J10,Atributos!$A$22:$B27,2))/5 -> 0.075 | N10: =+VLOOKUP($A10,S0!$C$2:$Y$89,20)/8 * VLOOKUP($I10,Atributos!$A$28:$B$31,2) * VLOOKUP($J10,Atributos!$A$22:$B$25,2)/5 -> 0.6 | O10: =+VLOOKUP($A10,S0!$C$2:$Y$89,21)/8 * VLOOKUP($I10,Atributos!$A$28:$B$31,2) * VLOOKUP($J10,Atributos!$A$22:$B$25,2)/5 -> 1.2 | P10: =+VLOOKUP($A10,S0!$C$2:$Y$89,22)/8 * VLOOKUP($I10,Atributos!$A$28:$B$31,2) * VLOOKUP($J10,Atributos!$A$22:$B$25,2)/5 -> 0.3 | Q10: =+VLOOKUP($A10,S0!$C$2:$Y$89,23)/8 * VLOOKUP($I10,Atributos!$A$28:$B$31,2) * VLOOKUP($J10,Atributos!$A$22:$B$25,2)/5 -> 0.3 | R10: =SUM(M10:P10) -> 2.175 | S10: =+(VLOOKUP($A10,S0!$C$2:$Y$89,19)/8 * VLOOKUP($I10,Atributos!$A$28:$B$31,2) * VLOOKUP($J10,Atributos!$G$22:$H$25,2))/5 -> 0.05 | T10: =+VLOOKUP($A10,S0!$C$2:$Y$89,20)/8 * VLOOKUP($I10,Atributos!$A$28:$B$31,2) * VLOOKUP($J10,Atributos!$G$22:$H$25,2)/5 -> 0.4 | U10: =+VLOOKUP($A10,S0!$C$2:$Y$89,21)/8 * VLOOKUP($I10,Atributos!$A$28:$B$31,2) * VLOOKUP($J10,Atributos!$G$22:$H$25,2)/5 -> 0.8 | V10: =+VLOOKUP($A10,S0!$C$2:$Y$89,22)/8 * VLOOKUP($I10,Atributos!$A$28:$B$31,2) * VLOOKUP($J10,Atributos!$G$22:$H$25,2)/5 -> 0.2 | W10: =+VLOOKUP($A10,S0!$C$2:$Y$89,23)/8 * VLOOKUP($I10,Atributos!$A$28:$B$31,2) * VLOOKUP($J10,Atributos!$G$22:$H$25,2)/5 -> 0.2 | X10: =SUM(S10:V10) -> 1.45 | Y10: =(S10+M10)/2 -> 0.0625 | Z10: =(T10+N10)/2 -> 0.5 | AA10: =(U10+O10)/2 -> 1 | AB10: =(V10+P10)/2 -> 0.25 | AC10: =(W10+Q10)/2 -> 0.25 | AD10: =SUM(Y10:AB10) -> 1.8125
A11: CO-03_Control de Ingresos, costos y gastos(CO_P020) | B11: =+VLOOKUP(A11,S0!$C$2:$I$89,7) -> CO | C11: J54 | D11: Overhead Cost Accounting | E11: =+VLOOKUP(A11,S0!$C$2:$I$89,3) -> Imputación real a cuentas de ingresos, costos y gastos. Gestión de órdenes internas de gastos y de inversión. Creación de ciclos de distribución y de subreparto. | F11: =+VLOOKUP(A11,S0!$C$2:$I$89,4) -> Comprende los distintos procesos por los cuales se registran imputaciones reales en las cuentas contables de costos, gastos, ingresos e inversión, ya sea por medio de centros de costos, centros de beneficio u órdenes internas. La ordenes internas son objetos de costos que se usan para identificar operaciones específicas y temporales con el fin de facilitar un análisis. Estas se aplican para controlar proyectos, campañas, obras en curso, etc. Los ciclos de distribución y/o subreparto sirven para distribuir o trasladar los costos de objetos de costos origen a objetos de costos destino. El ciclo de distribución traslada a través de la misma clase de costo, mientras el subreparto requiere de la clase de coste secundaria. | G11: =+VLOOKUP(A11,S0!$C$2:$I$89,5) -> * Imputaciones a cecos * Imputaciones a diferentes clase de Ordenes ( Inversión, reales , estadisticas) * Ciclos de distribución con diferentes metodos ( % , VE, Importe Fijo , etc) * Ciclos de Subreparto diferentes métodos ( % , VE , importe Fijo , Etc) | H11: =+VLOOKUP(A11,S0!$C$2:$I$89,6) -> * Los Drivers de los ciclos de distribución y subreparto no son automaticos ; si se define que el valor es mensual entonces se debe actualizar . * Todo objeto de costo con movimiento no puede ser eliminado. | I11: 01 Adoptar | J11: 02 Media | K11: Revisión de driver para operaciones en planta y campo. | L11: =+(VLOOKUP($A11,S0!$C$2:$Y$89,18)/8 * VLOOKUP($I11,Atributos!$A$28:$B$31,2) * VLOOKUP($J11,Atributos!$A$22:$B$25,2))/5 -> 0.05625 | M11: =+(VLOOKUP($A11,S0!$C$2:$Y$89,19)/8 * VLOOKUP($I11,Atributos!$A$28:$B34,2) * VLOOKUP($J11,Atributos!$A$22:$B28,2))/5 -> 0.1125 | N11: =+VLOOKUP($A11,S0!$C$2:$Y$89,20)/8 * VLOOKUP($I11,Atributos!$A$28:$B$31,2) * VLOOKUP($J11,Atributos!$A$22:$B$25,2)/5 -> 0.9 | O11: =+VLOOKUP($A11,S0!$C$2:$Y$89,21)/8 * VLOOKUP($I11,Atributos!$A$28:$B$31,2) * VLOOKUP($J11,Atributos!$A$22:$B$25,2)/5 -> 1.8 | P11: =+VLOOKUP($A11,S0!$C$2:$Y$89,22)/8 * VLOOKUP($I11,Atributos!$A$28:$B$31,2) * VLOOKUP($J11,Atributos!$A$22:$B$25,2)/5 -> 0.45 | Q11: =+VLOOKUP($A11,S0!$C$2:$Y$89,23)/8 * VLOOKUP($I11,Atributos!$A$28:$B$31,2) * VLOOKUP($J11,Atributos!$A$22:$B$25,2)/5 -> 0.45 | R11: =SUM(M11:P11) -> 3.2625 | S11: =+(VLOOKUP($A11,S0!$C$2:$Y$89,19)/8 * VLOOKUP($I11,Atributos!$A$28:$B$31,2) * VLOOKUP($J11,Atributos!$G$22:$H$25,2))/5 -> 0.075 | T11: =+VLOOKUP($A11,S0!$C$2:$Y$89,20)/8 * VLOOKUP($I11,Atributos!$A$28:$B$31,2) * VLOOKUP($J11,Atributos!$G$22:$H$25,2)/5 -> 0.6 | U11: =+VLOOKUP($A11,S0!$C$2:$Y$89,21)/8 * VLOOKUP($I11,Atributos!$A$28:$B$31,2) * VLOOKUP($J11,Atributos!$G$22:$H$25,2)/5 -> 1.2 | V11: =+VLOOKUP($A11,S0!$C$2:$Y$89,22)/8 * VLOOKUP($I11,Atributos!$A$28:$B$31,2) * VLOOKUP($J11,Atributos!$G$22:$H$25,2)/5 -> 0.3 | W11: =+VLOOKUP($A11,S0!$C$2:$Y$89,23)/8 * VLOOKUP($I11,Atributos!$A$28:$B$31,2) * VLOOKUP($J11,Atributos!$G$22:$H$25,2)/5 -> 0.3 | X11: =SUM(S11:V11) -> 2.175 | Y11: =(S11+M11)/2 -> 0.09375 | Z11: =(T11+N11)/2 -> 0.75 | AA11: =(U11+O11)/2 -> 1.5 | AB11: =(V11+P11)/2 -> 0.375 | AC11: =(W11+Q11)/2 -> 0.375 | AD11: =SUM(Y11:AB11) -> 2.71875
A12: CO-04_Análisis de Rentabilidad(CO_P040) | B12: =+VLOOKUP(A12,S0!$C$2:$I$89,7) -> CO | C12: J55 | D12: Margin Analysis | E12: =+VLOOKUP(A12,S0!$C$2:$I$89,3) -> Definición características CO-PA. Subreparto de gastos. | F12: =+VLOOKUP(A12,S0!$C$2:$I$89,4) -> Es una herramienta que brinda SAP, para ayudar a las empresas a evaluar su rentabilidad mediante sus segmentos de mercado a partir de sus ventas, ganancias/pérdidas e información proveniente de otros módulos como finanzas, ventas y logística. Se tienen características como canal de ventas, línea de negocio, oficina de ventas, cliente, material, etc. dicha información puede ser analizada por periodos, ejercicio. | G12: =+VLOOKUP(A12,S0!$C$2:$I$89,5) -> * COPA - Análitico * COPA - Contable * Agregar caracteristicas Z* * Agregar caracteristicas despues de la activación de COPA * Ciclos de Subreparto de PA * Ejecución del TOP- DOW | H12: =+VLOOKUP(A12,S0!$C$2:$I$89,6) -> * COPA - Análitico ; existe la posibilidad que no cuadre exacto con la contabilidad ya que se usa para gestión * Los drivers del ciclo de subreparto no son automaticos . | I12: 01 Adoptar | J12: 01 Baja | L12: =+(VLOOKUP($A12,S0!$C$2:$Y$89,18)/8 * VLOOKUP($I12,Atributos!$A$28:$B$31,2) * VLOOKUP($J12,Atributos!$A$22:$B$25,2))/5 -> 0.0375 | M12: =+(VLOOKUP($A12,S0!$C$2:$Y$89,19)/8 * VLOOKUP($I12,Atributos!$A$28:$B35,2) * VLOOKUP($J12,Atributos!$A$22:$B29,2))/5 -> 0.075 | N12: =+VLOOKUP($A12,S0!$C$2:$Y$89,20)/8 * VLOOKUP($I12,Atributos!$A$28:$B$31,2) * VLOOKUP($J12,Atributos!$A$22:$B$25,2)/5 -> 0.6 | O12: =+VLOOKUP($A12,S0!$C$2:$Y$89,21)/8 * VLOOKUP($I12,Atributos!$A$28:$B$31,2) * VLOOKUP($J12,Atributos!$A$22:$B$25,2)/5 -> 1.2 | P12: =+VLOOKUP($A12,S0!$C$2:$Y$89,22)/8 * VLOOKUP($I12,Atributos!$A$28:$B$31,2) * VLOOKUP($J12,Atributos!$A$22:$B$25,2)/5 -> 0.3 | Q12: =+VLOOKUP($A12,S0!$C$2:$Y$89,23)/8 * VLOOKUP($I12,Atributos!$A$28:$B$31,2) * VLOOKUP($J12,Atributos!$A$22:$B$25,2)/5 -> 0.3 | R12: =SUM(M12:P12) -> 2.175 | S12: =+(VLOOKUP($A12,S0!$C$2:$Y$89,19)/8 * VLOOKUP($I12,Atributos!$A$28:$B$31,2) * VLOOKUP($J12,Atributos!$G$22:$H$25,2))/5 -> 0.05 | T12: =+VLOOKUP($A12,S0!$C$2:$Y$89,20)/8 * VLOOKUP($I12,Atributos!$A$28:$B$31,2) * VLOOKUP($J12,Atributos!$G$22:$H$25,2)/5 -> 0.4 | U12: =+VLOOKUP($A12,S0!$C$2:$Y$89,21)/8 * VLOOKUP($I12,Atributos!$A$28:$B$31,2) * VLOOKUP($J12,Atributos!$G$22:$H$25,2)/5 -> 0.8 | V12: =+VLOOKUP($A12,S0!$C$2:$Y$89,22)/8 * VLOOKUP($I12,Atributos!$A$28:$B$31,2) * VLOOKUP($J12,Atributos!$G$22:$H$25,2)/5 -> 0.2 | W12: =+VLOOKUP($A12,S0!$C$2:$Y$89,23)/8 * VLOOKUP($I12,Atributos!$A$28:$B$31,2) * VLOOKUP($J12,Atributos!$G$22:$H$25,2)/5 -> 0.2 | X12: =SUM(S12:V12) -> 1.45 | Y12: =(S12+M12)/2 -> 0.0625 | Z12: =(T12+N12)/2 -> 0.5 | AA12: =(U12+O12)/2 -> 1 | AB12: =(V12+P12)/2 -> 0.25 | AC12: =(W12+Q12)/2 -> 0.25 | AD12: =SUM(Y12:AB12) -> 1.8125
A13: CO-05_Reportes de Análisis(CO_P050) | B13: =+VLOOKUP(A13,S0!$C$2:$I$89,7) -> CO | C13: 4RC | D13: Integrated Financial Planning | E13: =+VLOOKUP(A13,S0!$C$2:$I$89,3) -> Reportes de Rentabilidad. Elaboración de reportes de gestión. Elaboración de estados financieros internos. | F13: =+VLOOKUP(A13,S0!$C$2:$I$89,4) -> Se refiere a los reportes de gastos por centros de costos, reportes de márgenes (por sociedad, unidad de negocio, etc.) y de estados financieros internos, por medio de la herramienta Report Painter. | G13: =+VLOOKUP(A13,S0!$C$2:$I$89,5) -> 0 | H13: =+VLOOKUP(A13,S0!$C$2:$I$89,6) -> * Los reportes son Report Writer no se pueden transformar en ALV | I13: 01 Adoptar | J13: 01 Baja | L13: =+(VLOOKUP($A13,S0!$C$2:$Y$89,18)/8 * VLOOKUP($I13,Atributos!$A$28:$B$31,2) * VLOOKUP($J13,Atributos!$A$22:$B$25,2))/5 -> 0.0375 | M13: =+(VLOOKUP($A13,S0!$C$2:$Y$89,19)/8 * VLOOKUP($I13,Atributos!$A$28:$B36,2) * VLOOKUP($J13,Atributos!$A$22:$B30,2))/5 -> 0.15 | N13: =+VLOOKUP($A13,S0!$C$2:$Y$89,20)/8 * VLOOKUP($I13,Atributos!$A$28:$B$31,2) * VLOOKUP($J13,Atributos!$A$22:$B$25,2)/5 -> 0.15 | O13: =+VLOOKUP($A13,S0!$C$2:$Y$89,21)/8 * VLOOKUP($I13,Atributos!$A$28:$B$31,2) * VLOOKUP($J13,Atributos!$A$22:$B$25,2)/5 -> 0.6 | P13: =+VLOOKUP($A13,S0!$C$2:$Y$89,22)/8 * VLOOKUP($I13,Atributos!$A$28:$B$31,2) * VLOOKUP($J13,Atributos!$A$22:$B$25,2)/5 -> 0 | Q13: =+VLOOKUP($A13,S0!$C$2:$Y$89,23)/8 * VLOOKUP($I13,Atributos!$A$28:$B$31,2) * VLOOKUP($J13,Atributos!$A$22:$B$25,2)/5 -> 0.3 | R13: =SUM(M13:P13) -> 0.9 | S13: =+(VLOOKUP($A13,S0!$C$2:$Y$89,19)/8 * VLOOKUP($I13,Atributos!$A$28:$B$31,2) * VLOOKUP($J13,Atributos!$G$22:$H$25,2))/5 -> 0.05 | T13: =+VLOOKUP($A13,S0!$C$2:$Y$89,20)/8 * VLOOKUP($I13,Atributos!$A$28:$B$31,2) * VLOOKUP($J13,Atributos!$G$22:$H$25,2)/5 -> 0.1 | U13: =+VLOOKUP($A13,S0!$C$2:$Y$89,21)/8 * VLOOKUP($I13,Atributos!$A$28:$B$31,2) * VLOOKUP($J13,Atributos!$G$22:$H$25,2)/5 -> 0.4 | V13: =+VLOOKUP($A13,S0!$C$2:$Y$89,22)/8 * VLOOKUP($I13,Atributos!$A$28:$B$31,2) * VLOOKUP($J13,Atributos!$G$22:$H$25,2)/5 -> 0 | W13: =+VLOOKUP($A13,S0!$C$2:$Y$89,23)/8 * VLOOKUP($I13,Atributos!$A$28:$B$31,2) * VLOOKUP($J13,Atributos!$G$22:$H$25,2)/5 -> 0.2 | X13: =SUM(S13:V13) -> 0.55 | Y13: =(S13+M13)/2 -> 0.1 | Z13: =(T13+N13)/2 -> 0.125 | AA13: =(U13+O13)/2 -> 0.5 | AB13: =(V13+P13)/2 -> 0 | AC13: =(W13+Q13)/2 -> 0.25 | AD13: =SUM(Y13:AB13) -> 0.725
A14: CO-06_Cierre de Controlling(CO_P060) | B14: =+VLOOKUP(A14,S0!$C$2:$I$89,7) -> CO | C14: J54 | D14: Overhead Cost Accounting | E14: =+VLOOKUP(A14,S0!$C$2:$I$89,3) -> Análisis de ingresos en centros de beneficio. Análisis de costos y gastos en centros de costo y órdenes. Liquidación de ordenes internas. Ejecución de Distribución / Subreparto de gasto. | F14: =+VLOOKUP(A14,S0!$C$2:$I$89,4) -> En el cierre de Controlling, se tienen los siguientes eventos: - Análisis de ingresos en centros de beneficio: El proceso de análisis de los ingresos debe ser periodico durante el mes. - Análisis de costos y gastos en centros de costo y órdenes: El proceso de análisis de los costos y gastos deben ser periodicos durante el mes. - Liquidación de las ordenes internas: Las ordenes son acumuladores de gasto temporales por lo que en el cierre del periodo se debe realizar el proceso de liquidación con el objetivo que queden en cero. - Ejecución de distribución / subreparto de gasto: Este proceso comprende a las distribuciones de gastos operativos entre las unidades de negocio o según el modelo/criterio que determine la empresa. | G14: =+VLOOKUP(A14,S0!$C$2:$I$89,5) -> 0 | H14: =+VLOOKUP(A14,S0!$C$2:$I$89,6) -> 0 | I14: 01 Adoptar | J14: 03 Alta | K14: El cierre de costos debe contemplar las actividades propias de campo y planta. Considerando que en campo existen otros procedimientos para el costeo de la producción. | L14: =+(VLOOKUP($A14,S0!$C$2:$Y$89,18)/8 * VLOOKUP($I14,Atributos!$A$28:$B$31,2) * VLOOKUP($J14,Atributos!$A$22:$B$25,2))/5 -> 0.075 | M14: =+(VLOOKUP($A14,S0!$C$2:$Y$89,19)/8 * VLOOKUP($I14,Atributos!$A$28:$B37,2) * VLOOKUP($J14,Atributos!$A$22:$B31,2))/5 -> 0.3 | N14: =+VLOOKUP($A14,S0!$C$2:$Y$89,20)/8 * VLOOKUP($I14,Atributos!$A$28:$B$31,2) * VLOOKUP($J14,Atributos!$A$22:$B$25,2)/5 -> 1.2 | O14: =+VLOOKUP($A14,S0!$C$2:$Y$89,21)/8 * VLOOKUP($I14,Atributos!$A$28:$B$31,2) * VLOOKUP($J14,Atributos!$A$22:$B$25,2)/5 -> 2.4 | P14: =+VLOOKUP($A14,S0!$C$2:$Y$89,22)/8 * VLOOKUP($I14,Atributos!$A$28:$B$31,2) * VLOOKUP($J14,Atributos!$A$22:$B$25,2)/5 -> 0.6 | Q14: =+VLOOKUP($A14,S0!$C$2:$Y$89,23)/8 * VLOOKUP($I14,Atributos!$A$28:$B$31,2) * VLOOKUP($J14,Atributos!$A$22:$B$25,2)/5 -> 0.6 | R14: =SUM(M14:P14) -> 4.5 | S14: =+(VLOOKUP($A14,S0!$C$2:$Y$89,19)/8 * VLOOKUP($I14,Atributos!$A$28:$B$31,2) * VLOOKUP($J14,Atributos!$G$22:$H$25,2))/5 -> 0.1 | T14: =+VLOOKUP($A14,S0!$C$2:$Y$89,20)/8 * VLOOKUP($I14,Atributos!$A$28:$B$31,2) * VLOOKUP($J14,Atributos!$G$22:$H$25,2)/5 -> 0.8 | U14: =+VLOOKUP($A14,S0!$C$2:$Y$89,21)/8 * VLOOKUP($I14,Atributos!$A$28:$B$31,2) * VLOOKUP($J14,Atributos!$G$22:$H$25,2)/5 -> 1.6 | V14: =+VLOOKUP($A14,S0!$C$2:$Y$89,22)/8 * VLOOKUP($I14,Atributos!$A$28:$B$31,2) * VLOOKUP($J14,Atributos!$G$22:$H$25,2)/5 -> 0.4 | W14: =+VLOOKUP($A14,S0!$C$2:$Y$89,23)/8 * VLOOKUP($I14,Atributos!$A$28:$B$31,2) * VLOOKUP($J14,Atributos!$G$22:$H$25,2)/5 -> 0.4 | X14: =SUM(S14:V14) -> 2.9 | Y14: =(S14+M14)/2 -> 0.2 | Z14: =(T14+N14)/2 -> 1 | AA14: =(U14+O14)/2 -> 2 | AB14: =(V14+P14)/2 -> 0.5 | AC14: =(W14+Q14)/2 -> 0.5 | AD14: =SUM(Y14:AB14) -> 3.7
A15: CO-07_Costos de producción(CO_P030) | B15: =+VLOOKUP(A15,S0!$C$2:$I$89,7) -> CO | C15: 2QW N/A S0p | D15: Analytics for Production Unit - Plan/Actual Production Cost | E15: =+VLOOKUP(A15,S0!$C$2:$I$89,3) -> 0 | F15: =+VLOOKUP(A15,S0!$C$2:$I$89,4) -> 0 | G15: =+VLOOKUP(A15,S0!$C$2:$I$89,5) -> 0 | H15: =+VLOOKUP(A15,S0!$C$2:$I$89,6) -> 0 | I15: 02 Ajustar | J15: 03 Alta | K15: Modelamiento del costo de producción en campo. | L15: =+(VLOOKUP($A15,S0!$C$2:$Y$89,18)/8 * VLOOKUP($I15,Atributos!$A$28:$B$31,2) * VLOOKUP($J15,Atributos!$A$22:$B$25,2))/5 -> 0.1125 | M15: =+(VLOOKUP($A15,S0!$C$2:$Y$89,19)/8 * VLOOKUP($I15,Atributos!$A$28:$B38,2) * VLOOKUP($J15,Atributos!$A$22:$B32,2))/5 -> 0.45 | N15: =+VLOOKUP($A15,S0!$C$2:$Y$89,20)/8 * VLOOKUP($I15,Atributos!$A$28:$B$31,2) * VLOOKUP($J15,Atributos!$A$22:$B$25,2)/5 -> 1.8 | O15: =+VLOOKUP($A15,S0!$C$2:$Y$89,21)/8 * VLOOKUP($I15,Atributos!$A$28:$B$31,2) * VLOOKUP($J15,Atributos!$A$22:$B$25,2)/5 -> 3.6 | P15: =+VLOOKUP($A15,S0!$C$2:$Y$89,22)/8 * VLOOKUP($I15,Atributos!$A$28:$B$31,2) * VLOOKUP($J15,Atributos!$A$22:$B$25,2)/5 -> 0.9 | Q15: =+VLOOKUP($A15,S0!$C$2:$Y$89,23)/8 * VLOOKUP($I15,Atributos!$A$28:$B$31,2) * VLOOKUP($J15,Atributos!$A$22:$B$25,2)/5 -> 0.9 | R15: =SUM(M15:P15) -> 6.75 | S15: =+(VLOOKUP($A15,S0!$C$2:$Y$89,19)/8 * VLOOKUP($I15,Atributos!$A$28:$B$31,2) * VLOOKUP($J15,Atributos!$G$22:$H$25,2))/5 -> 0.15 | T15: =+VLOOKUP($A15,S0!$C$2:$Y$89,20)/8 * VLOOKUP($I15,Atributos!$A$28:$B$31,2) * VLOOKUP($J15,Atributos!$G$22:$H$25,2)/5 -> 1.2 | U15: =+VLOOKUP($A15,S0!$C$2:$Y$89,21)/8 * VLOOKUP($I15,Atributos!$A$28:$B$31,2) * VLOOKUP($J15,Atributos!$G$22:$H$25,2)/5 -> 2.4 | V15: =+VLOOKUP($A15,S0!$C$2:$Y$89,22)/8 * VLOOKUP($I15,Atributos!$A$28:$B$31,2) * VLOOKUP($J15,Atributos!$G$22:$H$25,2)/5 -> 0.6 | W15: =+VLOOKUP($A15,S0!$C$2:$Y$89,23)/8 * VLOOKUP($I15,Atributos!$A$28:$B$31,2) * VLOOKUP($J15,Atributos!$G$22:$H$25,2)/5 -> 0.6 | X15: =SUM(S15:V15) -> 4.35 | Y15: =(S15+M15)/2 -> 0.3 | Z15: =(T15+N15)/2 -> 1.5 | AA15: =(U15+O15)/2 -> 3 | AB15: =(V15+P15)/2 -> 0.75 | AC15: =(W15+Q15)/2 -> 0.75 | AD15: =SUM(Y15:AB15) -> 5.55
A16: EWM-00_Estructura organizativa(EWM_EO1) | B16: =+VLOOKUP(A16,S0!$C$2:$I$89,7) -> EWM | C16: N/A EO | D16: No aplica en Estructura Organizativa | E16: =+VLOOKUP(A16,S0!$C$2:$I$89,3) -> Número de almacén Tipos de almacén Áreas de almacenamiento | F16: =+VLOOKUP(A16,S0!$C$2:$I$89,4) -> Se detallan los niveles en los que se subdivide centro de distribución | G16: =+VLOOKUP(A16,S0!$C$2:$I$89,5) -> 0 | H16: =+VLOOKUP(A16,S0!$C$2:$I$89,6) -> 0 | I16: 04 Abstener | J16: 01 Baja | L16: =+(VLOOKUP($A16,S0!$C$2:$Y$89,18)/8 * VLOOKUP($I16,Atributos!$A$28:$B$31,2) * VLOOKUP($J16,Atributos!$A$22:$B$25,2))/5 -> 0 | M16: =+(VLOOKUP($A16,S0!$C$2:$Y$89,19)/8 * VLOOKUP($I16,Atributos!$A$28:$B39,2) * VLOOKUP($J16,Atributos!$A$22:$B33,2))/5 -> 0.075 | N16: =+VLOOKUP($A16,S0!$C$2:$Y$89,20)/8 * VLOOKUP($I16,Atributos!$A$28:$B$31,2) * VLOOKUP($J16,Atributos!$A$22:$B$25,2)/5 -> 0 | O16: =+VLOOKUP($A16,S0!$C$2:$Y$89,21)/8 * VLOOKUP($I16,Atributos!$A$28:$B$31,2) * VLOOKUP($J16,Atributos!$A$22:$B$25,2)/5 -> 0 | P16: =+VLOOKUP($A16,S0!$C$2:$Y$89,22)/8 * VLOOKUP($I16,Atributos!$A$28:$B$31,2) * VLOOKUP($J16,Atributos!$A$22:$B$25,2)/5 -> 0 | Q16: =+VLOOKUP($A16,S0!$C$2:$Y$89,23)/8 * VLOOKUP($I16,Atributos!$A$28:$B$31,2) * VLOOKUP($J16,Atributos!$A$22:$B$25,2)/5 -> 0 | R16: =SUM(M16:P16) -> 0.075 | S16: =+(VLOOKUP($A16,S0!$C$2:$Y$89,19)/8 * VLOOKUP($I16,Atributos!$A$28:$B$31,2) * VLOOKUP($J16,Atributos!$G$22:$H$25,2))/5 -> 0 | T16: =+VLOOKUP($A16,S0!$C$2:$Y$89,20)/8 * VLOOKUP($I16,Atributos!$A$28:$B$31,2) * VLOOKUP($J16,Atributos!$G$22:$H$25,2)/5 -> 0 | U16: =+VLOOKUP($A16,S0!$C$2:$Y$89,21)/8 * VLOOKUP($I16,Atributos!$A$28:$B$31,2) * VLOOKUP($J16,Atributos!$G$22:$H$25,2)/5 -> 0 | V16: =+VLOOKUP($A16,S0!$C$2:$Y$89,22)/8 * VLOOKUP($I16,Atributos!$A$28:$B$31,2) * VLOOKUP($J16,Atributos!$G$22:$H$25,2)/5 -> 0 | W16: =+VLOOKUP($A16,S0!$C$2:$Y$89,23)/8 * VLOOKUP($I16,Atributos!$A$28:$B$31,2) * VLOOKUP($J16,Atributos!$G$22:$H$25,2)/5 -> 0 | X16: =SUM(S16:V16) -> 0 | Y16: =(S16+M16)/2 -> 0.0375 | Z16: =(T16+N16)/2 -> 0 | AA16: =(U16+O16)/2 -> 0 | AB16: =(V16+P16)/2 -> 0 | AC16: =(W16+Q16)/2 -> 0 | AD16: =SUM(Y16:AB16) -> 0.0375
A17: EWM-01_Administración de Datos Maestros(EWM_M010) | B17: =+VLOOKUP(A17,S0!$C$2:$I$89,7) -> EWM | C17: N/A Master Data | D17: No aplica en Maestros | E17: =+VLOOKUP(A17,S0!$C$2:$I$89,3) -> Ampliación de materiales: Indicadores de tipo de almacén Indicadores de área de almacenamiento | F17: =+VLOOKUP(A17,S0!$C$2:$I$89,4) -> Se actualiza la información del material para colocarle los indicadores correspondientes a ingreso y salida. | G17: =+VLOOKUP(A17,S0!$C$2:$I$89,5) -> 0 | H17: =+VLOOKUP(A17,S0!$C$2:$I$89,6) -> 0 | I17: 04 Abstener | J17: 01 Baja | L17: =+(VLOOKUP($A17,S0!$C$2:$Y$89,18)/8 * VLOOKUP($I17,Atributos!$A$28:$B$31,2) * VLOOKUP($J17,Atributos!$A$22:$B$25,2))/5 -> 0 | M17: =+(VLOOKUP($A17,S0!$C$2:$Y$89,19)/8 * VLOOKUP($I17,Atributos!$A$28:$B40,2) * VLOOKUP($J17,Atributos!$A$22:$B34,2))/5 -> 0.075 | N17: =+VLOOKUP($A17,S0!$C$2:$Y$89,20)/8 * VLOOKUP($I17,Atributos!$A$28:$B$31,2) * VLOOKUP($J17,Atributos!$A$22:$B$25,2)/5 -> 0 | O17: =+VLOOKUP($A17,S0!$C$2:$Y$89,21)/8 * VLOOKUP($I17,Atributos!$A$28:$B$31,2) * VLOOKUP($J17,Atributos!$A$22:$B$25,2)/5 -> 0 | P17: =+VLOOKUP($A17,S0!$C$2:$Y$89,22)/8 * VLOOKUP($I17,Atributos!$A$28:$B$31,2) * VLOOKUP($J17,Atributos!$A$22:$B$25,2)/5 -> 0 | Q17: =+VLOOKUP($A17,S0!$C$2:$Y$89,23)/8 * VLOOKUP($I17,Atributos!$A$28:$B$31,2) * VLOOKUP($J17,Atributos!$A$22:$B$25,2)/5 -> 0 | R17: =SUM(M17:P17) -> 0.075 | S17: =+(VLOOKUP($A17,S0!$C$2:$Y$89,19)/8 * VLOOKUP($I17,Atributos!$A$28:$B$31,2) * VLOOKUP($J17,Atributos!$G$22:$H$25,2))/5 -> 0 | T17: =+VLOOKUP($A17,S0!$C$2:$Y$89,20)/8 * VLOOKUP($I17,Atributos!$A$28:$B$31,2) * VLOOKUP($J17,Atributos!$G$22:$H$25,2)/5 -> 0 | U17: =+VLOOKUP($A17,S0!$C$2:$Y$89,21)/8 * VLOOKUP($I17,Atributos!$A$28:$B$31,2) * VLOOKUP($J17,Atributos!$G$22:$H$25,2)/5 -> 0 | V17: =+VLOOKUP($A17,S0!$C$2:$Y$89,22)/8 * VLOOKUP($I17,Atributos!$A$28:$B$31,2) * VLOOKUP($J17,Atributos!$G$22:$H$25,2)/5 -> 0 | W17: =+VLOOKUP($A17,S0!$C$2:$Y$89,23)/8 * VLOOKUP($I17,Atributos!$A$28:$B$31,2) * VLOOKUP($J17,Atributos!$G$22:$H$25,2)/5 -> 0 | X17: =SUM(S17:V17) -> 0 | Y17: =(S17+M17)/2 -> 0.0375 | Z17: =(T17+N17)/2 -> 0 | AA17: =(U17+O17)/2 -> 0 | AB17: =(V17+P17)/2 -> 0 | AC17: =(W17+Q17)/2 -> 0 | AD17: =SUM(Y17:AB17) -> 0.0375
A18: EWM-02_Procesos de entrada (EWM_P010) | B18: =+VLOOKUP(A18,S0!$C$2:$I$89,7) -> EWM | C18: 4RO N/A S0p | D18: Inbound Processing | E18: =+VLOOKUP(A18,S0!$C$2:$I$89,3) -> Orden de compra o ingreso directo: Generación de la entrega entrante Modificación de la entrega/contabilización Creación de la orden de almacén Confirmación de de la orden | F18: =+VLOOKUP(A18,S0!$C$2:$I$89,4) -> El proceso de ingreso permite brindar soporte a las actividades ejecutadas desde la recepción de la mercadería hasta la colocación de los materiales en la ubicación final | G18: =+VLOOKUP(A18,S0!$C$2:$I$89,5) -> - Ingreso por compra - Ingreso directo sin pedido - Ingreso por traslado | H18: =+VLOOKUP(A18,S0!$C$2:$I$89,6) -> 0 | I18: 04 Abstener | J18: 01 Baja | L18: =+(VLOOKUP($A18,S0!$C$2:$Y$89,18)/8 * VLOOKUP($I18,Atributos!$A$28:$B$31,2) * VLOOKUP($J18,Atributos!$A$22:$B$25,2))/5 -> 0 | M18: =+(VLOOKUP($A18,S0!$C$2:$Y$89,19)/8 * VLOOKUP($I18,Atributos!$A$28:$B41,2) * VLOOKUP($J18,Atributos!$A$22:$B35,2))/5 -> 0.4 | N18: =+VLOOKUP($A18,S0!$C$2:$Y$89,20)/8 * VLOOKUP($I18,Atributos!$A$28:$B$31,2) * VLOOKUP($J18,Atributos!$A$22:$B$25,2)/5 -> 0 | O18: =+VLOOKUP($A18,S0!$C$2:$Y$89,21)/8 * VLOOKUP($I18,Atributos!$A$28:$B$31,2) * VLOOKUP($J18,Atributos!$A$22:$B$25,2)/5 -> 0 | P18: =+VLOOKUP($A18,S0!$C$2:$Y$89,22)/8 * VLOOKUP($I18,Atributos!$A$28:$B$31,2) * VLOOKUP($J18,Atributos!$A$22:$B$25,2)/5 -> 0 | Q18: =+VLOOKUP($A18,S0!$C$2:$Y$89,23)/8 * VLOOKUP($I18,Atributos!$A$28:$B$31,2) * VLOOKUP($J18,Atributos!$A$22:$B$25,2)/5 -> 0 | R18: =SUM(M18:P18) -> 0.4 | S18: =+(VLOOKUP($A18,S0!$C$2:$Y$89,19)/8 * VLOOKUP($I18,Atributos!$A$28:$B$31,2) * VLOOKUP($J18,Atributos!$G$22:$H$25,2))/5 -> 0 | T18: =+VLOOKUP($A18,S0!$C$2:$Y$89,20)/8 * VLOOKUP($I18,Atributos!$A$28:$B$31,2) * VLOOKUP($J18,Atributos!$G$22:$H$25,2)/5 -> 0 | U18: =+VLOOKUP($A18,S0!$C$2:$Y$89,21)/8 * VLOOKUP($I18,Atributos!$A$28:$B$31,2) * VLOOKUP($J18,Atributos!$G$22:$H$25,2)/5 -> 0 | V18: =+VLOOKUP($A18,S0!$C$2:$Y$89,22)/8 * VLOOKUP($I18,Atributos!$A$28:$B$31,2) * VLOOKUP($J18,Atributos!$G$22:$H$25,2)/5 -> 0 | W18: =+VLOOKUP($A18,S0!$C$2:$Y$89,23)/8 * VLOOKUP($I18,Atributos!$A$28:$B$31,2) * VLOOKUP($J18,Atributos!$G$22:$H$25,2)/5 -> 0 | X18: =SUM(S18:V18) -> 0 | Y18: =(S18+M18)/2 -> 0.2 | Z18: =(T18+N18)/2 -> 0 | AA18: =(U18+O18)/2 -> 0 | AB18: =(V18+P18)/2 -> 0 | AC18: =(W18+Q18)/2 -> 0 | AD18: =SUM(Y18:AB18) -> 0.2
A19: EWM-03_Procesos de salida (EWM_P020) | B19: =+VLOOKUP(A19,S0!$C$2:$I$89,7) -> EWM | C19: 4RP N/A S0p | D19: Outbound Processing | E19: =+VLOOKUP(A19,S0!$C$2:$I$89,3) -> Pedido de venta o salida directa: Generación de la entrega de salida Creación de la orden de almacén Confirmación de de la orden Contabilización de la entrega de salida | F19: =+VLOOKUP(A19,S0!$C$2:$I$89,4) -> El proceso de salida permite brindar soporte a las actividades ejecutadas desde la extracción de la recepción de la mercadería hasta la colocación de los materiales en la ubicación final | G19: =+VLOOKUP(A19,S0!$C$2:$I$89,5) -> -Salida por venta -Salida por consumo directo -Salida por traslado | H19: =+VLOOKUP(A19,S0!$C$2:$I$89,6) -> 0 | I19: 04 Abstener | J19: 01 Baja | L19: =+(VLOOKUP($A19,S0!$C$2:$Y$89,18)/8 * VLOOKUP($I19,Atributos!$A$28:$B$31,2) * VLOOKUP($J19,Atributos!$A$22:$B$25,2))/5 -> 0 | M19: =+(VLOOKUP($A19,S0!$C$2:$Y$89,19)/8 * VLOOKUP($I19,Atributos!$A$28:$B42,2) * VLOOKUP($J19,Atributos!$A$22:$B36,2))/5 -> 0.375 | N19: =+VLOOKUP($A19,S0!$C$2:$Y$89,20)/8 * VLOOKUP($I19,Atributos!$A$28:$B$31,2) * VLOOKUP($J19,Atributos!$A$22:$B$25,2)/5 -> 0 | O19: =+VLOOKUP($A19,S0!$C$2:$Y$89,21)/8 * VLOOKUP($I19,Atributos!$A$28:$B$31,2) * VLOOKUP($J19,Atributos!$A$22:$B$25,2)/5 -> 0 | P19: =+VLOOKUP($A19,S0!$C$2:$Y$89,22)/8 * VLOOKUP($I19,Atributos!$A$28:$B$31,2) * VLOOKUP($J19,Atributos!$A$22:$B$25,2)/5 -> 0 | Q19: =+VLOOKUP($A19,S0!$C$2:$Y$89,23)/8 * VLOOKUP($I19,Atributos!$A$28:$B$31,2) * VLOOKUP($J19,Atributos!$A$22:$B$25,2)/5 -> 0 | R19: =SUM(M19:P19) -> 0.375 | S19: =+(VLOOKUP($A19,S0!$C$2:$Y$89,19)/8 * VLOOKUP($I19,Atributos!$A$28:$B$31,2) * VLOOKUP($J19,Atributos!$G$22:$H$25,2))/5 -> 0 | T19: =+VLOOKUP($A19,S0!$C$2:$Y$89,20)/8 * VLOOKUP($I19,Atributos!$A$28:$B$31,2) * VLOOKUP($J19,Atributos!$G$22:$H$25,2)/5 -> 0 | U19: =+VLOOKUP($A19,S0!$C$2:$Y$89,21)/8 * VLOOKUP($I19,Atributos!$A$28:$B$31,2) * VLOOKUP($J19,Atributos!$G$22:$H$25,2)/5 -> 0 | V19: =+VLOOKUP($A19,S0!$C$2:$Y$89,22)/8 * VLOOKUP($I19,Atributos!$A$28:$B$31,2) * VLOOKUP($J19,Atributos!$G$22:$H$25,2)/5 -> 0 | W19: =+VLOOKUP($A19,S0!$C$2:$Y$89,23)/8 * VLOOKUP($I19,Atributos!$A$28:$B$31,2) * VLOOKUP($J19,Atributos!$G$22:$H$25,2)/5 -> 0 | X19: =SUM(S19:V19) -> 0 | Y19: =(S19+M19)/2 -> 0.1875 | Z19: =(T19+N19)/2 -> 0 | AA19: =(U19+O19)/2 -> 0 | AB19: =(V19+P19)/2 -> 0 | AC19: =(W19+Q19)/2 -> 0 | AD19: =SUM(Y19:AB19) -> 0.1875
A20: EWM-04_Procesos internos (EWM_P030) | B20: =+VLOOKUP(A20,S0!$C$2:$I$89,7) -> EWM | C20: 4RQ 4RS N/A S0p | D20: Ad Hoc goods Issue / Replenishment | E20: =+VLOOKUP(A20,S0!$C$2:$I$89,3) -> Cambio de ubicación individual Cambio de ubicaión masivo Cambio de tipo de stock | F20: =+VLOOKUP(A20,S0!$C$2:$I$89,4) -> Los procesos dentro del almacén pueden ser mapeados a detalle en el sistema para reflejar los cambios de ubicación y/o tipos de stock | G20: =+VLOOKUP(A20,S0!$C$2:$I$89,5) -> -Cambio de ubicación individual -Cambio de ubicación masivo -Cambio de tipo de stock | H20: =+VLOOKUP(A20,S0!$C$2:$I$89,6) -> 0 | I20: 04 Abstener | J20: 01 Baja | L20: =+(VLOOKUP($A20,S0!$C$2:$Y$89,18)/8 * VLOOKUP($I20,Atributos!$A$28:$B$31,2) * VLOOKUP($J20,Atributos!$A$22:$B$25,2))/5 -> 0 | M20: =+(VLOOKUP($A20,S0!$C$2:$Y$89,19)/8 * VLOOKUP($I20,Atributos!$A$28:$B43,2) * VLOOKUP($J20,Atributos!$A$22:$B37,2))/5 -> 0.375 | N20: =+VLOOKUP($A20,S0!$C$2:$Y$89,20)/8 * VLOOKUP($I20,Atributos!$A$28:$B$31,2) * VLOOKUP($J20,Atributos!$A$22:$B$25,2)/5 -> 0 | O20: =+VLOOKUP($A20,S0!$C$2:$Y$89,21)/8 * VLOOKUP($I20,Atributos!$A$28:$B$31,2) * VLOOKUP($J20,Atributos!$A$22:$B$25,2)/5 -> 0 | P20: =+VLOOKUP($A20,S0!$C$2:$Y$89,22)/8 * VLOOKUP($I20,Atributos!$A$28:$B$31,2) * VLOOKUP($J20,Atributos!$A$22:$B$25,2)/5 -> 0 | Q20: =+VLOOKUP($A20,S0!$C$2:$Y$89,23)/8 * VLOOKUP($I20,Atributos!$A$28:$B$31,2) * VLOOKUP($J20,Atributos!$A$22:$B$25,2)/5 -> 0 | R20: =SUM(M20:P20) -> 0.375 | S20: =+(VLOOKUP($A20,S0!$C$2:$Y$89,19)/8 * VLOOKUP($I20,Atributos!$A$28:$B$31,2) * VLOOKUP($J20,Atributos!$G$22:$H$25,2))/5 -> 0 | T20: =+VLOOKUP($A20,S0!$C$2:$Y$89,20)/8 * VLOOKUP($I20,Atributos!$A$28:$B$31,2) * VLOOKUP($J20,Atributos!$G$22:$H$25,2)/5 -> 0 | U20: =+VLOOKUP($A20,S0!$C$2:$Y$89,21)/8 * VLOOKUP($I20,Atributos!$A$28:$B$31,2) * VLOOKUP($J20,Atributos!$G$22:$H$25,2)/5 -> 0 | V20: =+VLOOKUP($A20,S0!$C$2:$Y$89,22)/8 * VLOOKUP($I20,Atributos!$A$28:$B$31,2) * VLOOKUP($J20,Atributos!$G$22:$H$25,2)/5 -> 0 | W20: =+VLOOKUP($A20,S0!$C$2:$Y$89,23)/8 * VLOOKUP($I20,Atributos!$A$28:$B$31,2) * VLOOKUP($J20,Atributos!$G$22:$H$25,2)/5 -> 0 | X20: =SUM(S20:V20) -> 0 | Y20: =(S20+M20)/2 -> 0.1875 | Z20: =(T20+N20)/2 -> 0 | AA20: =(U20+O20)/2 -> 0 | AB20: =(V20+P20)/2 -> 0 | AC20: =(W20+Q20)/2 -> 0 | AD20: =SUM(Y20:AB20) -> 0.1875
A21: EWM-05_Inventario (EWM_P040) | B21: =+VLOOKUP(A21,S0!$C$2:$I$89,7) -> EWM | C21: 4RR | D21: Physical Inventory | E21: =+VLOOKUP(A21,S0!$C$2:$I$89,3) -> Toma de inventario por material Toma de inventario por ubicación | F21: =+VLOOKUP(A21,S0!$C$2:$I$89,4) -> Proceso de conteo de materiales y/o ubicaciones con mayor precisión | G21: =+VLOOKUP(A21,S0!$C$2:$I$89,5) -> -Toma de inventario por material sin diferencia -Tomoa de inventario por ubicación con diferencia | H21: =+VLOOKUP(A21,S0!$C$2:$I$89,6) -> 0 | I21: 04 Abstener | J21: 01 Baja | L21: =+(VLOOKUP($A21,S0!$C$2:$Y$89,18)/8 * VLOOKUP($I21,Atributos!$A$28:$B$31,2) * VLOOKUP($J21,Atributos!$A$22:$B$25,2))/5 -> 0 | M21: =+(VLOOKUP($A21,S0!$C$2:$Y$89,19)/8 * VLOOKUP($I21,Atributos!$A$28:$B44,2) * VLOOKUP($J21,Atributos!$A$22:$B38,2))/5 -> 0.375 | N21: =+VLOOKUP($A21,S0!$C$2:$Y$89,20)/8 * VLOOKUP($I21,Atributos!$A$28:$B$31,2) * VLOOKUP($J21,Atributos!$A$22:$B$25,2)/5 -> 0 | O21: =+VLOOKUP($A21,S0!$C$2:$Y$89,21)/8 * VLOOKUP($I21,Atributos!$A$28:$B$31,2) * VLOOKUP($J21,Atributos!$A$22:$B$25,2)/5 -> 0 | P21: =+VLOOKUP($A21,S0!$C$2:$Y$89,22)/8 * VLOOKUP($I21,Atributos!$A$28:$B$31,2) * VLOOKUP($J21,Atributos!$A$22:$B$25,2)/5 -> 0 | Q21: =+VLOOKUP($A21,S0!$C$2:$Y$89,23)/8 * VLOOKUP($I21,Atributos!$A$28:$B$31,2) * VLOOKUP($J21,Atributos!$A$22:$B$25,2)/5 -> 0 | R21: =SUM(M21:P21) -> 0.375 | S21: =+(VLOOKUP($A21,S0!$C$2:$Y$89,19)/8 * VLOOKUP($I21,Atributos!$A$28:$B$31,2) * VLOOKUP($J21,Atributos!$G$22:$H$25,2))/5 -> 0 | T21: =+VLOOKUP($A21,S0!$C$2:$Y$89,20)/8 * VLOOKUP($I21,Atributos!$A$28:$B$31,2) * VLOOKUP($J21,Atributos!$G$22:$H$25,2)/5 -> 0 | U21: =+VLOOKUP($A21,S0!$C$2:$Y$89,21)/8 * VLOOKUP($I21,Atributos!$A$28:$B$31,2) * VLOOKUP($J21,Atributos!$G$22:$H$25,2)/5 -> 0 | V21: =+VLOOKUP($A21,S0!$C$2:$Y$89,22)/8 * VLOOKUP($I21,Atributos!$A$28:$B$31,2) * VLOOKUP($J21,Atributos!$G$22:$H$25,2)/5 -> 0 | W21: =+VLOOKUP($A21,S0!$C$2:$Y$89,23)/8 * VLOOKUP($I21,Atributos!$A$28:$B$31,2) * VLOOKUP($J21,Atributos!$G$22:$H$25,2)/5 -> 0 | X21: =SUM(S21:V21) -> 0 | Y21: =(S21+M21)/2 -> 0.1875 | Z21: =(T21+N21)/2 -> 0 | AA21: =(U21+O21)/2 -> 0 | AB21: =(V21+P21)/2 -> 0 | AC21: =(W21+Q21)/2 -> 0 | AD21: =SUM(Y21:AB21) -> 0.1875
A22: FI-00_Estructura Organizativa(FI_EO1) | B22: =+VLOOKUP(A22,S0!$C$2:$I$89,7) -> FI | C22: N/A EO | D22: No aplica en Estructura Organizativa | E22: =+VLOOKUP(A22,S0!$C$2:$I$89,3) -> Sociedad FI Variante de ejercicio Variante de periodos Plan de cuentas Clase de cuentas Definición de monedas Clases de documentos Claves de contabilización Documento financiero Tipo de cambio Ledgers paralelos Sociedad GL | F22: =+VLOOKUP(A22,S0!$C$2:$I$89,4) -> La estructura organizativa representa la vista jurídica u organizativa de la empresa y corresponde a un requisito esencial tanto para la determinación de los datos maestros, como para los procesos a definir en la empresa. Asi mismo, abarca la definción de conceptos escenciales para dar soporte a los procesos contables. Por ejemplo, conceptos como: las Clases de documento, variante de ejercicio, variante de periodos, Claves de contabiización y otros. | G22: =+VLOOKUP(A22,S0!$C$2:$I$89,5) -> - Las Sociedades FI pueden estar sujetas a alguna caracteristicas desde su creación por ejemplo: a) Plan de Cuentas Operativo y Plan de Cuentas País ( Se define en Base a la Sociedad Matriz o Grupo ) | H22: =+VLOOKUP(A22,S0!$C$2:$I$89,6) -> "Revalorización en modena extranjera" Caso que se generea ingreso o gasto que de manera automática se imputa a un cebe o ceco. | I22: 01 Adoptar | J22: 01 Baja | L22: =+(VLOOKUP($A22,S0!$C$2:$Y$89,18)/8 * VLOOKUP($I22,Atributos!$A$28:$B$31,2) * VLOOKUP($J22,Atributos!$A$22:$B$25,2))/5 -> 0.0375 | M22: =+(VLOOKUP($A22,S0!$C$2:$Y$89,19)/8 * VLOOKUP($I22,Atributos!$A$28:$B45,2) * VLOOKUP($J22,Atributos!$A$22:$B39,2))/5 -> 0.0375 | N22: =+VLOOKUP($A22,S0!$C$2:$Y$89,20)/8 * VLOOKUP($I22,Atributos!$A$28:$B$31,2) * VLOOKUP($J22,Atributos!$A$22:$B$25,2)/5 -> 0.15 | O22: =+VLOOKUP($A22,S0!$C$2:$Y$89,21)/8 * VLOOKUP($I22,Atributos!$A$28:$B$31,2) * VLOOKUP($J22,Atributos!$A$22:$B$25,2)/5 -> 0.15 | P22: =+VLOOKUP($A22,S0!$C$2:$Y$89,22)/8 * VLOOKUP($I22,Atributos!$A$28:$B$31,2) * VLOOKUP($J22,Atributos!$A$22:$B$25,2)/5 -> 0 | Q22: =+VLOOKUP($A22,S0!$C$2:$Y$89,23)/8 * VLOOKUP($I22,Atributos!$A$28:$B$31,2) * VLOOKUP($J22,Atributos!$A$22:$B$25,2)/5 -> 0 | R22: =SUM(M22:P22) -> 0.3375 | S22: =+(VLOOKUP($A22,S0!$C$2:$Y$89,19)/8 * VLOOKUP($I22,Atributos!$A$28:$B$31,2) * VLOOKUP($J22,Atributos!$G$22:$H$25,2))/5 -> 0.025 | T22: =+VLOOKUP($A22,S0!$C$2:$Y$89,20)/8 * VLOOKUP($I22,Atributos!$A$28:$B$31,2) * VLOOKUP($J22,Atributos!$G$22:$H$25,2)/5 -> 0.1 | U22: =+VLOOKUP($A22,S0!$C$2:$Y$89,21)/8 * VLOOKUP($I22,Atributos!$A$28:$B$31,2) * VLOOKUP($J22,Atributos!$G$22:$H$25,2)/5 -> 0.1 | V22: =+VLOOKUP($A22,S0!$C$2:$Y$89,22)/8 * VLOOKUP($I22,Atributos!$A$28:$B$31,2) * VLOOKUP($J22,Atributos!$G$22:$H$25,2)/5 -> 0 | W22: =+VLOOKUP($A22,S0!$C$2:$Y$89,23)/8 * VLOOKUP($I22,Atributos!$A$28:$B$31,2) * VLOOKUP($J22,Atributos!$G$22:$H$25,2)/5 -> 0 | X22: =SUM(S22:V22) -> 0.225 | Y22: =(S22+M22)/2 -> 0.03125 | Z22: =(T22+N22)/2 -> 0.125 | AA22: =(U22+O22)/2 -> 0.125 | AB22: =(V22+P22)/2 -> 0 | AC22: =(W22+Q22)/2 -> 0 | AD22: =SUM(Y22:AB22) -> 0.28125
A23: FI-01_Maestro de Contabilidad General(FI_M010) | B23: =+VLOOKUP(A23,S0!$C$2:$I$89,7) -> FI | C23: J58 | D23: Accounting and Financial Close | E23: =+VLOOKUP(A23,S0!$C$2:$I$89,3) -> Plan de cuentas Operativo -Segmento de Plan de Cuentas -Segmento de Sociedad Reportes | F23: =+VLOOKUP(A23,S0!$C$2:$I$89,4) -> El maestro del Plan de Cuentas, agrupa la totalidad de las cuentas de mayor de la organización. En SAP, una sociedad puede gestionar tres planes de cuentas: - Plan de cuentas operativo (es indispensable). - Plan de cuentas de grupo. - Plan de cuentas del país | G23: =+VLOOKUP(A23,S0!$C$2:$I$89,5) -> 1) Manejar en la Sociedad solo con el Plan Contable Operativo ( ejemplo :PCGE ) 2) Manejar en la Sociedad Plan Contable Operativo y Alternativo ( ejemplo : CAPE (Opeativo ) y Alternativo PCGE ( Local ) 3) Opcional manejar Plan de Cuenta Grupo | H23: =+VLOOKUP(A23,S0!$C$2:$I$89,6) -> 0 | I23: 01 Adoptar | J23: 01 Baja | L23: =+(VLOOKUP($A23,S0!$C$2:$Y$89,18)/8 * VLOOKUP($I23,Atributos!$A$28:$B$31,2) * VLOOKUP($J23,Atributos!$A$22:$B$25,2))/5 -> 0.0375 | M23: =+(VLOOKUP($A23,S0!$C$2:$Y$89,19)/8 * VLOOKUP($I23,Atributos!$A$28:$B46,2) * VLOOKUP($J23,Atributos!$A$22:$B40,2))/5 -> 0.075 | N23: =+VLOOKUP($A23,S0!$C$2:$Y$89,20)/8 * VLOOKUP($I23,Atributos!$A$28:$B$31,2) * VLOOKUP($J23,Atributos!$A$22:$B$25,2)/5 -> 0.3 | O23: =+VLOOKUP($A23,S0!$C$2:$Y$89,21)/8 * VLOOKUP($I23,Atributos!$A$28:$B$31,2) * VLOOKUP($J23,Atributos!$A$22:$B$25,2)/5 -> 0.3 | P23: =+VLOOKUP($A23,S0!$C$2:$Y$89,22)/8 * VLOOKUP($I23,Atributos!$A$28:$B$31,2) * VLOOKUP($J23,Atributos!$A$22:$B$25,2)/5 -> 0.3 | Q23: =+VLOOKUP($A23,S0!$C$2:$Y$89,23)/8 * VLOOKUP($I23,Atributos!$A$28:$B$31,2) * VLOOKUP($J23,Atributos!$A$22:$B$25,2)/5 -> 0 | R23: =SUM(M23:P23) -> 0.975 | S23: =+(VLOOKUP($A23,S0!$C$2:$Y$89,19)/8 * VLOOKUP($I23,Atributos!$A$28:$B$31,2) * VLOOKUP($J23,Atributos!$G$22:$H$25,2))/5 -> 0.025 | T23: =+VLOOKUP($A23,S0!$C$2:$Y$89,20)/8 * VLOOKUP($I23,Atributos!$A$28:$B$31,2) * VLOOKUP($J23,Atributos!$G$22:$H$25,2)/5 -> 0.2 | U23: =+VLOOKUP($A23,S0!$C$2:$Y$89,21)/8 * VLOOKUP($I23,Atributos!$A$28:$B$31,2) * VLOOKUP($J23,Atributos!$G$22:$H$25,2)/5 -> 0.2 | V23: =+VLOOKUP($A23,S0!$C$2:$Y$89,22)/8 * VLOOKUP($I23,Atributos!$A$28:$B$31,2) * VLOOKUP($J23,Atributos!$G$22:$H$25,2)/5 -> 0.2 | W23: =+VLOOKUP($A23,S0!$C$2:$Y$89,23)/8 * VLOOKUP($I23,Atributos!$A$28:$B$31,2) * VLOOKUP($J23,Atributos!$G$22:$H$25,2)/5 -> 0 | X23: =SUM(S23:V23) -> 0.625 | Y23: =(S23+M23)/2 -> 0.05 | Z23: =(T23+N23)/2 -> 0.25 | AA23: =(U23+O23)/2 -> 0.25 | AB23: =(V23+P23)/2 -> 0.25 | AC23: =(W23+Q23)/2 -> 0 | AD23: =SUM(Y23:AB23) -> 0.8
A24: FI-02_Maestro de Activos Fijos(FI_M020) | B24: =+VLOOKUP(A24,S0!$C$2:$I$89,7) -> FI | C24: J62 | D24: Asset Accounting | E24: =+VLOOKUP(A24,S0!$C$2:$I$89,3) -> Maestro de Activos Fijos | F24: =+VLOOKUP(A24,S0!$C$2:$I$89,4) -> El maestro de activos fijos centraliza la administración de los activos fijos mediante la creación y mantenimiento de códigos únicos de AF. Bajos los cuales se contabilizan las altas, bajas, traslados, depreciación u otras operaciones. Los códigos de activos fijos dan soporte a los procesos de activos fijos y permite un análisis contable por código de activo. | G24: =+VLOOKUP(A24,S0!$C$2:$I$89,5) -> 1) Manejar diferentes Areas de Valoración para su tratamiento Contable,Tributario o de Revaluaciones 2) Manejar diferentes tipos de Clave de Amortización : Ejemplo Lineal o por Unidades Producidas. 3) Llevar el control de las Altas, Bajas y traspasos de las diferentes clases de activos dependiendo de sus Vida Utiles | H24: =+VLOOKUP(A24,S0!$C$2:$I$89,6) -> 0 | I24: 02 Ajustar | J24: 02 Media | K24: Activos fijos en curso en Campo | L24: =+(VLOOKUP($A24,S0!$C$2:$Y$89,18)/8 * VLOOKUP($I24,Atributos!$A$28:$B$31,2) * VLOOKUP($J24,Atributos!$A$22:$B$25,2))/5 -> 0.084375 | M24: =+(VLOOKUP($A24,S0!$C$2:$Y$89,19)/8 * VLOOKUP($I24,Atributos!$A$28:$B47,2) * VLOOKUP($J24,Atributos!$A$22:$B41,2))/5 -> 0.16875 | N24: =+VLOOKUP($A24,S0!$C$2:$Y$89,20)/8 * VLOOKUP($I24,Atributos!$A$28:$B$31,2) * VLOOKUP($J24,Atributos!$A$22:$B$25,2)/5 -> 0.675 | O24: =+VLOOKUP($A24,S0!$C$2:$Y$89,21)/8 * VLOOKUP($I24,Atributos!$A$28:$B$31,2) * VLOOKUP($J24,Atributos!$A$22:$B$25,2)/5 -> 0.675 | P24: =+VLOOKUP($A24,S0!$C$2:$Y$89,22)/8 * VLOOKUP($I24,Atributos!$A$28:$B$31,2) * VLOOKUP($J24,Atributos!$A$22:$B$25,2)/5 -> 0.675 | Q24: =+VLOOKUP($A24,S0!$C$2:$Y$89,23)/8 * VLOOKUP($I24,Atributos!$A$28:$B$31,2) * VLOOKUP($J24,Atributos!$A$22:$B$25,2)/5 -> 0 | R24: =SUM(M24:P24) -> 2.19375 | S24: =+(VLOOKUP($A24,S0!$C$2:$Y$89,19)/8 * VLOOKUP($I24,Atributos!$A$28:$B$31,2) * VLOOKUP($J24,Atributos!$G$22:$H$25,2))/5 -> 0.05625 | T24: =+VLOOKUP($A24,S0!$C$2:$Y$89,20)/8 * VLOOKUP($I24,Atributos!$A$28:$B$31,2) * VLOOKUP($J24,Atributos!$G$22:$H$25,2)/5 -> 0.45 | U24: =+VLOOKUP($A24,S0!$C$2:$Y$89,21)/8 * VLOOKUP($I24,Atributos!$A$28:$B$31,2) * VLOOKUP($J24,Atributos!$G$22:$H$25,2)/5 -> 0.45 | V24: =+VLOOKUP($A24,S0!$C$2:$Y$89,22)/8 * VLOOKUP($I24,Atributos!$A$28:$B$31,2) * VLOOKUP($J24,Atributos!$G$22:$H$25,2)/5 -> 0.45 | W24: =+VLOOKUP($A24,S0!$C$2:$Y$89,23)/8 * VLOOKUP($I24,Atributos!$A$28:$B$31,2) * VLOOKUP($J24,Atributos!$G$22:$H$25,2)/5 -> 0 | X24: =SUM(S24:V24) -> 1.40625 | Y24: =(S24+M24)/2 -> 0.1125 | Z24: =(T24+N24)/2 -> 0.5625 | AA24: =(U24+O24)/2 -> 0.5625 | AB24: =(V24+P24)/2 -> 0.5625 | AC24: =(W24+Q24)/2 -> 0 | AD24: =SUM(Y24:AB24) -> 1.8
A25: FI-03_Maestro de bancos(FI_M030) | B25: =+VLOOKUP(A25,S0!$C$2:$I$89,7) -> FI | C25: BFA | D25: Basic Bank Account Management | E25: =+VLOOKUP(A25,S0!$C$2:$I$89,3) -> Maestro de Bancos Bancos propios Cuentas bancarias | F25: =+VLOOKUP(A25,S0!$C$2:$I$89,4) -> Con la gestión de cuentas bancarias el área de tesorería puede centralizar la gestión de cuentas bancarias utilizando los datos maestros de cuentas bancarias. | G25: =+VLOOKUP(A25,S0!$C$2:$I$89,5) -> 1) Crear Bancos País 2) Crear Bancos Propios 3) Crear Cuentas Bancarias de Bancos Propios. | H25: =+VLOOKUP(A25,S0!$C$2:$I$89,6) -> 0 | I25: 01 Adoptar | J25: 01 Baja | L25: =+(VLOOKUP($A25,S0!$C$2:$Y$89,18)/8 * VLOOKUP($I25,Atributos!$A$28:$B$31,2) * VLOOKUP($J25,Atributos!$A$22:$B$25,2))/5 -> 0.0375 | M25: =+(VLOOKUP($A25,S0!$C$2:$Y$89,19)/8 * VLOOKUP($I25,Atributos!$A$28:$B48,2) * VLOOKUP($J25,Atributos!$A$22:$B42,2))/5 -> 0.1 | N25: =+VLOOKUP($A25,S0!$C$2:$Y$89,20)/8 * VLOOKUP($I25,Atributos!$A$28:$B$31,2) * VLOOKUP($J25,Atributos!$A$22:$B$25,2)/5 -> 0.3 | O25: =+VLOOKUP($A25,S0!$C$2:$Y$89,21)/8 * VLOOKUP($I25,Atributos!$A$28:$B$31,2) * VLOOKUP($J25,Atributos!$A$22:$B$25,2)/5 -> 0.3 | P25: =+VLOOKUP($A25,S0!$C$2:$Y$89,22)/8 * VLOOKUP($I25,Atributos!$A$28:$B$31,2) * VLOOKUP($J25,Atributos!$A$22:$B$25,2)/5 -> 0.3 | Q25: =+VLOOKUP($A25,S0!$C$2:$Y$89,23)/8 * VLOOKUP($I25,Atributos!$A$28:$B$31,2) * VLOOKUP($J25,Atributos!$A$22:$B$25,2)/5 -> 0 | R25: =SUM(M25:P25) -> 1 | S25: =+(VLOOKUP($A25,S0!$C$2:$Y$89,19)/8 * VLOOKUP($I25,Atributos!$A$28:$B$31,2) * VLOOKUP($J25,Atributos!$G$22:$H$25,2))/5 -> 0.025 | T25: =+VLOOKUP($A25,S0!$C$2:$Y$89,20)/8 * VLOOKUP($I25,Atributos!$A$28:$B$31,2) * VLOOKUP($J25,Atributos!$G$22:$H$25,2)/5 -> 0.2 | U25: =+VLOOKUP($A25,S0!$C$2:$Y$89,21)/8 * VLOOKUP($I25,Atributos!$A$28:$B$31,2) * VLOOKUP($J25,Atributos!$G$22:$H$25,2)/5 -> 0.2 | V25: =+VLOOKUP($A25,S0!$C$2:$Y$89,22)/8 * VLOOKUP($I25,Atributos!$A$28:$B$31,2) * VLOOKUP($J25,Atributos!$G$22:$H$25,2)/5 -> 0.2 | W25: =+VLOOKUP($A25,S0!$C$2:$Y$89,23)/8 * VLOOKUP($I25,Atributos!$A$28:$B$31,2) * VLOOKUP($J25,Atributos!$G$22:$H$25,2)/5 -> 0 | X25: =SUM(S25:V25) -> 0.625 | Y25: =(S25+M25)/2 -> 0.0625 | Z25: =(T25+N25)/2 -> 0.25 | AA25: =(U25+O25)/2 -> 0.25 | AB25: =(V25+P25)/2 -> 0.25 | AC25: =(W25+Q25)/2 -> 0 | AD25: =SUM(Y25:AB25) -> 0.8125
A26: FI-04_Contabilidad General(FI_P010) | B26: =+VLOOKUP(A26,S0!$C$2:$I$89,7) -> FI | C26: J58 | D26: Accounting and Financial Close | E26: =+VLOOKUP(A26,S0!$C$2:$I$89,3) -> Registro de Asientos de Diario Registro de Asientos de provisiones Asientos periódicos Anulación de registros Desglose de documentos Reportes | F26: =+VLOOKUP(A26,S0!$C$2:$I$89,4) -> En SAP S/4HANA este proceso proporciona soporte a la gestión de la información financiera referida a la evaluación y generación de los reportes de resultados y de cuentas de balance. Por lo que, permite la emisión de documentos de contabilidad general, como asientos diarios o asientos periódicos. | G26: =+VLOOKUP(A26,S0!$C$2:$I$89,5) -> 1) Provisiones y Extornos ( Afectos o Inafectos ) 2) Reclasificaciones 2) Asientos Periodicos por concepto de Alquileres 3) Anulaciones de documentos. | H26: =+VLOOKUP(A26,S0!$C$2:$I$89,6) -> 0 | I26: 01 Adoptar | J26: 01 Baja | L26: =+(VLOOKUP($A26,S0!$C$2:$Y$89,18)/8 * VLOOKUP($I26,Atributos!$A$28:$B$31,2) * VLOOKUP($J26,Atributos!$A$22:$B$25,2))/5 -> 0.0375 | M26: =+(VLOOKUP($A26,S0!$C$2:$Y$89,19)/8 * VLOOKUP($I26,Atributos!$A$28:$B49,2) * VLOOKUP($J26,Atributos!$A$22:$B43,2))/5 -> 0.2 | N26: =+VLOOKUP($A26,S0!$C$2:$Y$89,20)/8 * VLOOKUP($I26,Atributos!$A$28:$B$31,2) * VLOOKUP($J26,Atributos!$A$22:$B$25,2)/5 -> 0.6 | O26: =+VLOOKUP($A26,S0!$C$2:$Y$89,21)/8 * VLOOKUP($I26,Atributos!$A$28:$B$31,2) * VLOOKUP($J26,Atributos!$A$22:$B$25,2)/5 -> 1.2 | P26: =+VLOOKUP($A26,S0!$C$2:$Y$89,22)/8 * VLOOKUP($I26,Atributos!$A$28:$B$31,2) * VLOOKUP($J26,Atributos!$A$22:$B$25,2)/5 -> 0.3 | Q26: =+VLOOKUP($A26,S0!$C$2:$Y$89,23)/8 * VLOOKUP($I26,Atributos!$A$28:$B$31,2) * VLOOKUP($J26,Atributos!$A$22:$B$25,2)/5 -> 0.3 | R26: =SUM(M26:P26) -> 2.3 | S26: =+(VLOOKUP($A26,S0!$C$2:$Y$89,19)/8 * VLOOKUP($I26,Atributos!$A$28:$B$31,2) * VLOOKUP($J26,Atributos!$G$22:$H$25,2))/5 -> 0.05 | T26: =+VLOOKUP($A26,S0!$C$2:$Y$89,20)/8 * VLOOKUP($I26,Atributos!$A$28:$B$31,2) * VLOOKUP($J26,Atributos!$G$22:$H$25,2)/5 -> 0.4 | U26: =+VLOOKUP($A26,S0!$C$2:$Y$89,21)/8 * VLOOKUP($I26,Atributos!$A$28:$B$31,2) * VLOOKUP($J26,Atributos!$G$22:$H$25,2)/5 -> 0.8 | V26: =+VLOOKUP($A26,S0!$C$2:$Y$89,22)/8 * VLOOKUP($I26,Atributos!$A$28:$B$31,2) * VLOOKUP($J26,Atributos!$G$22:$H$25,2)/5 -> 0.2 | W26: =+VLOOKUP($A26,S0!$C$2:$Y$89,23)/8 * VLOOKUP($I26,Atributos!$A$28:$B$31,2) * VLOOKUP($J26,Atributos!$G$22:$H$25,2)/5 -> 0.2 | X26: =SUM(S26:V26) -> 1.45 | Y26: =(S26+M26)/2 -> 0.125 | Z26: =(T26+N26)/2 -> 0.5 | AA26: =(U26+O26)/2 -> 1 | AB26: =(V26+P26)/2 -> 0.25 | AC26: =(W26+Q26)/2 -> 0.25 | AD26: =SUM(Y26:AB26) -> 1.875
A27: FI-05_Cuentas por Pagar(FI_P020) | B27: =+VLOOKUP(A27,S0!$C$2:$I$89,7) -> FI | C27: J60 | D27: Accounts Payable | E27: =+VLOOKUP(A27,S0!$C$2:$I$89,3) -> Maestro de Interlocutor Comercial (Acreedores o Proveedores) Registro de Facturas y otros Comprobantes de Proveedor - Registro de Comprobantes por Finanzas (FI) - Registro de Comprobantes Con Orden de Compra (MM) Indicadores de impuestos Compras Percepciones por compra Registro de Comprobantes de Importación de bienes Registro de IGV no domiciliado Solicitudes de Anticipo Acreedor Retenciones en la factura - Detracciones de IGV - Retenciones no Domiciliados - Retenciones dietas Retenciones en el pago - Retenciones de IGV - Retenciones de 4ta categoría Anulación de Registro Registros preliminares Cuenta de mayor especial (CME) Compensaciones - Con anticipos - Con N/D y N/C - Canje de letras - Factura Negociable o Factoring o Compensación Deudor/Acreedor o Anulación de compensación Reportes | F27: =+VLOOKUP(A27,S0!$C$2:$I$89,4) -> El proceso de cuentas por pagar comprende básicamente la contabilidad en acreedores producto de las operaciones de adquisición de bienes o servicios que generen una obligación de pago. Los acreedores cuentan con un código único en el maestro de Business Partner bajo el cual se registran sus operaciones y permiten el análisis auxiliar por cuenta acreedora. Así mismo se contabilizan facturas y abonos, se registran pagos y anticipos, se gestionan los valores entregados como medios de pago y al contabilizar datos en acreedores, el sistema crea un documento contable y transfiere los datos introducidos al libro mayor y según corresponda al Libro de Compras. | G27: =+VLOOKUP(A27,S0!$C$2:$I$89,5) -> 1) Registro de Comprobantes por Finanzas ( Todos los documentos SUNAT ) 2) Registro de Comprobantes usando los diferentes tipos de Indicadores de Impuestos. 3) Registro de FActura de No Domiciliado , Provisión IGV No Domiciliado y Extorno provisión IGV 4) Registro de Formulario de Declaración - pago o Boleta de pago de tributos Internos 5) Generar Solicitudes de Anticipo y su respectiva Contabilización. 6) Anulaciones de Registros o Comprobantes 7) Creación de documentos preliminares antes de su contabilización 8) Redireccionamiento de Cuentas a través del uso del CME 9) Compensaciones Parciales o Totales de la cuentas por pagar. Letras, Factura Negociable y Facttoring 10) Compensaciones entre Deudores(CXC) y Acreedores ( CXP) 11) Descompesación de documentos de pago | H27: =+VLOOKUP(A27,S0!$C$2:$I$89,6) -> Los indicadores de impuestos están asociado al IGV. No está considerado otro tipo de impuesto como ISC, impuestos especiales de sectores industriales, FISE, Rodamiento, impuestos a los plásticos, etc | I27: 01 Adoptar | J27: 01 Baja | L27: =+(VLOOKUP($A27,S0!$C$2:$Y$89,18)/8 * VLOOKUP($I27,Atributos!$A$28:$B$31,2) * VLOOKUP($J27,Atributos!$A$22:$B$25,2))/5 -> 0.0375 | M27: =+(VLOOKUP($A27,S0!$C$2:$Y$89,19)/8 * VLOOKUP($I27,Atributos!$A$28:$B50,2) * VLOOKUP($J27,Atributos!$A$22:$B44,2))/5 -> 0.2 | N27: =+VLOOKUP($A27,S0!$C$2:$Y$89,20)/8 * VLOOKUP($I27,Atributos!$A$28:$B$31,2) * VLOOKUP($J27,Atributos!$A$22:$B$25,2)/5 -> 0.6 | O27: =+VLOOKUP($A27,S0!$C$2:$Y$89,21)/8 * VLOOKUP($I27,Atributos!$A$28:$B$31,2) * VLOOKUP($J27,Atributos!$A$22:$B$25,2)/5 -> 1.2 | P27: =+VLOOKUP($A27,S0!$C$2:$Y$89,22)/8 * VLOOKUP($I27,Atributos!$A$28:$B$31,2) * VLOOKUP($J27,Atributos!$A$22:$B$25,2)/5 -> 0.3 | Q27: =+VLOOKUP($A27,S0!$C$2:$Y$89,23)/8 * VLOOKUP($I27,Atributos!$A$28:$B$31,2) * VLOOKUP($J27,Atributos!$A$22:$B$25,2)/5 -> 0.3 | R27: =SUM(M27:P27) -> 2.3 | S27: =+(VLOOKUP($A27,S0!$C$2:$Y$89,19)/8 * VLOOKUP($I27,Atributos!$A$28:$B$31,2) * VLOOKUP($J27,Atributos!$G$22:$H$25,2))/5 -> 0.05 | T27: =+VLOOKUP($A27,S0!$C$2:$Y$89,20)/8 * VLOOKUP($I27,Atributos!$A$28:$B$31,2) * VLOOKUP($J27,Atributos!$G$22:$H$25,2)/5 -> 0.4 | U27: =+VLOOKUP($A27,S0!$C$2:$Y$89,21)/8 * VLOOKUP($I27,Atributos!$A$28:$B$31,2) * VLOOKUP($J27,Atributos!$G$22:$H$25,2)/5 -> 0.8 | V27: =+VLOOKUP($A27,S0!$C$2:$Y$89,22)/8 * VLOOKUP($I27,Atributos!$A$28:$B$31,2) * VLOOKUP($J27,Atributos!$G$22:$H$25,2)/5 -> 0.2 | W27: =+VLOOKUP($A27,S0!$C$2:$Y$89,23)/8 * VLOOKUP($I27,Atributos!$A$28:$B$31,2) * VLOOKUP($J27,Atributos!$G$22:$H$25,2)/5 -> 0.2 | X27: =SUM(S27:V27) -> 1.45 | Y27: =(S27+M27)/2 -> 0.125 | Z27: =(T27+N27)/2 -> 0.5 | AA27: =(U27+O27)/2 -> 1 | AB27: =(V27+P27)/2 -> 0.25 | AC27: =(W27+Q27)/2 -> 0.25 | AD27: =SUM(Y27:AB27) -> 1.875
A28: FI-06_Otras Cuentas por Pagar(FI_P021) | B28: =+VLOOKUP(A28,S0!$C$2:$I$89,7) -> FI | C28: J60 | D28: Accounts Payable | E28: =+VLOOKUP(A28,S0!$C$2:$I$89,3) -> Registro de otras Cuentas por Pagar (Prestamos con terceros o vinculadas, Pagares, Financiamientos, Cuotas de Leasing) Impuestos Caja Chica - Constitución de Caja Chica por medio de anticipo. - Registro de Facturas y otros Comprobantes de Proveedor - Liquidación de documentos - Reposición de Caja Chica Entregas a Rendir - Solicitud (anticipo) - Registro de Salidas a Rendir (Pago a colaborador) - Registro de facturas - Liquidación de Gastos Desembolsos - Registro de facturas por pagar - Compensación de facturas por pagar contra cuenta por pagar al trabajador - Reposición al trabajador Tarjetas de crédito empresariales - Registro de facturas por pagar - Compensación de comprobantes de pago contra cuenta de tarjetas de crédito - Registro de cuenta tarjetas de crédito contra cuenta bancos Reportes | F28: =+VLOOKUP(A28,S0!$C$2:$I$89,4) -> El proceso de Otras cuentas por pagar abarca el registro en acreedores de operaciones no core de negocio. Tales como financiamientos, impuestos, entredas a rendir, caja chica. | G28: =+VLOOKUP(A28,S0!$C$2:$I$89,5) -> 1) Generar documentos por Préstamos a Terceros o Vinculadas 2) Generar documentos por Obligaciones Bancarias ( Pagarés ); incluyendo sus amortizaciones y cancelaciones 3) Generar documentos por Financiamientos con Bancos; incluyendo sus amortizaciones y cancelaciones. 4) Registros de Cuotas de Leasing ( Devengamiento incluyendo Intereses ). 5) Registar los impuestos por Pagar ( IGV) contra la SUNAT. 6) Registro, liquidación y reposición Caja Chica 7) Permite registrar Solicitud de Entregas a Rendir, registros de comprobantes y liquidación. 8) Registrar Desembolsos a Empleados por gestionar compras menores a nombre de la Empresa. Registrar comprobante y reposición del dinero al Empleado. 9) Permitir liquidaciones de tarjetas de crédito empresarial contra los comprobantes incurridos. | H28: =+VLOOKUP(A28,S0!$C$2:$I$89,6) -> Los indicadores de impuestos están asociado al IGV. No está considerado otro tipo de impuesto como ISC, impuestos especiales de sectores industriales, FISE, Rodamiento, impuestos a los plásticos, etc | I28: 01 Adoptar | J28: 01 Baja | L28: =+(VLOOKUP($A28,S0!$C$2:$Y$89,18)/8 * VLOOKUP($I28,Atributos!$A$28:$B$31,2) * VLOOKUP($J28,Atributos!$A$22:$B$25,2))/5 -> 0.0375 | M28: =+(VLOOKUP($A28,S0!$C$2:$Y$89,19)/8 * VLOOKUP($I28,Atributos!$A$28:$B51,2) * VLOOKUP($J28,Atributos!$A$22:$B45,2))/5 -> 0.2 | N28: =+VLOOKUP($A28,S0!$C$2:$Y$89,20)/8 * VLOOKUP($I28,Atributos!$A$28:$B$31,2) * VLOOKUP($J28,Atributos!$A$22:$B$25,2)/5 -> 0.6 | O28: =+VLOOKUP($A28,S0!$C$2:$Y$89,21)/8 * VLOOKUP($I28,Atributos!$A$28:$B$31,2) * VLOOKUP($J28,Atributos!$A$22:$B$25,2)/5 -> 1.2 | P28: =+VLOOKUP($A28,S0!$C$2:$Y$89,22)/8 * VLOOKUP($I28,Atributos!$A$28:$B$31,2) * VLOOKUP($J28,Atributos!$A$22:$B$25,2)/5 -> 0.3 | Q28: =+VLOOKUP($A28,S0!$C$2:$Y$89,23)/8 * VLOOKUP($I28,Atributos!$A$28:$B$31,2) * VLOOKUP($J28,Atributos!$A$22:$B$25,2)/5 -> 0.3 | R28: =SUM(M28:P28) -> 2.3 | S28: =+(VLOOKUP($A28,S0!$C$2:$Y$89,19)/8 * VLOOKUP($I28,Atributos!$A$28:$B$31,2) * VLOOKUP($J28,Atributos!$G$22:$H$25,2))/5 -> 0.05 | T28: =+VLOOKUP($A28,S0!$C$2:$Y$89,20)/8 * VLOOKUP($I28,Atributos!$A$28:$B$31,2) * VLOOKUP($J28,Atributos!$G$22:$H$25,2)/5 -> 0.4 | U28: =+VLOOKUP($A28,S0!$C$2:$Y$89,21)/8 * VLOOKUP($I28,Atributos!$A$28:$B$31,2) * VLOOKUP($J28,Atributos!$G$22:$H$25,2)/5 -> 0.8 | V28: =+VLOOKUP($A28,S0!$C$2:$Y$89,22)/8 * VLOOKUP($I28,Atributos!$A$28:$B$31,2) * VLOOKUP($J28,Atributos!$G$22:$H$25,2)/5 -> 0.2 | W28: =+VLOOKUP($A28,S0!$C$2:$Y$89,23)/8 * VLOOKUP($I28,Atributos!$A$28:$B$31,2) * VLOOKUP($J28,Atributos!$G$22:$H$25,2)/5 -> 0.2 | X28: =SUM(S28:V28) -> 1.45 | Y28: =(S28+M28)/2 -> 0.125 | Z28: =(T28+N28)/2 -> 0.5 | AA28: =(U28+O28)/2 -> 1 | AB28: =(V28+P28)/2 -> 0.25 | AC28: =(W28+Q28)/2 -> 0.25 | AD28: =SUM(Y28:AB28) -> 1.875
A29: FI-07_Pago a Proveedores(FI_P022) | B29: =+VLOOKUP(A29,S0!$C$2:$I$89,7) -> FI | C29: J60 | D29: Accounts Payable | E29: =+VLOOKUP(A29,S0!$C$2:$I$89,3) -> Anticipo a Proveedores Pago Individuales y Masivos - Con nota de crédito (aplicación) - Con Cheque - Con Transferencia Electrónica - Pagos Interbancarios Pago de Planillas de RRHH Pagos Parciales Retenciones en el pago Anulación de pagos Vías de pago Bloqueos de pago Condición de pago Reportes | F29: =+VLOOKUP(A29,S0!$C$2:$I$89,4) -> El proceso de pago a proveedores abarca los diferentes mecanismos y condiciones que el modulo FI ofrece para contabilzar los pagos sobre los registros previamente generados en el proceso de cuentas por pagar. | G29: =+VLOOKUP(A29,S0!$C$2:$I$89,5) -> 1) Generar Solicitudes de Anticipos para la Caja Chica, Entregas a Rendir y Anticipos a Terceros 2) Pagos Individuales o Masivos a Proveedores. Aplicando pagos parciales o totales. 3) Registrar documentos que estan sujetos a Retenciones sea en el documento o en el Pago ( Localización ) 4) Registrar las anulaciones de las compensaciones por los documentos de pago. | H29: =+VLOOKUP(A29,S0!$C$2:$I$89,6) -> 0 | I29: 01 Adoptar | J29: 01 Baja | L29: =+(VLOOKUP($A29,S0!$C$2:$Y$89,18)/8 * VLOOKUP($I29,Atributos!$A$28:$B$31,2) * VLOOKUP($J29,Atributos!$A$22:$B$25,2))/5 -> 0.0375 | M29: =+(VLOOKUP($A29,S0!$C$2:$Y$89,19)/8 * VLOOKUP($I29,Atributos!$A$28:$B52,2) * VLOOKUP($J29,Atributos!$A$22:$B46,2))/5 -> 0.2 | N29: =+VLOOKUP($A29,S0!$C$2:$Y$89,20)/8 * VLOOKUP($I29,Atributos!$A$28:$B$31,2) * VLOOKUP($J29,Atributos!$A$22:$B$25,2)/5 -> 0.6 | O29: =+VLOOKUP($A29,S0!$C$2:$Y$89,21)/8 * VLOOKUP($I29,Atributos!$A$28:$B$31,2) * VLOOKUP($J29,Atributos!$A$22:$B$25,2)/5 -> 1.2 | P29: =+VLOOKUP($A29,S0!$C$2:$Y$89,22)/8 * VLOOKUP($I29,Atributos!$A$28:$B$31,2) * VLOOKUP($J29,Atributos!$A$22:$B$25,2)/5 -> 0.3 | Q29: =+VLOOKUP($A29,S0!$C$2:$Y$89,23)/8 * VLOOKUP($I29,Atributos!$A$28:$B$31,2) * VLOOKUP($J29,Atributos!$A$22:$B$25,2)/5 -> 0.3 | R29: =SUM(M29:P29) -> 2.3 | S29: =+(VLOOKUP($A29,S0!$C$2:$Y$89,19)/8 * VLOOKUP($I29,Atributos!$A$28:$B$31,2) * VLOOKUP($J29,Atributos!$G$22:$H$25,2))/5 -> 0.05 | T29: =+VLOOKUP($A29,S0!$C$2:$Y$89,20)/8 * VLOOKUP($I29,Atributos!$A$28:$B$31,2) * VLOOKUP($J29,Atributos!$G$22:$H$25,2)/5 -> 0.4 | U29: =+VLOOKUP($A29,S0!$C$2:$Y$89,21)/8 * VLOOKUP($I29,Atributos!$A$28:$B$31,2) * VLOOKUP($J29,Atributos!$G$22:$H$25,2)/5 -> 0.8 | V29: =+VLOOKUP($A29,S0!$C$2:$Y$89,22)/8 * VLOOKUP($I29,Atributos!$A$28:$B$31,2) * VLOOKUP($J29,Atributos!$G$22:$H$25,2)/5 -> 0.2 | W29: =+VLOOKUP($A29,S0!$C$2:$Y$89,23)/8 * VLOOKUP($I29,Atributos!$A$28:$B$31,2) * VLOOKUP($J29,Atributos!$G$22:$H$25,2)/5 -> 0.2 | X29: =SUM(S29:V29) -> 1.45 | Y29: =(S29+M29)/2 -> 0.125 | Z29: =(T29+N29)/2 -> 0.5 | AA29: =(U29+O29)/2 -> 1 | AB29: =(V29+P29)/2 -> 0.25 | AC29: =(W29+Q29)/2 -> 0.25 | AD29: =SUM(Y29:AB29) -> 1.875
A30: FI-08_Cuentas Por Cobrar(FI_P030) | B30: =+VLOOKUP(A30,S0!$C$2:$I$89,7) -> FI | C30: J59 | D30: Accounts Receivable | E30: =+VLOOKUP(A30,S0!$C$2:$I$89,3) -> Maestro de Interlocutor Comercial (Deudores o Clientes) Registro de Facturas y otros Comprobantes de Clientes - Registro de Comprobantes por Finanzas (FI) - Registro de Comprobantes Con Pedido Venta(SD) Indicadores de impuestos Ventas Percepciones Venta Registro de Comprobantes de Importación de bienes Registro de IGV no domiciliado Solicitudes de Anticipo Acreedor Retenciones en la factura - Detracciones de IGV - Retenciones no Domiciliados - Retenciones dietas Retenciones en el pago - Retenciones de IGV - Retenciones de 4ta categoría Anulación de Registro Registros preliminares Cuenta de mayor especial (CME) Compensaciones - Con anticipos - Con N/D y N/C - Canje de letras - Factura Negociable o Factoring o Compensación Deudor/Acreedor o Anulación de compensación Reportes | F30: =+VLOOKUP(A30,S0!$C$2:$I$89,4) -> El proceso de cuentas por cobrar comprende básicamente la contabilidad en deudores producto de las operaciones de venta de bienes o servicios que generen una obligación de cobro. Los clientes cuentan con un código único en el maestro de Business Partner bajo el cual se registran sus operaciones y permiten el análisis auxiliar por cuenta deudora. | G30: =+VLOOKUP(A30,S0!$C$2:$I$89,5) -> 1) Registrar Comprobantes de Ventas por FI ( Facturas , Notas de Crédito y Débito ) con sus indicadores de IVA 2) Registrar Provisiones de Ingresos por FI 3) Registrar documentos por Provisión de Cobranza Dudosa 4) Registrar préstamos entre Empresas Vinculadas o Terceros 5) Registro de Otras de Cuentas por Cobrar Diversas 6) Registrar Retenciones en la cuentas por Cobrar en el momento de la contabilización de la factura ( Localización ). Manejando Percepción de Venta y Detracción de Venta. 7) Anulación del documento de venta generado 9) Compensación de Partidas Deudoras, Anticipos, Notas de Crédito y Débito. 10) Compensación de Deudores con Acreedores 11) Anulación o descompnesación de documentos de cobro. | H30: =+VLOOKUP(A30,S0!$C$2:$I$89,6) -> Los indicadores de impuestos están asociado al IGV. No está considerado otro tipo de impuesto como ISC, impuestos especiales de sectores industriales, FISE, Rodamiento, impuestos a los plásticos, etc | I30: 01 Adoptar | J30: 01 Baja | L30: =+(VLOOKUP($A30,S0!$C$2:$Y$89,18)/8 * VLOOKUP($I30,Atributos!$A$28:$B$31,2) * VLOOKUP($J30,Atributos!$A$22:$B$25,2))/5 -> 0.0375 | M30: =+(VLOOKUP($A30,S0!$C$2:$Y$89,19)/8 * VLOOKUP($I30,Atributos!$A$28:$B53,2) * VLOOKUP($J30,Atributos!$A$22:$B47,2))/5 -> 0.2 | N30: =+VLOOKUP($A30,S0!$C$2:$Y$89,20)/8 * VLOOKUP($I30,Atributos!$A$28:$B$31,2) * VLOOKUP($J30,Atributos!$A$22:$B$25,2)/5 -> 0.6 | O30: =+VLOOKUP($A30,S0!$C$2:$Y$89,21)/8 * VLOOKUP($I30,Atributos!$A$28:$B$31,2) * VLOOKUP($J30,Atributos!$A$22:$B$25,2)/5 -> 1.2 | P30: =+VLOOKUP($A30,S0!$C$2:$Y$89,22)/8 * VLOOKUP($I30,Atributos!$A$28:$B$31,2) * VLOOKUP($J30,Atributos!$A$22:$B$25,2)/5 -> 0.3 | Q30: =+VLOOKUP($A30,S0!$C$2:$Y$89,23)/8 * VLOOKUP($I30,Atributos!$A$28:$B$31,2) * VLOOKUP($J30,Atributos!$A$22:$B$25,2)/5 -> 0.3 | R30: =SUM(M30:P30) -> 2.3 | S30: =+(VLOOKUP($A30,S0!$C$2:$Y$89,19)/8 * VLOOKUP($I30,Atributos!$A$28:$B$31,2) * VLOOKUP($J30,Atributos!$G$22:$H$25,2))/5 -> 0.05 | T30: =+VLOOKUP($A30,S0!$C$2:$Y$89,20)/8 * VLOOKUP($I30,Atributos!$A$28:$B$31,2) * VLOOKUP($J30,Atributos!$G$22:$H$25,2)/5 -> 0.4 | U30: =+VLOOKUP($A30,S0!$C$2:$Y$89,21)/8 * VLOOKUP($I30,Atributos!$A$28:$B$31,2) * VLOOKUP($J30,Atributos!$G$22:$H$25,2)/5 -> 0.8 | V30: =+VLOOKUP($A30,S0!$C$2:$Y$89,22)/8 * VLOOKUP($I30,Atributos!$A$28:$B$31,2) * VLOOKUP($J30,Atributos!$G$22:$H$25,2)/5 -> 0.2 | W30: =+VLOOKUP($A30,S0!$C$2:$Y$89,23)/8 * VLOOKUP($I30,Atributos!$A$28:$B$31,2) * VLOOKUP($J30,Atributos!$G$22:$H$25,2)/5 -> 0.2 | X30: =SUM(S30:V30) -> 1.45 | Y30: =(S30+M30)/2 -> 0.125 | Z30: =(T30+N30)/2 -> 0.5 | AA30: =(U30+O30)/2 -> 1 | AB30: =(V30+P30)/2 -> 0.25 | AC30: =(W30+Q30)/2 -> 0.25 | AD30: =SUM(Y30:AB30) -> 1.875
A31: FI-09_Gestión de Tesorería(FI_P040) | B31: =+VLOOKUP(A31,S0!$C$2:$I$89,7) -> FI | C31: 4X8 N/A S0p | D31: No aplica en S0p | E31: =+VLOOKUP(A31,S0!$C$2:$I$89,3) -> Operaciones de Tesorería - Transferencia entre Cuentas - Compra/Venta de Divisas Reportes | F31: =+VLOOKUP(A31,S0!$C$2:$I$89,4) -> La Gestión de Tesorería, abarca el registro de las operaciones propias a la administración de los fondos de la empresa. | G31: =+VLOOKUP(A31,S0!$C$2:$I$89,5) -> 1) Gestionar Transferencia Bancarias 2) Registrar Compra / Venta de Divisas 3) Cobranzas | H31: =+VLOOKUP(A31,S0!$C$2:$I$89,6) -> 0 | I31: 01 Adoptar | J31: 01 Baja | L31: =+(VLOOKUP($A31,S0!$C$2:$Y$89,18)/8 * VLOOKUP($I31,Atributos!$A$28:$B$31,2) * VLOOKUP($J31,Atributos!$A$22:$B$25,2))/5 -> 0.0375 | M31: =+(VLOOKUP($A31,S0!$C$2:$Y$89,19)/8 * VLOOKUP($I31,Atributos!$A$28:$B54,2) * VLOOKUP($J31,Atributos!$A$22:$B48,2))/5 -> 0.1 | N31: =+VLOOKUP($A31,S0!$C$2:$Y$89,20)/8 * VLOOKUP($I31,Atributos!$A$28:$B$31,2) * VLOOKUP($J31,Atributos!$A$22:$B$25,2)/5 -> 0.6 | O31: =+VLOOKUP($A31,S0!$C$2:$Y$89,21)/8 * VLOOKUP($I31,Atributos!$A$28:$B$31,2) * VLOOKUP($J31,Atributos!$A$22:$B$25,2)/5 -> 1.2 | P31: =+VLOOKUP($A31,S0!$C$2:$Y$89,22)/8 * VLOOKUP($I31,Atributos!$A$28:$B$31,2) * VLOOKUP($J31,Atributos!$A$22:$B$25,2)/5 -> 0.3 | Q31: =+VLOOKUP($A31,S0!$C$2:$Y$89,23)/8 * VLOOKUP($I31,Atributos!$A$28:$B$31,2) * VLOOKUP($J31,Atributos!$A$22:$B$25,2)/5 -> 0.3 | R31: =SUM(M31:P31) -> 2.2 | S31: =+(VLOOKUP($A31,S0!$C$2:$Y$89,19)/8 * VLOOKUP($I31,Atributos!$A$28:$B$31,2) * VLOOKUP($J31,Atributos!$G$22:$H$25,2))/5 -> 0.05 | T31: =+VLOOKUP($A31,S0!$C$2:$Y$89,20)/8 * VLOOKUP($I31,Atributos!$A$28:$B$31,2) * VLOOKUP($J31,Atributos!$G$22:$H$25,2)/5 -> 0.4 | U31: =+VLOOKUP($A31,S0!$C$2:$Y$89,21)/8 * VLOOKUP($I31,Atributos!$A$28:$B$31,2) * VLOOKUP($J31,Atributos!$G$22:$H$25,2)/5 -> 0.8 | V31: =+VLOOKUP($A31,S0!$C$2:$Y$89,22)/8 * VLOOKUP($I31,Atributos!$A$28:$B$31,2) * VLOOKUP($J31,Atributos!$G$22:$H$25,2)/5 -> 0.2 | W31: =+VLOOKUP($A31,S0!$C$2:$Y$89,23)/8 * VLOOKUP($I31,Atributos!$A$28:$B$31,2) * VLOOKUP($J31,Atributos!$G$22:$H$25,2)/5 -> 0.2 | X31: =SUM(S31:V31) -> 1.45 | Y31: =(S31+M31)/2 -> 0.075 | Z31: =(T31+N31)/2 -> 0.5 | AA31: =(U31+O31)/2 -> 1 | AB31: =(V31+P31)/2 -> 0.25 | AC31: =(W31+Q31)/2 -> 0.25 | AD31: =SUM(Y31:AB31) -> 1.825
A32: FI-10_Gestión de Activos Fijos(FI_P050) | B32: =+VLOOKUP(A32,S0!$C$2:$I$89,7) -> FI | C32: J62 | D32: Asset Accounting | E32: =+VLOOKUP(A32,S0!$C$2:$I$89,3) -> Alta de Activos Fijos - Por Compra directa - Por Adquisición bajo arrendamiento financiero. - Por liquidación de obra en curso Traslados Baja de Activos Fijos - Por venta - Por desguace Activos mantenidos para la venta Revaluación y Desvalorización Depreciación Operaciones de Cierre Anual Reportes | F32: =+VLOOKUP(A32,S0!$C$2:$I$89,4) -> Este proceso comprende las diferentes operaciones contables que se registran sobre los activos fijos. Así mismo, abarca la reportería para el análisis contable de los activos fijos. | G32: =+VLOOKUP(A32,S0!$C$2:$I$89,5) -> 1) Alta de Activos por Compras o Liquidaciones de Activos en Curso. 2) Alta de Activos por Arrendamiento Financiero desde FI. 3) Traspasos de Activos 4) Bajas de Activos: Baja por Desguace / Baja por Venta 5) Revaluaciones de Activos Fijos 6) Ejecución de las Depreciaciones 7) Cambio de Ejercicio y Cierre de Ejercicio de Activos Fijos | H32: =+VLOOKUP(A32,S0!$C$2:$I$89,6) -> 0 | I32: 02 Ajustar | J32: 02 Media | K32: GEstión de los activos fijos en curso en Campo. | L32: =+(VLOOKUP($A32,S0!$C$2:$Y$89,18)/8 * VLOOKUP($I32,Atributos!$A$28:$B$31,2) * VLOOKUP($J32,Atributos!$A$22:$B$25,2))/5 -> 0.084375 | M32: =+(VLOOKUP($A32,S0!$C$2:$Y$89,19)/8 * VLOOKUP($I32,Atributos!$A$28:$B55,2) * VLOOKUP($J32,Atributos!$A$22:$B49,2))/5 -> 0.45 | N32: =+VLOOKUP($A32,S0!$C$2:$Y$89,20)/8 * VLOOKUP($I32,Atributos!$A$28:$B$31,2) * VLOOKUP($J32,Atributos!$A$22:$B$25,2)/5 -> 1.35 | O32: =+VLOOKUP($A32,S0!$C$2:$Y$89,21)/8 * VLOOKUP($I32,Atributos!$A$28:$B$31,2) * VLOOKUP($J32,Atributos!$A$22:$B$25,2)/5 -> 2.7 | P32: =+VLOOKUP($A32,S0!$C$2:$Y$89,22)/8 * VLOOKUP($I32,Atributos!$A$28:$B$31,2) * VLOOKUP($J32,Atributos!$A$22:$B$25,2)/5 -> 0.675 | Q32: =+VLOOKUP($A32,S0!$C$2:$Y$89,23)/8 * VLOOKUP($I32,Atributos!$A$28:$B$31,2) * VLOOKUP($J32,Atributos!$A$22:$B$25,2)/5 -> 0.675 | R32: =SUM(M32:P32) -> 5.175 | S32: =+(VLOOKUP($A32,S0!$C$2:$Y$89,19)/8 * VLOOKUP($I32,Atributos!$A$28:$B$31,2) * VLOOKUP($J32,Atributos!$G$22:$H$25,2))/5 -> 0.1125 | T32: =+VLOOKUP($A32,S0!$C$2:$Y$89,20)/8 * VLOOKUP($I32,Atributos!$A$28:$B$31,2) * VLOOKUP($J32,Atributos!$G$22:$H$25,2)/5 -> 0.9 | U32: =+VLOOKUP($A32,S0!$C$2:$Y$89,21)/8 * VLOOKUP($I32,Atributos!$A$28:$B$31,2) * VLOOKUP($J32,Atributos!$G$22:$H$25,2)/5 -> 1.8 | V32: =+VLOOKUP($A32,S0!$C$2:$Y$89,22)/8 * VLOOKUP($I32,Atributos!$A$28:$B$31,2) * VLOOKUP($J32,Atributos!$G$22:$H$25,2)/5 -> 0.45 | W32: =+VLOOKUP($A32,S0!$C$2:$Y$89,23)/8 * VLOOKUP($I32,Atributos!$A$28:$B$31,2) * VLOOKUP($J32,Atributos!$G$22:$H$25,2)/5 -> 0.45 | X32: =SUM(S32:V32) -> 3.2625 | Y32: =(S32+M32)/2 -> 0.28125 | Z32: =(T32+N32)/2 -> 1.125 | AA32: =(U32+O32)/2 -> 2.25 | AB32: =(V32+P32)/2 -> 0.5625 | AC32: =(W32+Q32)/2 -> 0.5625 | AD32: =SUM(Y32:AB32) -> 4.21875
A33: FI-11_Cierre Contable(FI_P100) | B33: =+VLOOKUP(A33,S0!$C$2:$I$89,7) -> FI | C33: J58 | D33: Accounting and Financial Close | E33: =+VLOOKUP(A33,S0!$C$2:$I$89,3) -> Proceso de Cierre de Mes - Registro de documentos - Apertura y Cierre de Períodos contables - Desplazamiento de periodo logístico - Anulación de documentos FI - Análisis y Compensación de cuentas - Conciliación bancaria - Valoración de Moneda Extranjera - Traslación - Liquidación de AFeC - Depreciación/Amortización de activos fijos o intangibles Proceso de Cierre de Año - Arrastre de Saldos Anual - Cierre de ejercicio de Activos Fijos Estados Financieros y libros oficiales Reportes | F33: =+VLOOKUP(A33,S0!$C$2:$I$89,4) -> Este proceso se encuentra constituido por las actividades que permiten cerrar las operaciones necesarias del día, mes y del ejercicio. Para ello, el sistema ofrece un conjunto de programas que permiten ejecutar los procesos de cierre y hacer análisis a través reportes de resultados y de cuentas balance. | G33: =+VLOOKUP(A33,S0!$C$2:$I$89,5) -> 1) Apertura y Cierre periodos contables( Variante de Ejercicio FI) 2) Desplazamiento de Periodo Logistico. 3) Compensaciones Manuales o Automaticas de Cuentas de Mayor 4) Conciliación Banacaria ( Localización ) 5) Valoración de Moneda Extranjera ( Ejemplo: USD a PEN ) 6) Traslasión Moneda Local ( Ejemplo PEN a USD ) 7) Liquidación de Activos FIjo en Curso 8) Ejecución de la Depreciaión del mes correspondiente. 9) Arrastre de Saldos que incluye la apertura del nuevo ejercicio para Activos Fijos. 10) Cierre de Ejercicio de Activos Fijos 11) Reporteria Balance General o Report Painters 12) Libros Electrónicos SUNAT ( Localización Z) | H33: =+VLOOKUP(A33,S0!$C$2:$I$89,6) -> 0 | I33: 01 Adoptar | J33: 01 Baja | L33: =+(VLOOKUP($A33,S0!$C$2:$Y$89,18)/8 * VLOOKUP($I33,Atributos!$A$28:$B$31,2) * VLOOKUP($J33,Atributos!$A$22:$B$25,2))/5 -> 0.0375 | M33: =+(VLOOKUP($A33,S0!$C$2:$Y$89,19)/8 * VLOOKUP($I33,Atributos!$A$28:$B56,2) * VLOOKUP($J33,Atributos!$A$22:$B50,2))/5 -> 0.2 | N33: =+VLOOKUP($A33,S0!$C$2:$Y$89,20)/8 * VLOOKUP($I33,Atributos!$A$28:$B$31,2) * VLOOKUP($J33,Atributos!$A$22:$B$25,2)/5 -> 0.6 | O33: =+VLOOKUP($A33,S0!$C$2:$Y$89,21)/8 * VLOOKUP($I33,Atributos!$A$28:$B$31,2) * VLOOKUP($J33,Atributos!$A$22:$B$25,2)/5 -> 1.2 | P33: =+VLOOKUP($A33,S0!$C$2:$Y$89,22)/8 * VLOOKUP($I33,Atributos!$A$28:$B$31,2) * VLOOKUP($J33,Atributos!$A$22:$B$25,2)/5 -> 0.3 | Q33: =+VLOOKUP($A33,S0!$C$2:$Y$89,23)/8 * VLOOKUP($I33,Atributos!$A$28:$B$31,2) * VLOOKUP($J33,Atributos!$A$22:$B$25,2)/5 -> 0.3 | R33: =SUM(M33:P33) -> 2.3 | S33: =+(VLOOKUP($A33,S0!$C$2:$Y$89,19)/8 * VLOOKUP($I33,Atributos!$A$28:$B$31,2) * VLOOKUP($J33,Atributos!$G$22:$H$25,2))/5 -> 0.05 | T33: =+VLOOKUP($A33,S0!$C$2:$Y$89,20)/8 * VLOOKUP($I33,Atributos!$A$28:$B$31,2) * VLOOKUP($J33,Atributos!$G$22:$H$25,2)/5 -> 0.4 | U33: =+VLOOKUP($A33,S0!$C$2:$Y$89,21)/8 * VLOOKUP($I33,Atributos!$A$28:$B$31,2) * VLOOKUP($J33,Atributos!$G$22:$H$25,2)/5 -> 0.8 | V33: =+VLOOKUP($A33,S0!$C$2:$Y$89,22)/8 * VLOOKUP($I33,Atributos!$A$28:$B$31,2) * VLOOKUP($J33,Atributos!$G$22:$H$25,2)/5 -> 0.2 | W33: =+VLOOKUP($A33,S0!$C$2:$Y$89,23)/8 * VLOOKUP($I33,Atributos!$A$28:$B$31,2) * VLOOKUP($J33,Atributos!$G$22:$H$25,2)/5 -> 0.2 | X33: =SUM(S33:V33) -> 1.45 | Y33: =(S33+M33)/2 -> 0.125 | Z33: =(T33+N33)/2 -> 0.5 | AA33: =(U33+O33)/2 -> 1 | AB33: =(V33+P33)/2 -> 0.25 | AC33: =(W33+Q33)/2 -> 0.25 | AD33: =SUM(Y33:AB33) -> 1.875
